Workbook

Sheet Giving Pyramid
B2: Giving Pyramid — Individual Gifts
B4: Fiscal Year (Jul–Jun): | C4: 2025
B5: Period: | C5: =DATE(C4-1,7,1) -> 45474 | D5: ="to "&TEXT(DATE(C4,6,30),"mmm d, yyyy") -> to Jun 30, 2025
B7: Gift Range | C7: Low | D7: High | E7: # of Gifts | F7: Total $ | G7: Avg Gift | H7: % of Gifts | I7: % of Total $
B8: $25,000 + | C8: 25000 | D8: 100000000 | E8: =COUNTIFS('AHCF_Gifts_19952026 (1)'!$D:$D,">="&$C$5,'AHCF_Gifts_19952026 (1)'!$D:$D,"<="&DATE($C$4,6,30),'AHCF_Gifts_19952026 (1)'!$E:$E,">="&$C8,'AHCF_Gifts_19952026 (1)'!$E:$E,"<="&$D8) -> 9 | F8: =SUMIFS('AHCF_Gifts_19952026 (1)'!$E:$E,'AHCF_Gifts_19952026 (1)'!$D:$D,">="&$C$5,'AHCF_Gifts_19952026 (1)'!$D:$D,"<="&DATE($C$4,6,30),'AHCF_Gifts_19952026 (1)'!$E:$E,">="&$C8,'AHCF_Gifts_19952026 (1)'!$E:$E,"<="&$D8) -> 362090 | G8: =IF(E8=0,0,F8/E8) -> 40232.222 | H8: =IF($E$17=0,0,E8/$E$17) -> 0.0038643195 | I8: =IF($F$17=0,0,F8/$F$17) -> 0.23219441
B9: $10,000 – $24,999 | C9: 10000 | D9: 24999.99 | E9: =COUNTIFS('AHCF_Gifts_19952026 (1)'!$D:$D,">="&$C$5,'AHCF_Gifts_19952026 (1)'!$D:$D,"<="&DATE($C$4,6,30),'AHCF_Gifts_19952026 (1)'!$E:$E,">="&$C9,'AHCF_Gifts_19952026 (1)'!$E:$E,"<="&$D9) -> 33 | F9: =SUMIFS('AHCF_Gifts_19952026 (1)'!$E:$E,'AHCF_Gifts_19952026 (1)'!$D:$D,">="&$C$5,'AHCF_Gifts_19952026 (1)'!$D:$D,"<="&DATE($C$4,6,30),'AHCF_Gifts_19952026 (1)'!$E:$E,">="&$C9,'AHCF_Gifts_19952026 (1)'!$E:$E,"<="&$D9) -> 513208.59 | G9: =IF(E9=0,0,F9/E9) -> 15551.775 | H9: =IF($E$17=0,0,E9/$E$17) -> 0.014169171 | I9: =IF($F$17=0,0,F9/$F$17) -> 0.32910096
B10: $5,000 – $9,999 | C10: 5000 | D10: 9999.99 | E10: =COUNTIFS('AHCF_Gifts_19952026 (1)'!$D:$D,">="&$C$5,'AHCF_Gifts_19952026 (1)'!$D:$D,"<="&DATE($C$4,6,30),'AHCF_Gifts_19952026 (1)'!$E:$E,">="&$C10,'AHCF_Gifts_19952026 (1)'!$E:$E,"<="&$D10) -> 39 | F10: =SUMIFS('AHCF_Gifts_19952026 (1)'!$E:$E,'AHCF_Gifts_19952026 (1)'!$D:$D,">="&$C$5,'AHCF_Gifts_19952026 (1)'!$D:$D,"<="&DATE($C$4,6,30),'AHCF_Gifts_19952026 (1)'!$E:$E,">="&$C10,'AHCF_Gifts_19952026 (1)'!$E:$E,"<="&$D10) -> 213695.98 | G10: =IF(E10=0,0,F10/E10) -> 5479.3841 | H10: =IF($E$17=0,0,E10/$E$17) -> 0.016745384 | I10: =IF($F$17=0,0,F10/$F$17) -> 0.13703503
B11: $2,500 – $4,999 | C11: 2500 | D11: 4999.99 | E11: =COUNTIFS('AHCF_Gifts_19952026 (1)'!$D:$D,">="&$C$5,'AHCF_Gifts_19952026 (1)'!$D:$D,"<="&DATE($C$4,6,30),'AHCF_Gifts_19952026 (1)'!$E:$E,">="&$C11,'AHCF_Gifts_19952026 (1)'!$E:$E,"<="&$D11) -> 34 | F11: =SUMIFS('AHCF_Gifts_19952026 (1)'!$E:$E,'AHCF_Gifts_19952026 (1)'!$D:$D,">="&$C$5,'AHCF_Gifts_19952026 (1)'!$D:$D,"<="&DATE($C$4,6,30),'AHCF_Gifts_19952026 (1)'!$E:$E,">="&$C11,'AHCF_Gifts_19952026 (1)'!$E:$E,"<="&$D11) -> 99000 | G11: =IF(E11=0,0,F11/E11) -> 2911.7647 | H11: =IF($E$17=0,0,E11/$E$17) -> 0.01459854 | I11: =IF($F$17=0,0,F11/$F$17) -> 0.063484898
B12: $1,000 – $2,499 | C12: 1000 | D12: 2499.99 | E12: =COUNTIFS('AHCF_Gifts_19952026 (1)'!$D:$D,">="&$C$5,'AHCF_Gifts_19952026 (1)'!$D:$D,"<="&DATE($C$4,6,30),'AHCF_Gifts_19952026 (1)'!$E:$E,">="&$C12,'AHCF_Gifts_19952026 (1)'!$E:$E,"<="&$D12) -> 142 | F12: =SUMIFS('AHCF_Gifts_19952026 (1)'!$E:$E,'AHCF_Gifts_19952026 (1)'!$D:$D,">="&$C$5,'AHCF_Gifts_19952026 (1)'!$D:$D,"<="&DATE($C$4,6,30),'AHCF_Gifts_19952026 (1)'!$E:$E,">="&$C12,'AHCF_Gifts_19952026 (1)'!$E:$E,"<="&$D12) -> 185454.69 | G12: =IF(E12=0,0,F12/E12) -> 1306.0189 | H12: =IF($E$17=0,0,E12/$E$17) -> 0.060970374 | I12: =IF($F$17=0,0,F12/$F$17) -> 0.11892497
B13: $500 – $999 | C13: 500 | D13: 999.99 | E13: =COUNTIFS('AHCF_Gifts_19952026 (1)'!$D:$D,">="&$C$5,'AHCF_Gifts_19952026 (1)'!$D:$D,"<="&DATE($C$4,6,30),'AHCF_Gifts_19952026 (1)'!$E:$E,">="&$C13,'AHCF_Gifts_19952026 (1)'!$E:$E,"<="&$D13) -> 106 | F13: =SUMIFS('AHCF_Gifts_19952026 (1)'!$E:$E,'AHCF_Gifts_19952026 (1)'!$D:$D,">="&$C$5,'AHCF_Gifts_19952026 (1)'!$D:$D,"<="&DATE($C$4,6,30),'AHCF_Gifts_19952026 (1)'!$E:$E,">="&$C13,'AHCF_Gifts_19952026 (1)'!$E:$E,"<="&$D13) -> 60706.54 | G13: =IF(E13=0,0,F13/E13) -> 572.70321 | H13: =IF($E$17=0,0,E13/$E$17) -> 0.045513096 | I13: =IF($F$17=0,0,F13/$F$17) -> 0.038928773
B14: $250 – $499 | C14: 250 | D14: 499.99 | E14: =COUNTIFS('AHCF_Gifts_19952026 (1)'!$D:$D,">="&$C$5,'AHCF_Gifts_19952026 (1)'!$D:$D,"<="&DATE($C$4,6,30),'AHCF_Gifts_19952026 (1)'!$E:$E,">="&$C14,'AHCF_Gifts_19952026 (1)'!$E:$E,"<="&$D14) -> 95 | F14: =SUMIFS('AHCF_Gifts_19952026 (1)'!$E:$E,'AHCF_Gifts_19952026 (1)'!$D:$D,">="&$C$5,'AHCF_Gifts_19952026 (1)'!$D:$D,"<="&DATE($C$4,6,30),'AHCF_Gifts_19952026 (1)'!$E:$E,">="&$C14,'AHCF_Gifts_19952026 (1)'!$E:$E,"<="&$D14) -> 30724.38 | G14: =IF(E14=0,0,F14/E14) -> 323.41453 | H14: =IF($E$17=0,0,E14/$E$17) -> 0.040790039 | I14: =IF($F$17=0,0,F14/$F$17) -> 0.019702365
B15: $100 – $249 | C15: 100 | D15: 249.99 | E15: =COUNTIFS('AHCF_Gifts_19952026 (1)'!$D:$D,">="&$C$5,'AHCF_Gifts_19952026 (1)'!$D:$D,"<="&DATE($C$4,6,30),'AHCF_Gifts_19952026 (1)'!$E:$E,">="&$C15,'AHCF_Gifts_19952026 (1)'!$E:$E,"<="&$D15) -> 331 | F15: =SUMIFS('AHCF_Gifts_19952026 (1)'!$E:$E,'AHCF_Gifts_19952026 (1)'!$D:$D,">="&$C$5,'AHCF_Gifts_19952026 (1)'!$D:$D,"<="&DATE($C$4,6,30),'AHCF_Gifts_19952026 (1)'!$E:$E,">="&$C15,'AHCF_Gifts_19952026 (1)'!$E:$E,"<="&$D15) -> 40733.32 | G15: =IF(E15=0,0,F15/E15) -> 123.06139 | H15: =IF($E$17=0,0,E15/$E$17) -> 0.14212108 | I15: =IF($F$17=0,0,F15/$F$17) -> 0.026120714
B16: Under $100 | C16: 0.01 | D16: 99.99 | E16: =COUNTIFS('AHCF_Gifts_19952026 (1)'!$D:$D,">="&$C$5,'AHCF_Gifts_19952026 (1)'!$D:$D,"<="&DATE($C$4,6,30),'AHCF_Gifts_19952026 (1)'!$E:$E,">="&$C16,'AHCF_Gifts_19952026 (1)'!$E:$E,"<="&$D16) -> 1540 | F16: =SUMIFS('AHCF_Gifts_19952026 (1)'!$E:$E,'AHCF_Gifts_19952026 (1)'!$D:$D,">="&$C$5,'AHCF_Gifts_19952026 (1)'!$D:$D,"<="&DATE($C$4,6,30),'AHCF_Gifts_19952026 (1)'!$E:$E,">="&$C16,'AHCF_Gifts_19952026 (1)'!$E:$E,"<="&$D16) -> 53812.48 | G16: =IF(E16=0,0,F16/E16) -> 34.943169 | H16: =IF($E$17=0,0,E16/$E$17) -> 0.66122799 | I16: =IF($F$17=0,0,F16/$F$17) -> 0.034507877
B17: Total | E17: =SUM(E8:E16) -> 2329 | F17: =SUM(F8:F16) -> 1559426 | G17: =IF(E17=0,0,F17/E17) -> 669.56891 | H17: =SUM(H8:H16) -> 1 | I17: =SUM(I8:I16) -> 1
B19: Chart source (updates with FY)
B20: Year-over-Year Performance (all fiscal years)
B21: Fiscal Year | C21: Total $ | D21: # of Gifts
B22: 2011 | C22: =SUMIFS('AHCF_Gifts_19952026 (1)'!$E:$E,'AHCF_Gifts_19952026 (1)'!$D:$D,">="&DATE($B22-1,7,1),'AHCF_Gifts_19952026 (1)'!$D:$D,"<="&DATE($B22,6,30)) -> 856703.38 | D22: =COUNTIFS('AHCF_Gifts_19952026 (1)'!$D:$D,">="&DATE($B22-1,7,1),'AHCF_Gifts_19952026 (1)'!$D:$D,"<="&DATE($B22,6,30)) -> 1688 | N22: ="FY"&B22 -> FY2011
B23: =B22+1 -> 2012 | C23: =SUMIFS('AHCF_Gifts_19952026 (1)'!$E:$E,'AHCF_Gifts_19952026 (1)'!$D:$D,">="&DATE($B23-1,7,1),'AHCF_Gifts_19952026 (1)'!$D:$D,"<="&DATE($B23,6,30)) -> 820822.16 | D23: =COUNTIFS('AHCF_Gifts_19952026 (1)'!$D:$D,">="&DATE($B23-1,7,1),'AHCF_Gifts_19952026 (1)'!$D:$D,"<="&DATE($B23,6,30)) -> 1631 | N23: ="FY"&B23 -> FY2012
B24: =B23+1 -> 2013 | C24: =SUMIFS('AHCF_Gifts_19952026 (1)'!$E:$E,'AHCF_Gifts_19952026 (1)'!$D:$D,">="&DATE($B24-1,7,1),'AHCF_Gifts_19952026 (1)'!$D:$D,"<="&DATE($B24,6,30)) -> 11730012 | D24: =COUNTIFS('AHCF_Gifts_19952026 (1)'!$D:$D,">="&DATE($B24-1,7,1),'AHCF_Gifts_19952026 (1)'!$D:$D,"<="&DATE($B24,6,30)) -> 1571 | N24: ="FY"&B24 -> FY2013
B25: =B24+1 -> 2014 | C25: =SUMIFS('AHCF_Gifts_19952026 (1)'!$E:$E,'AHCF_Gifts_19952026 (1)'!$D:$D,">="&DATE($B25-1,7,1),'AHCF_Gifts_19952026 (1)'!$D:$D,"<="&DATE($B25,6,30)) -> 4260256.7 | D25: =COUNTIFS('AHCF_Gifts_19952026 (1)'!$D:$D,">="&DATE($B25-1,7,1),'AHCF_Gifts_19952026 (1)'!$D:$D,"<="&DATE($B25,6,30)) -> 1525 | N25: ="FY"&B25 -> FY2014
B26: =B25+1 -> 2015 | C26: =SUMIFS('AHCF_Gifts_19952026 (1)'!$E:$E,'AHCF_Gifts_19952026 (1)'!$D:$D,">="&DATE($B26-1,7,1),'AHCF_Gifts_19952026 (1)'!$D:$D,"<="&DATE($B26,6,30)) -> 1408187.6 | D26: =COUNTIFS('AHCF_Gifts_19952026 (1)'!$D:$D,">="&DATE($B26-1,7,1),'AHCF_Gifts_19952026 (1)'!$D:$D,"<="&DATE($B26,6,30)) -> 2125 | K26: Tier | L26: # of Gifts | N26: ="FY"&B26 -> FY2015
B27: =B26+1 -> 2016 | C27: =SUMIFS('AHCF_Gifts_19952026 (1)'!$E:$E,'AHCF_Gifts_19952026 (1)'!$D:$D,">="&DATE($B27-1,7,1),'AHCF_Gifts_19952026 (1)'!$D:$D,"<="&DATE($B27,6,30)) -> 1752133.7 | D27: =COUNTIFS('AHCF_Gifts_19952026 (1)'!$D:$D,">="&DATE($B27-1,7,1),'AHCF_Gifts_19952026 (1)'!$D:$D,"<="&DATE($B27,6,30)) -> 2132 | K27: =B8 -> $25,000 + | L27: =E8 -> 9 | N27: ="FY"&B27 -> FY2016
B28: =B27+1 -> 2017 | C28: =SUMIFS('AHCF_Gifts_19952026 (1)'!$E:$E,'AHCF_Gifts_19952026 (1)'!$D:$D,">="&DATE($B28-1,7,1),'AHCF_Gifts_19952026 (1)'!$D:$D,"<="&DATE($B28,6,30)) -> 1228110.1 | D28: =COUNTIFS('AHCF_Gifts_19952026 (1)'!$D:$D,">="&DATE($B28-1,7,1),'AHCF_Gifts_19952026 (1)'!$D:$D,"<="&DATE($B28,6,30)) -> 1933 | K28: =B9 -> $10,000 – $24,999 | L28: =E9 -> 33 | N28: ="FY"&B28 -> FY2017
B29: =B28+1 -> 2018 | C29: =SUMIFS('AHCF_Gifts_19952026 (1)'!$E:$E,'AHCF_Gifts_19952026 (1)'!$D:$D,">="&DATE($B29-1,7,1),'AHCF_Gifts_19952026 (1)'!$D:$D,"<="&DATE($B29,6,30)) -> 3878534.5 | D29: =COUNTIFS('AHCF_Gifts_19952026 (1)'!$D:$D,">="&DATE($B29-1,7,1),'AHCF_Gifts_19952026 (1)'!$D:$D,"<="&DATE($B29,6,30)) -> 2101 | K29: =B10 -> $5,000 – $9,999 | L29: =E10 -> 39 | N29: ="FY"&B29 -> FY2018
B30: =B29+1 -> 2019 | C30: =SUMIFS('AHCF_Gifts_19952026 (1)'!$E:$E,'AHCF_Gifts_19952026 (1)'!$D:$D,">="&DATE($B30-1,7,1),'AHCF_Gifts_19952026 (1)'!$D:$D,"<="&DATE($B30,6,30)) -> 2136157 | D30: =COUNTIFS('AHCF_Gifts_19952026 (1)'!$D:$D,">="&DATE($B30-1,7,1),'AHCF_Gifts_19952026 (1)'!$D:$D,"<="&DATE($B30,6,30)) -> 2176 | K30: =B11 -> $2,500 – $4,999 | L30: =E11 -> 34 | N30: ="FY"&B30 -> FY2019
B31: =B30+1 -> 2020 | C31: =SUMIFS('AHCF_Gifts_19952026 (1)'!$E:$E,'AHCF_Gifts_19952026 (1)'!$D:$D,">="&DATE($B31-1,7,1),'AHCF_Gifts_19952026 (1)'!$D:$D,"<="&DATE($B31,6,30)) -> 3808669.7 | D31: =COUNTIFS('AHCF_Gifts_19952026 (1)'!$D:$D,">="&DATE($B31-1,7,1),'AHCF_Gifts_19952026 (1)'!$D:$D,"<="&DATE($B31,6,30)) -> 2286 | K31: =B12 -> $1,000 – $2,499 | L31: =E12 -> 142 | N31: ="FY"&B31 -> FY2020
B32: =B31+1 -> 2021 | C32: =SUMIFS('AHCF_Gifts_19952026 (1)'!$E:$E,'AHCF_Gifts_19952026 (1)'!$D:$D,">="&DATE($B32-1,7,1),'AHCF_Gifts_19952026 (1)'!$D:$D,"<="&DATE($B32,6,30)) -> 2847023.3 | D32: =COUNTIFS('AHCF_Gifts_19952026 (1)'!$D:$D,">="&DATE($B32-1,7,1),'AHCF_Gifts_19952026 (1)'!$D:$D,"<="&DATE($B32,6,30)) -> 2988 | K32: =B13 -> $500 – $999 | L32: =E13 -> 106 | N32: ="FY"&B32 -> FY2021
B33: =B32+1 -> 2022 | C33: =SUMIFS('AHCF_Gifts_19952026 (1)'!$E:$E,'AHCF_Gifts_19952026 (1)'!$D:$D,">="&DATE($B33-1,7,1),'AHCF_Gifts_19952026 (1)'!$D:$D,"<="&DATE($B33,6,30)) -> 2443105.9 | D33: =COUNTIFS('AHCF_Gifts_19952026 (1)'!$D:$D,">="&DATE($B33-1,7,1),'AHCF_Gifts_19952026 (1)'!$D:$D,"<="&DATE($B33,6,30)) -> 2826 | K33: =B14 -> $250 – $499 | L33: =E14 -> 95 | N33: ="FY"&B33 -> FY2022
B34: =B33+1 -> 2023 | C34: =SUMIFS('AHCF_Gifts_19952026 (1)'!$E:$E,'AHCF_Gifts_19952026 (1)'!$D:$D,">="&DATE($B34-1,7,1),'AHCF_Gifts_19952026 (1)'!$D:$D,"<="&DATE($B34,6,30)) -> 1360029.8 | D34: =COUNTIFS('AHCF_Gifts_19952026 (1)'!$D:$D,">="&DATE($B34-1,7,1),'AHCF_Gifts_19952026 (1)'!$D:$D,"<="&DATE($B34,6,30)) -> 2708 | K34: =B15 -> $100 – $249 | L34: =E15 -> 331 | N34: ="FY"&B34 -> FY2023
B35: =B34+1 -> 2024 | C35: =SUMIFS('AHCF_Gifts_19952026 (1)'!$E:$E,'AHCF_Gifts_19952026 (1)'!$D:$D,">="&DATE($B35-1,7,1),'AHCF_Gifts_19952026 (1)'!$D:$D,"<="&DATE($B35,6,30)) -> 3169714.5 | D35: =COUNTIFS('AHCF_Gifts_19952026 (1)'!$D:$D,">="&DATE($B35-1,7,1),'AHCF_Gifts_19952026 (1)'!$D:$D,"<="&DATE($B35,6,30)) -> 2465 | K35: =B16 -> Under $100 | L35: =E16 -> 1540 | N35: ="FY"&B35 -> FY2024
B36: =B35+1 -> 2025 | C36: =SUMIFS('AHCF_Gifts_19952026 (1)'!$E:$E,'AHCF_Gifts_19952026 (1)'!$D:$D,">="&DATE($B36-1,7,1),'AHCF_Gifts_19952026 (1)'!$D:$D,"<="&DATE($B36,6,30)) -> 1559426 | D36: =COUNTIFS('AHCF_Gifts_19952026 (1)'!$D:$D,">="&DATE($B36-1,7,1),'AHCF_Gifts_19952026 (1)'!$D:$D,"<="&DATE($B36,6,30)) -> 2337 | N36: ="FY"&B36 -> FY2025
B37: =B36+1 -> 2026 | C37: =SUMIFS('AHCF_Gifts_19952026 (1)'!$E:$E,'AHCF_Gifts_19952026 (1)'!$D:$D,">="&DATE($B37-1,7,1),'AHCF_Gifts_19952026 (1)'!$D:$D,"<="&DATE($B37,6,30)) -> 1768709.3 | D37: =COUNTIFS('AHCF_Gifts_19952026 (1)'!$D:$D,">="&DATE($B37-1,7,1),'AHCF_Gifts_19952026 (1)'!$D:$D,"<="&DATE($B37,6,30)) -> 2373 | N37: ="FY"&B37 -> FY2026

Sheet Donor Retention
B2: Donor Retention
B3: Retention rate = share of the prior fiscal year's unique donors (by Constituent ID) who gave again the following year. Fiscal year = Jul–Jun.
B5: Fiscal Year | C5: Active Donors | D5: Prior-Yr Donors | E5: Retained Donors | F5: Retention Rate | G5: New / Reactivated
B6: 2011 | C6: =SUM(INDEX('Retention Calc'!$B$2:$Q$2698,0,MATCH($B6,'Retention Calc'!$B$1:$Q$1,0))) -> 337 | D6: =IFERROR(SUM(INDEX('Retention Calc'!$B$2:$Q$2698,0,MATCH($B6-1,'Retention Calc'!$B$1:$Q$1,0))),"") | E6: =IFERROR(SUMPRODUCT(INDEX('Retention Calc'!$B$2:$Q$2698,0,MATCH($B6,'Retention Calc'!$B$1:$Q$1,0)),INDEX('Retention Calc'!$B$2:$Q$2698,0,MATCH($B6-1,'Retention Calc'!$B$1:$Q$1,0))),"") | F6: =IFERROR(E6/D6,"") | G6: =IF(E6="",C6,C6-E6) -> 337 | T6: ="FY"&B6 -> FY2011
B7: =B6+1 -> 2012 | C7: =SUM(INDEX('Retention Calc'!$B$2:$Q$2698,0,MATCH($B7,'Retention Calc'!$B$1:$Q$1,0))) -> 340 | D7: =IFERROR(SUM(INDEX('Retention Calc'!$B$2:$Q$2698,0,MATCH($B7-1,'Retention Calc'!$B$1:$Q$1,0))),"") -> 337 | E7: =IFERROR(SUMPRODUCT(INDEX('Retention Calc'!$B$2:$Q$2698,0,MATCH($B7,'Retention Calc'!$B$1:$Q$1,0)),INDEX('Retention Calc'!$B$2:$Q$2698,0,MATCH($B7-1,'Retention Calc'!$B$1:$Q$1,0))),"") -> 176 | F7: =IFERROR(E7/D7,"") -> 0.52225519 | G7: =IF(E7="",C7,C7-E7) -> 164 | T7: ="FY"&B7 -> FY2012
B8: =B7+1 -> 2013 | C8: =SUM(INDEX('Retention Calc'!$B$2:$Q$2698,0,MATCH($B8,'Retention Calc'!$B$1:$Q$1,0))) -> 357 | D8: =IFERROR(SUM(INDEX('Retention Calc'!$B$2:$Q$2698,0,MATCH($B8-1,'Retention Calc'!$B$1:$Q$1,0))),"") -> 340 | E8: =IFERROR(SUMPRODUCT(INDEX('Retention Calc'!$B$2:$Q$2698,0,MATCH($B8,'Retention Calc'!$B$1:$Q$1,0)),INDEX('Retention Calc'!$B$2:$Q$2698,0,MATCH($B8-1,'Retention Calc'!$B$1:$Q$1,0))),"") -> 193 | F8: =IFERROR(E8/D8,"") -> 0.56764706 | G8: =IF(E8="",C8,C8-E8) -> 164 | T8: ="FY"&B8 -> FY2013
B9: =B8+1 -> 2014 | C9: =SUM(INDEX('Retention Calc'!$B$2:$Q$2698,0,MATCH($B9,'Retention Calc'!$B$1:$Q$1,0))) -> 365 | D9: =IFERROR(SUM(INDEX('Retention Calc'!$B$2:$Q$2698,0,MATCH($B9-1,'Retention Calc'!$B$1:$Q$1,0))),"") -> 357 | E9: =IFERROR(SUMPRODUCT(INDEX('Retention Calc'!$B$2:$Q$2698,0,MATCH($B9,'Retention Calc'!$B$1:$Q$1,0)),INDEX('Retention Calc'!$B$2:$Q$2698,0,MATCH($B9-1,'Retention Calc'!$B$1:$Q$1,0))),"") -> 221 | F9: =IFERROR(E9/D9,"") -> 0.61904762 | G9: =IF(E9="",C9,C9-E9) -> 144 | T9: ="FY"&B9 -> FY2014
B10: =B9+1 -> 2015 | C10: =SUM(INDEX('Retention Calc'!$B$2:$Q$2698,0,MATCH($B10,'Retention Calc'!$B$1:$Q$1,0))) -> 440 | D10: =IFERROR(SUM(INDEX('Retention Calc'!$B$2:$Q$2698,0,MATCH($B10-1,'Retention Calc'!$B$1:$Q$1,0))),"") -> 365 | E10: =IFERROR(SUMPRODUCT(INDEX('Retention Calc'!$B$2:$Q$2698,0,MATCH($B10,'Retention Calc'!$B$1:$Q$1,0)),INDEX('Retention Calc'!$B$2:$Q$2698,0,MATCH($B10-1,'Retention Calc'!$B$1:$Q$1,0))),"") -> 239 | F10: =IFERROR(E10/D10,"") -> 0.65479452 | G10: =IF(E10="",C10,C10-E10) -> 201 | T10: ="FY"&B10 -> FY2015
B11: =B10+1 -> 2016 | C11: =SUM(INDEX('Retention Calc'!$B$2:$Q$2698,0,MATCH($B11,'Retention Calc'!$B$1:$Q$1,0))) -> 482 | D11: =IFERROR(SUM(INDEX('Retention Calc'!$B$2:$Q$2698,0,MATCH($B11-1,'Retention Calc'!$B$1:$Q$1,0))),"") -> 440 | E11: =IFERROR(SUMPRODUCT(INDEX('Retention Calc'!$B$2:$Q$2698,0,MATCH($B11,'Retention Calc'!$B$1:$Q$1,0)),INDEX('Retention Calc'!$B$2:$Q$2698,0,MATCH($B11-1,'Retention Calc'!$B$1:$Q$1,0))),"") -> 264 | F11: =IFERROR(E11/D11,"") -> 0.6 | G11: =IF(E11="",C11,C11-E11) -> 218 | T11: ="FY"&B11 -> FY2016
B12: =B11+1 -> 2017 | C12: =SUM(INDEX('Retention Calc'!$B$2:$Q$2698,0,MATCH($B12,'Retention Calc'!$B$1:$Q$1,0))) -> 521 | D12: =IFERROR(SUM(INDEX('Retention Calc'!$B$2:$Q$2698,0,MATCH($B12-1,'Retention Calc'!$B$1:$Q$1,0))),"") -> 482 | E12: =IFERROR(SUMPRODUCT(INDEX('Retention Calc'!$B$2:$Q$2698,0,MATCH($B12,'Retention Calc'!$B$1:$Q$1,0)),INDEX('Retention Calc'!$B$2:$Q$2698,0,MATCH($B12-1,'Retention Calc'!$B$1:$Q$1,0))),"") -> 263 | F12: =IFERROR(E12/D12,"") -> 0.54564315 | G12: =IF(E12="",C12,C12-E12) -> 258 | T12: ="FY"&B12 -> FY2017
B13: =B12+1 -> 2018 | C13: =SUM(INDEX('Retention Calc'!$B$2:$Q$2698,0,MATCH($B13,'Retention Calc'!$B$1:$Q$1,0))) -> 456 | D13: =IFERROR(SUM(INDEX('Retention Calc'!$B$2:$Q$2698,0,MATCH($B13-1,'Retention Calc'!$B$1:$Q$1,0))),"") -> 521 | E13: =IFERROR(SUMPRODUCT(INDEX('Retention Calc'!$B$2:$Q$2698,0,MATCH($B13,'Retention Calc'!$B$1:$Q$1,0)),INDEX('Retention Calc'!$B$2:$Q$2698,0,MATCH($B13-1,'Retention Calc'!$B$1:$Q$1,0))),"") -> 269 | F13: =IFERROR(E13/D13,"") -> 0.51631478 | G13: =IF(E13="",C13,C13-E13) -> 187 | T13: ="FY"&B13 -> FY2018
B14: =B13+1 -> 2019 | C14: =SUM(INDEX('Retention Calc'!$B$2:$Q$2698,0,MATCH($B14,'Retention Calc'!$B$1:$Q$1,0))) -> 439 | D14: =IFERROR(SUM(INDEX('Retention Calc'!$B$2:$Q$2698,0,MATCH($B14-1,'Retention Calc'!$B$1:$Q$1,0))),"") -> 456 | E14: =IFERROR(SUMPRODUCT(INDEX('Retention Calc'!$B$2:$Q$2698,0,MATCH($B14,'Retention Calc'!$B$1:$Q$1,0)),INDEX('Retention Calc'!$B$2:$Q$2698,0,MATCH($B14-1,'Retention Calc'!$B$1:$Q$1,0))),"") -> 259 | F14: =IFERROR(E14/D14,"") -> 0.56798246 | G14: =IF(E14="",C14,C14-E14) -> 180 | T14: ="FY"&B14 -> FY2019
B15: =B14+1 -> 2020 | C15: =SUM(INDEX('Retention Calc'!$B$2:$Q$2698,0,MATCH($B15,'Retention Calc'!$B$1:$Q$1,0))) -> 464 | D15: =IFERROR(SUM(INDEX('Retention Calc'!$B$2:$Q$2698,0,MATCH($B15-1,'Retention Calc'!$B$1:$Q$1,0))),"") -> 439 | E15: =IFERROR(SUMPRODUCT(INDEX('Retention Calc'!$B$2:$Q$2698,0,MATCH($B15,'Retention Calc'!$B$1:$Q$1,0)),INDEX('Retention Calc'!$B$2:$Q$2698,0,MATCH($B15-1,'Retention Calc'!$B$1:$Q$1,0))),"") -> 219 | F15: =IFERROR(E15/D15,"") -> 0.49886105 | G15: =IF(E15="",C15,C15-E15) -> 245 | T15: ="FY"&B15 -> FY2020
B16: =B15+1 -> 2021 | C16: =SUM(INDEX('Retention Calc'!$B$2:$Q$2698,0,MATCH($B16,'Retention Calc'!$B$1:$Q$1,0))) -> 546 | D16: =IFERROR(SUM(INDEX('Retention Calc'!$B$2:$Q$2698,0,MATCH($B16-1,'Retention Calc'!$B$1:$Q$1,0))),"") -> 464 | E16: =IFERROR(SUMPRODUCT(INDEX('Retention Calc'!$B$2:$Q$2698,0,MATCH($B16,'Retention Calc'!$B$1:$Q$1,0)),INDEX('Retention Calc'!$B$2:$Q$2698,0,MATCH($B16-1,'Retention Calc'!$B$1:$Q$1,0))),"") -> 262 | F16: =IFERROR(E16/D16,"") -> 0.56465517 | G16: =IF(E16="",C16,C16-E16) -> 284 | T16: ="FY"&B16 -> FY2021
B17: =B16+1 -> 2022 | C17: =SUM(INDEX('Retention Calc'!$B$2:$Q$2698,0,MATCH($B17,'Retention Calc'!$B$1:$Q$1,0))) -> 525 | D17: =IFERROR(SUM(INDEX('Retention Calc'!$B$2:$Q$2698,0,MATCH($B17-1,'Retention Calc'!$B$1:$Q$1,0))),"") -> 546 | E17: =IFERROR(SUMPRODUCT(INDEX('Retention Calc'!$B$2:$Q$2698,0,MATCH($B17,'Retention Calc'!$B$1:$Q$1,0)),INDEX('Retention Calc'!$B$2:$Q$2698,0,MATCH($B17-1,'Retention Calc'!$B$1:$Q$1,0))),"") -> 297 | F17: =IFERROR(E17/D17,"") -> 0.54395604 | G17: =IF(E17="",C17,C17-E17) -> 228 | T17: ="FY"&B17 -> FY2022
B18: =B17+1 -> 2023 | C18: =SUM(INDEX('Retention Calc'!$B$2:$Q$2698,0,MATCH($B18,'Retention Calc'!$B$1:$Q$1,0))) -> 537 | D18: =IFERROR(SUM(INDEX('Retention Calc'!$B$2:$Q$2698,0,MATCH($B18-1,'Retention Calc'!$B$1:$Q$1,0))),"") -> 525 | E18: =IFERROR(SUMPRODUCT(INDEX('Retention Calc'!$B$2:$Q$2698,0,MATCH($B18,'Retention Calc'!$B$1:$Q$1,0)),INDEX('Retention Calc'!$B$2:$Q$2698,0,MATCH($B18-1,'Retention Calc'!$B$1:$Q$1,0))),"") -> 304 | F18: =IFERROR(E18/D18,"") -> 0.57904762 | G18: =IF(E18="",C18,C18-E18) -> 233 | T18: ="FY"&B18 -> FY2023
... B21: =B20+1 -> 2026 | C21: =SUM(INDEX('Retention Calc'!$B$2:$Q$2698,0,MATCH($B21,'Retention Calc'!$B$1:$Q$1,0))) -> 546 | D21: =IFERROR(SUM(INDEX('Retention Calc'!$B$2:$Q$2698,0,MATCH($B21-1,'Retention Calc'!$B$1:$Q$1,0))),"") -> 535 | E21: =IFERROR(SUMPRODUCT(INDEX('Retention Calc'!$B$2:$Q$2698,0,MATCH($B21,'Retention Calc'!$B$1:$Q$1,0)),INDEX('Retention Calc'!$B$2:$Q$2698,0,MATCH($B21-1,'Retention Calc'!$B$1:$Q$1,0))),"") -> 296 | F21: =IFERROR(E21/D21,"") -> 0.55327103 | G21: =IF(E21="",C21,C21-E21) -> 250 | T21: ="FY"&B21 -> FY2026
B24: Cohort Retention — % of Acquisition Cohort Still Giving
B25: Donors grouped by fiscal year of their FIRST gift. Each cell = % of that cohort who gave in a later year. Year 0 = 100% by definition.
B26: Cohort | C26: Donors | D26: 0 | E26: 1 | F26: 2 | G26: 3 | H26: 4 | I26: 5 | J26: 6 | K26: 7 | L26: 8 | M26: 9 | N26: 10 | O26: 11 | P26: 12 | Q26: 13 | R26: 14 | S26: 15 | V26: Years since | W26: ="FY"&B27 -> FY2011 | X26: ="FY"&B28 -> FY2012 | Y26: ="FY"&B29 -> FY2013 | Z26: ="FY"&B30 -> FY2014 | AA26: ="FY"&B31 -> FY2015 | AB26: ="FY"&B32 -> FY2016 | AC26: ="FY"&B33 -> FY2017 | AD26: ="FY"&B34 -> FY2018 | AE26: ="FY"&B35 -> FY2019 | AF26: ="FY"&B36 -> FY2020 | AG26: ="FY"&B37 -> FY2021 | AH26: ="FY"&B38 -> FY2022 | AI26: ="FY"&B39 -> FY2023 | AJ26: ="FY"&B40 -> FY2024 | AK26: ="FY"&B41 -> FY2025 | AL26: ="FY"&B42 -> FY2026 | AM26: Blended
B27: 2011 | C27: =COUNTIF('Retention Calc'!$R$2:$R$2698,$B27) -> 337 | D27: {=IFERROR(IF($B27+D$26>2026,"",SUMPRODUCT(('Retention Calc'!$R$2:$R$2698=$B27)*INDEX('Retention Calc'!$B$2:$Q$2698,0,MATCH($B27+D$26,'Retention Calc'!$B$1:$Q$1,0)))/$C27),"")} -> 1 | E27: {=IFERROR(IF($B27+E$26>2026,"",SUMPRODUCT(('Retention Calc'!$R$2:$R$2698=$B27)*INDEX('Retention Calc'!$B$2:$Q$2698,0,MATCH($B27+E$26,'Retention Calc'!$B$1:$Q$1,0)))/$C27),"")} -> 0.52225519 | F27: {=IFERROR(IF($B27+F$26>2026,"",SUMPRODUCT(('Retention Calc'!$R$2:$R$2698=$B27)*INDEX('Retention Calc'!$B$2:$Q$2698,0,MATCH($B27+F$26,'Retention Calc'!$B$1:$Q$1,0)))/$C27),"")} -> 0.50148368 | G27: {=IFERROR(IF($B27+G$26>2026,"",SUMPRODUCT(('Retention Calc'!$R$2:$R$2698=$B27)*INDEX('Retention Calc'!$B$2:$Q$2698,0,MATCH($B27+G$26,'Retention Calc'!$B$1:$Q$1,0)))/$C27),"")} -> 0.45697329 | H27: {=IFERROR(IF($B27+H$26>2026,"",SUMPRODUCT(('Retention Calc'!$R$2:$R$2698=$B27)*INDEX('Retention Calc'!$B$2:$Q$2698,0,MATCH($B27+H$26,'Retention Calc'!$B$1:$Q$1,0)))/$C27),"")} -> 0.47477745 | I27: {=IFERROR(IF($B27+I$26>2026,"",SUMPRODUCT(('Retention Calc'!$R$2:$R$2698=$B27)*INDEX('Retention Calc'!$B$2:$Q$2698,0,MATCH($B27+I$26,'Retention Calc'!$B$1:$Q$1,0)))/$C27),"")} -> 0.44807122 | J27: {=IFERROR(IF($B27+J$26>2026,"",SUMPRODUCT(('Retention Calc'!$R$2:$R$2698=$B27)*INDEX('Retention Calc'!$B$2:$Q$2698,0,MATCH($B27+J$26,'Retention Calc'!$B$1:$Q$1,0)))/$C27),"")} -> 0.39762611 | K27: {=IFERROR(IF($B27+K$26>2026,"",SUMPRODUCT(('Retention Calc'!$R$2:$R$2698=$B27)*INDEX('Retention Calc'!$B$2:$Q$2698,0,MATCH($B27+K$26,'Retention Calc'!$B$1:$Q$1,0)))/$C27),"")} -> 0.38278932 | ... S27: {=IFERROR(IF($B27+S$26>2026,"",SUMPRODUCT(('Retention Calc'!$R$2:$R$2698=$B27)*INDEX('Retention Calc'!$B$2:$Q$2698,0,MATCH($B27+S$26,'Retention Calc'!$B$1:$Q$1,0)))/$C27),"")} -> 0.22255193 | V27: ="Year "&0 -> Year 0 | W27: =IF(D27="",NA(),D27) -> 1 | X27: =IF(D28="",NA(),D28) -> 1 | Y27: =IF(D29="",NA(),D29) -> 1 | Z27: =IF(D30="",NA(),D30) -> 1 | AA27: =IF(D31="",NA(),D31) -> 1 | AB27: =IF(D32="",NA(),D32) -> 1 | AC27: =IF(D33="",NA(),D33) -> 1 | AD27: =IF(D34="",NA(),D34) -> 1 | AE27: =IF(D35="",NA(),D35) -> 1 | AF27: =IF(D36="",NA(),D36) -> 1 | AG27: =IF(D37="",NA(),D37) -> 1 | AH27: =IF(D38="",NA(),D38) -> 1 | AI27: =IF(D39="",NA(),D39) -> 1 | AJ27: =IF(D40="",NA(),D40) -> 1 | AK27: =IF(D41="",NA(),D41) -> 1 | AL27: =IF(D42="",NA(),D42) -> 1 | AM27: =IF(D43="",NA(),D43) -> 1 | AN27: ="FY"&B27 -> FY2011
B28: =B27+1 -> 2012 | C28: =COUNTIF('Retention Calc'!$R$2:$R$2698,$B28) -> 164 | D28: {=IFERROR(IF($B28+D$26>2026,"",SUMPRODUCT(('Retention Calc'!$R$2:$R$2698=$B28)*INDEX('Retention Calc'!$B$2:$Q$2698,0,MATCH($B28+D$26,'Retention Calc'!$B$1:$Q$1,0)))/$C28),"")} -> 1 | E28: {=IFERROR(IF($B28+E$26>2026,"",SUMPRODUCT(('Retention Calc'!$R$2:$R$2698=$B28)*INDEX('Retention Calc'!$B$2:$Q$2698,0,MATCH($B28+E$26,'Retention Calc'!$B$1:$Q$1,0)))/$C28),"")} -> 0.32317073 | F28: {=IFERROR(IF($B28+F$26>2026,"",SUMPRODUCT(('Retention Calc'!$R$2:$R$2698=$B28)*INDEX('Retention Calc'!$B$2:$Q$2698,0,MATCH($B28+F$26,'Retention Calc'!$B$1:$Q$1,0)))/$C28),"")} -> 0.31707317 | G28: {=IFERROR(IF($B28+G$26>2026,"",SUMPRODUCT(('Retention Calc'!$R$2:$R$2698=$B28)*INDEX('Retention Calc'!$B$2:$Q$2698,0,MATCH($B28+G$26,'Retention Calc'!$B$1:$Q$1,0)))/$C28),"")} -> 0.32317073 | H28: {=IFERROR(IF($B28+H$26>2026,"",SUMPRODUCT(('Retention Calc'!$R$2:$R$2698=$B28)*INDEX('Retention Calc'!$B$2:$Q$2698,0,MATCH($B28+H$26,'Retention Calc'!$B$1:$Q$1,0)))/$C28),"")} -> 0.29268293 | I28: {=IFERROR(IF($B28+I$26>2026,"",SUMPRODUCT(('Retention Calc'!$R$2:$R$2698=$B28)*INDEX('Retention Calc'!$B$2:$Q$2698,0,MATCH($B28+I$26,'Retention Calc'!$B$1:$Q$1,0)))/$C28),"")} -> 0.2804878 | J28: {=IFERROR(IF($B28+J$26>2026,"",SUMPRODUCT(('Retention Calc'!$R$2:$R$2698=$B28)*INDEX('Retention Calc'!$B$2:$Q$2698,0,MATCH($B28+J$26,'Retention Calc'!$B$1:$Q$1,0)))/$C28),"")} -> 0.24390244 | K28: {=IFERROR(IF($B28+K$26>2026,"",SUMPRODUCT(('Retention Calc'!$R$2:$R$2698=$B28)*INDEX('Retention Calc'!$B$2:$Q$2698,0,MATCH($B28+K$26,'Retention Calc'!$B$1:$Q$1,0)))/$C28),"")} -> 0.20121951 | ... S28: {=IFERROR(IF($B28+S$26>2026,"",SUMPRODUCT(('Retention Calc'!$R$2:$R$2698=$B28)*INDEX('Retention Calc'!$B$2:$Q$2698,0,MATCH($B28+S$26,'Retention Calc'!$B$1:$Q$1,0)))/$C28),"")} | V28: ="Year "&1 -> Year 1 | W28: =IF(E27="",NA(),E27) -> 0.52225519 | X28: =IF(E28="",NA(),E28) -> 0.32317073 | Y28: =IF(E29="",NA(),E29) -> 0.34814815 | Z28: =IF(E30="",NA(),E30) -> 0.33035714 | AA28: =IF(E31="",NA(),E31) -> 0.27333333 | AB28: =IF(E32="",NA(),E32) -> 0.18023256 | AC28: =IF(E33="",NA(),E33) -> 0.20754717 | AD28: =IF(E34="",NA(),E34) -> 0.21774194 | AE28: =IF(E35="",NA(),E35) -> 0.084507042 | AF28: =IF(E36="",NA(),E36) -> 0.24691358 | AG28: =IF(E37="",NA(),E37) -> 0.21808511 | AH28: =IF(E38="",NA(),E38) -> 0.31318681 | AI28: =IF(E39="",NA(),E39) -> 0.28571429 | AJ28: =IF(E40="",NA(),E40) -> 0.30081301 | AK28: =IF(E41="",NA(),E41) -> 0.19875776 | AL28: =IF(E42="",NA(),E42) -> #N/A | AM28: =IF(E43="",NA(),E43) -> 0.28554502 | AN28: ="FY"&B28 -> FY2012
B29: =B28+1 -> 2013 | C29: =COUNTIF('Retention Calc'!$R$2:$R$2698,$B29) -> 135 | D29: {=IFERROR(IF($B29+D$26>2026,"",SUMPRODUCT(('Retention Calc'!$R$2:$R$2698=$B29)*INDEX('Retention Calc'!$B$2:$Q$2698,0,MATCH($B29+D$26,'Retention Calc'!$B$1:$Q$1,0)))/$C29),"")} -> 1 | E29: {=IFERROR(IF($B29+E$26>2026,"",SUMPRODUCT(('Retention Calc'!$R$2:$R$2698=$B29)*INDEX('Retention Calc'!$B$2:$Q$2698,0,MATCH($B29+E$26,'Retention Calc'!$B$1:$Q$1,0)))/$C29),"")} -> 0.34814815 | F29: {=IFERROR(IF($B29+F$26>2026,"",SUMPRODUCT(('Retention Calc'!$R$2:$R$2698=$B29)*INDEX('Retention Calc'!$B$2:$Q$2698,0,MATCH($B29+F$26,'Retention Calc'!$B$1:$Q$1,0)))/$C29),"")} -> 0.2962963 | G29: {=IFERROR(IF($B29+G$26>2026,"",SUMPRODUCT(('Retention Calc'!$R$2:$R$2698=$B29)*INDEX('Retention Calc'!$B$2:$Q$2698,0,MATCH($B29+G$26,'Retention Calc'!$B$1:$Q$1,0)))/$C29),"")} -> 0.27407407 | H29: {=IFERROR(IF($B29+H$26>2026,"",SUMPRODUCT(('Retention Calc'!$R$2:$R$2698=$B29)*INDEX('Retention Calc'!$B$2:$Q$2698,0,MATCH($B29+H$26,'Retention Calc'!$B$1:$Q$1,0)))/$C29),"")} -> 0.27407407 | I29: {=IFERROR(IF($B29+I$26>2026,"",SUMPRODUCT(('Retention Calc'!$R$2:$R$2698=$B29)*INDEX('Retention Calc'!$B$2:$Q$2698,0,MATCH($B29+I$26,'Retention Calc'!$B$1:$Q$1,0)))/$C29),"")} -> 0.23703704 | J29: {=IFERROR(IF($B29+J$26>2026,"",SUMPRODUCT(('Retention Calc'!$R$2:$R$2698=$B29)*INDEX('Retention Calc'!$B$2:$Q$2698,0,MATCH($B29+J$26,'Retention Calc'!$B$1:$Q$1,0)))/$C29),"")} -> 0.17777778 | K29: {=IFERROR(IF($B29+K$26>2026,"",SUMPRODUCT(('Retention Calc'!$R$2:$R$2698=$B29)*INDEX('Retention Calc'!$B$2:$Q$2698,0,MATCH($B29+K$26,'Retention Calc'!$B$1:$Q$1,0)))/$C29),"")} -> 0.15555556 | ... S29: {=IFERROR(IF($B29+S$26>2026,"",SUMPRODUCT(('Retention Calc'!$R$2:$R$2698=$B29)*INDEX('Retention Calc'!$B$2:$Q$2698,0,MATCH($B29+S$26,'Retention Calc'!$B$1:$Q$1,0)))/$C29),"")} | V29: ="Year "&2 -> Year 2 | W29: =IF(F27="",NA(),F27) -> 0.50148368 | X29: =IF(F28="",NA(),F28) -> 0.31707317 | Y29: =IF(F29="",NA(),F29) -> 0.2962963 | Z29: =IF(F30="",NA(),F30) -> 0.29464286 | AA29: =IF(F31="",NA(),F31) -> 0.22666667 | AB29: =IF(F32="",NA(),F32) -> 0.15116279 | AC29: =IF(F33="",NA(),F33) -> 0.13679245 | AD29: =IF(F34="",NA(),F34) -> 0.22580645 | AE29: =IF(F35="",NA(),F35) -> 0.13380282 | AF29: =IF(F36="",NA(),F36) -> 0.17283951 | AG29: =IF(F37="",NA(),F37) -> 0.20212766 | AH29: =IF(F38="",NA(),F38) -> 0.1978022 | AI29: =IF(F39="",NA(),F39) -> 0.18452381 | AJ29: =IF(F40="",NA(),F40) -> 0.2601626 | AK29: =IF(F41="",NA(),F41) -> #N/A | AL29: =IF(F42="",NA(),F42) -> #N/A | AM29: =IF(F43="",NA(),F43) -> 0.25094897 | AN29: ="FY"&B29 -> FY2013
B30: =B29+1 -> 2014 | C30: =COUNTIF('Retention Calc'!$R$2:$R$2698,$B30) -> 112 | D30: {=IFERROR(IF($B30+D$26>2026,"",SUMPRODUCT(('Retention Calc'!$R$2:$R$2698=$B30)*INDEX('Retention Calc'!$B$2:$Q$2698,0,MATCH($B30+D$26,'Retention Calc'!$B$1:$Q$1,0)))/$C30),"")} -> 1 | E30: {=IFERROR(IF($B30+E$26>2026,"",SUMPRODUCT(('Retention Calc'!$R$2:$R$2698=$B30)*INDEX('Retention Calc'!$B$2:$Q$2698,0,MATCH($B30+E$26,'Retention Calc'!$B$1:$Q$1,0)))/$C30),"")} -> 0.33035714 | F30: {=IFERROR(IF($B30+F$26>2026,"",SUMPRODUCT(('Retention Calc'!$R$2:$R$2698=$B30)*INDEX('Retention Calc'!$B$2:$Q$2698,0,MATCH($B30+F$26,'Retention Calc'!$B$1:$Q$1,0)))/$C30),"")} -> 0.29464286 | G30: {=IFERROR(IF($B30+G$26>2026,"",SUMPRODUCT(('Retention Calc'!$R$2:$R$2698=$B30)*INDEX('Retention Calc'!$B$2:$Q$2698,0,MATCH($B30+G$26,'Retention Calc'!$B$1:$Q$1,0)))/$C30),"")} -> 0.24107143 | H30: {=IFERROR(IF($B30+H$26>2026,"",SUMPRODUCT(('Retention Calc'!$R$2:$R$2698=$B30)*INDEX('Retention Calc'!$B$2:$Q$2698,0,MATCH($B30+H$26,'Retention Calc'!$B$1:$Q$1,0)))/$C30),"")} -> 0.25 | I30: {=IFERROR(IF($B30+I$26>2026,"",SUMPRODUCT(('Retention Calc'!$R$2:$R$2698=$B30)*INDEX('Retention Calc'!$B$2:$Q$2698,0,MATCH($B30+I$26,'Retention Calc'!$B$1:$Q$1,0)))/$C30),"")} -> 0.20535714 | J30: {=IFERROR(IF($B30+J$26>2026,"",SUMPRODUCT(('Retention Calc'!$R$2:$R$2698=$B30)*INDEX('Retention Calc'!$B$2:$Q$2698,0,MATCH($B30+J$26,'Retention Calc'!$B$1:$Q$1,0)))/$C30),"")} -> 0.13392857 | K30: {=IFERROR(IF($B30+K$26>2026,"",SUMPRODUCT(('Retention Calc'!$R$2:$R$2698=$B30)*INDEX('Retention Calc'!$B$2:$Q$2698,0,MATCH($B30+K$26,'Retention Calc'!$B$1:$Q$1,0)))/$C30),"")} -> 0.16964286 | ... S30: {=IFERROR(IF($B30+S$26>2026,"",SUMPRODUCT(('Retention Calc'!$R$2:$R$2698=$B30)*INDEX('Retention Calc'!$B$2:$Q$2698,0,MATCH($B30+S$26,'Retention Calc'!$B$1:$Q$1,0)))/$C30),"")} | V30: ="Year "&3 -> Year 3 | W30: =IF(G27="",NA(),G27) -> 0.45697329 | X30: =IF(G28="",NA(),G28) -> 0.32317073 | Y30: =IF(G29="",NA(),G29) -> 0.27407407 | Z30: =IF(G30="",NA(),G30) -> 0.24107143 | AA30: =IF(G31="",NA(),G31) -> 0.22 | AB30: =IF(G32="",NA(),G32) -> 0.11046512 | AC30: =IF(G33="",NA(),G33) -> 0.1509434 | AD30: =IF(G34="",NA(),G34) -> 0.31451613 | AE30: =IF(G35="",NA(),G35) -> 0.11971831 | AF30: =IF(G36="",NA(),G36) -> 0.13580247 | AG30: =IF(G37="",NA(),G37) -> 0.18085106 | AH30: =IF(G38="",NA(),G38) -> 0.12637363 | AI30: =IF(G39="",NA(),G39) -> 0.16666667 | AJ30: =IF(G40="",NA(),G40) -> #N/A | AK30: =IF(G41="",NA(),G41) -> #N/A | AL30: =IF(G42="",NA(),G42) -> #N/A | AM30: =IF(G43="",NA(),G43) -> 0.23042705 | AN30: ="FY"&B30 -> FY2014
B31: =B30+1 -> 2015 | C31: =COUNTIF('Retention Calc'!$R$2:$R$2698,$B31) -> 150 | D31: {=IFERROR(IF($B31+D$26>2026,"",SUMPRODUCT(('Retention Calc'!$R$2:$R$2698=$B31)*INDEX('Retention Calc'!$B$2:$Q$2698,0,MATCH($B31+D$26,'Retention Calc'!$B$1:$Q$1,0)))/$C31),"")} -> 1 | E31: {=IFERROR(IF($B31+E$26>2026,"",SUMPRODUCT(('Retention Calc'!$R$2:$R$2698=$B31)*INDEX('Retention Calc'!$B$2:$Q$2698,0,MATCH($B31+E$26,'Retention Calc'!$B$1:$Q$1,0)))/$C31),"")} -> 0.27333333 | F31: {=IFERROR(IF($B31+F$26>2026,"",SUMPRODUCT(('Retention Calc'!$R$2:$R$2698=$B31)*INDEX('Retention Calc'!$B$2:$Q$2698,0,MATCH($B31+F$26,'Retention Calc'!$B$1:$Q$1,0)))/$C31),"")} -> 0.22666667 | G31: {=IFERROR(IF($B31+G$26>2026,"",SUMPRODUCT(('Retention Calc'!$R$2:$R$2698=$B31)*INDEX('Retention Calc'!$B$2:$Q$2698,0,MATCH($B31+G$26,'Retention Calc'!$B$1:$Q$1,0)))/$C31),"")} -> 0.22 | H31: {=IFERROR(IF($B31+H$26>2026,"",SUMPRODUCT(('Retention Calc'!$R$2:$R$2698=$B31)*INDEX('Retention Calc'!$B$2:$Q$2698,0,MATCH($B31+H$26,'Retention Calc'!$B$1:$Q$1,0)))/$C31),"")} -> 0.2 | I31: {=IFERROR(IF($B31+I$26>2026,"",SUMPRODUCT(('Retention Calc'!$R$2:$R$2698=$B31)*INDEX('Retention Calc'!$B$2:$Q$2698,0,MATCH($B31+I$26,'Retention Calc'!$B$1:$Q$1,0)))/$C31),"")} -> 0.16666667 | J31: {=IFERROR(IF($B31+J$26>2026,"",SUMPRODUCT(('Retention Calc'!$R$2:$R$2698=$B31)*INDEX('Retention Calc'!$B$2:$Q$2698,0,MATCH($B31+J$26,'Retention Calc'!$B$1:$Q$1,0)))/$C31),"")} -> 0.18 | K31: {=IFERROR(IF($B31+K$26>2026,"",SUMPRODUCT(('Retention Calc'!$R$2:$R$2698=$B31)*INDEX('Retention Calc'!$B$2:$Q$2698,0,MATCH($B31+K$26,'Retention Calc'!$B$1:$Q$1,0)))/$C31),"")} -> 0.14 | ... S31: {=IFERROR(IF($B31+S$26>2026,"",SUMPRODUCT(('Retention Calc'!$R$2:$R$2698=$B31)*INDEX('Retention Calc'!$B$2:$Q$2698,0,MATCH($B31+S$26,'Retention Calc'!$B$1:$Q$1,0)))/$C31),"")} | V31: ="Year "&4 -> Year 4 | W31: =IF(H27="",NA(),H27) -> 0.47477745 | X31: =IF(H28="",NA(),H28) -> 0.29268293 | Y31: =IF(H29="",NA(),H29) -> 0.27407407 | Z31: =IF(H30="",NA(),H30) -> 0.25 | AA31: =IF(H31="",NA(),H31) -> 0.2 | AB31: =IF(H32="",NA(),H32) -> 0.087209302 | AC31: =IF(H33="",NA(),H33) -> 0.16037736 | AD31: =IF(H34="",NA(),H34) -> 0.23387097 | AE31: =IF(H35="",NA(),H35) -> 0.098591549 | AF31: =IF(H36="",NA(),H36) -> 0.14814815 | AG31: =IF(H37="",NA(),H37) -> 0.20744681 | AH31: =IF(H38="",NA(),H38) -> 0.14285714 | AI31: =IF(H39="",NA(),H39) -> #N/A | AJ31: =IF(H40="",NA(),H40) -> #N/A | AK31: =IF(H41="",NA(),H41) -> #N/A | AL31: =IF(H42="",NA(),H42) -> #N/A | AM31: =IF(H43="",NA(),H43) -> 0.23269231 | AN31: ="FY"&B31 -> FY2015
B32: =B31+1 -> 2016 | C32: =COUNTIF('Retention Calc'!$R$2:$R$2698,$B32) -> 172 | D32: {=IFERROR(IF($B32+D$26>2026,"",SUMPRODUCT(('Retention Calc'!$R$2:$R$2698=$B32)*INDEX('Retention Calc'!$B$2:$Q$2698,0,MATCH($B32+D$26,'Retention Calc'!$B$1:$Q$1,0)))/$C32),"")} -> 1 | E32: {=IFERROR(IF($B32+E$26>2026,"",SUMPRODUCT(('Retention Calc'!$R$2:$R$2698=$B32)*INDEX('Retention Calc'!$B$2:$Q$2698,0,MATCH($B32+E$26,'Retention Calc'!$B$1:$Q$1,0)))/$C32),"")} -> 0.18023256 | F32: {=IFERROR(IF($B32+F$26>2026,"",SUMPRODUCT(('Retention Calc'!$R$2:$R$2698=$B32)*INDEX('Retention Calc'!$B$2:$Q$2698,0,MATCH($B32+F$26,'Retention Calc'!$B$1:$Q$1,0)))/$C32),"")} -> 0.15116279 | G32: {=IFERROR(IF($B32+G$26>2026,"",SUMPRODUCT(('Retention Calc'!$R$2:$R$2698=$B32)*INDEX('Retention Calc'!$B$2:$Q$2698,0,MATCH($B32+G$26,'Retention Calc'!$B$1:$Q$1,0)))/$C32),"")} -> 0.11046512 | H32: {=IFERROR(IF($B32+H$26>2026,"",SUMPRODUCT(('Retention Calc'!$R$2:$R$2698=$B32)*INDEX('Retention Calc'!$B$2:$Q$2698,0,MATCH($B32+H$26,'Retention Calc'!$B$1:$Q$1,0)))/$C32),"")} -> 0.087209302 | I32: {=IFERROR(IF($B32+I$26>2026,"",SUMPRODUCT(('Retention Calc'!$R$2:$R$2698=$B32)*INDEX('Retention Calc'!$B$2:$Q$2698,0,MATCH($B32+I$26,'Retention Calc'!$B$1:$Q$1,0)))/$C32),"")} -> 0.11627907 | J32: {=IFERROR(IF($B32+J$26>2026,"",SUMPRODUCT(('Retention Calc'!$R$2:$R$2698=$B32)*INDEX('Retention Calc'!$B$2:$Q$2698,0,MATCH($B32+J$26,'Retention Calc'!$B$1:$Q$1,0)))/$C32),"")} -> 0.11046512 | K32: {=IFERROR(IF($B32+K$26>2026,"",SUMPRODUCT(('Retention Calc'!$R$2:$R$2698=$B32)*INDEX('Retention Calc'!$B$2:$Q$2698,0,MATCH($B32+K$26,'Retention Calc'!$B$1:$Q$1,0)))/$C32),"")} -> 0.075581395 | ... S32: {=IFERROR(IF($B32+S$26>2026,"",SUMPRODUCT(('Retention Calc'!$R$2:$R$2698=$B32)*INDEX('Retention Calc'!$B$2:$Q$2698,0,MATCH($B32+S$26,'Retention Calc'!$B$1:$Q$1,0)))/$C32),"")} | V32: ="Year "&5 -> Year 5 | W32: =IF(I27="",NA(),I27) -> 0.44807122 | X32: =IF(I28="",NA(),I28) -> 0.2804878 | Y32: =IF(I29="",NA(),I29) -> 0.23703704 | Z32: =IF(I30="",NA(),I30) -> 0.20535714 | AA32: =IF(I31="",NA(),I31) -> 0.16666667 | AB32: =IF(I32="",NA(),I32) -> 0.11627907 | AC32: =IF(I33="",NA(),I33) -> 0.11320755 | AD32: =IF(I34="",NA(),I34) -> 0.20967742 | AE32: =IF(I35="",NA(),I35) -> 0.11267606 | AF32: =IF(I36="",NA(),I36) -> 0.14814815 | AG32: =IF(I37="",NA(),I37) -> 0.13829787 | AH32: =IF(I38="",NA(),I38) -> #N/A | AI32: =IF(I39="",NA(),I39) -> #N/A | AJ32: =IF(I40="",NA(),I40) -> #N/A | AK32: =IF(I41="",NA(),I41) -> #N/A | AL32: =IF(I42="",NA(),I42) -> #N/A | AM32: =IF(I43="",NA(),I43) -> 0.21759747 | AN32: ="FY"&B32 -> FY2016
B33: =B32+1 -> 2017 | C33: =COUNTIF('Retention Calc'!$R$2:$R$2698,$B33) -> 212 | D33: {=IFERROR(IF($B33+D$26>2026,"",SUMPRODUCT(('Retention Calc'!$R$2:$R$2698=$B33)*INDEX('Retention Calc'!$B$2:$Q$2698,0,MATCH($B33+D$26,'Retention Calc'!$B$1:$Q$1,0)))/$C33),"")} -> 1 | E33: {=IFERROR(IF($B33+E$26>2026,"",SUMPRODUCT(('Retention Calc'!$R$2:$R$2698=$B33)*INDEX('Retention Calc'!$B$2:$Q$2698,0,MATCH($B33+E$26,'Retention Calc'!$B$1:$Q$1,0)))/$C33),"")} -> 0.20754717 | F33: {=IFERROR(IF($B33+F$26>2026,"",SUMPRODUCT(('Retention Calc'!$R$2:$R$2698=$B33)*INDEX('Retention Calc'!$B$2:$Q$2698,0,MATCH($B33+F$26,'Retention Calc'!$B$1:$Q$1,0)))/$C33),"")} -> 0.13679245 | G33: {=IFERROR(IF($B33+G$26>2026,"",SUMPRODUCT(('Retention Calc'!$R$2:$R$2698=$B33)*INDEX('Retention Calc'!$B$2:$Q$2698,0,MATCH($B33+G$26,'Retention Calc'!$B$1:$Q$1,0)))/$C33),"")} -> 0.1509434 | H33: {=IFERROR(IF($B33+H$26>2026,"",SUMPRODUCT(('Retention Calc'!$R$2:$R$2698=$B33)*INDEX('Retention Calc'!$B$2:$Q$2698,0,MATCH($B33+H$26,'Retention Calc'!$B$1:$Q$1,0)))/$C33),"")} -> 0.16037736 | I33: {=IFERROR(IF($B33+I$26>2026,"",SUMPRODUCT(('Retention Calc'!$R$2:$R$2698=$B33)*INDEX('Retention Calc'!$B$2:$Q$2698,0,MATCH($B33+I$26,'Retention Calc'!$B$1:$Q$1,0)))/$C33),"")} -> 0.11320755 | J33: {=IFERROR(IF($B33+J$26>2026,"",SUMPRODUCT(('Retention Calc'!$R$2:$R$2698=$B33)*INDEX('Retention Calc'!$B$2:$Q$2698,0,MATCH($B33+J$26,'Retention Calc'!$B$1:$Q$1,0)))/$C33),"")} -> 0.094339623 | K33: {=IFERROR(IF($B33+K$26>2026,"",SUMPRODUCT(('Retention Calc'!$R$2:$R$2698=$B33)*INDEX('Retention Calc'!$B$2:$Q$2698,0,MATCH($B33+K$26,'Retention Calc'!$B$1:$Q$1,0)))/$C33),"")} -> 0.11320755 | ... S33: {=IFERROR(IF($B33+S$26>2026,"",SUMPRODUCT(('Retention Calc'!$R$2:$R$2698=$B33)*INDEX('Retention Calc'!$B$2:$Q$2698,0,MATCH($B33+S$26,'Retention Calc'!$B$1:$Q$1,0)))/$C33),"")} | V33: ="Year "&6 -> Year 6 | W33: =IF(J27="",NA(),J27) -> 0.39762611 | X33: =IF(J28="",NA(),J28) -> 0.24390244 | Y33: =IF(J29="",NA(),J29) -> 0.17777778 | Z33: =IF(J30="",NA(),J30) -> 0.13392857 | AA33: =IF(J31="",NA(),J31) -> 0.18 | AB33: =IF(J32="",NA(),J32) -> 0.11046512 | AC33: =IF(J33="",NA(),J33) -> 0.094339623 | AD33: =IF(J34="",NA(),J34) -> 0.20967742 | AE33: =IF(J35="",NA(),J35) -> 0.11971831 | AF33: =IF(J36="",NA(),J36) -> 0.11111111 | AG33: =IF(J37="",NA(),J37) -> #N/A | AH33: =IF(J38="",NA(),J38) -> #N/A | AI33: =IF(J39="",NA(),J39) -> #N/A | AJ33: =IF(J40="",NA(),J40) -> #N/A | AK33: =IF(J41="",NA(),J41) -> #N/A | AL33: =IF(J42="",NA(),J42) -> #N/A | AM33: =IF(J43="",NA(),J43) -> 0.19883041 | AN33: ="FY"&B33 -> FY2017
B34: =B33+1 -> 2018 | C34: =COUNTIF('Retention Calc'!$R$2:$R$2698,$B34) -> 124 | D34: {=IFERROR(IF($B34+D$26>2026,"",SUMPRODUCT(('Retention Calc'!$R$2:$R$2698=$B34)*INDEX('Retention Calc'!$B$2:$Q$2698,0,MATCH($B34+D$26,'Retention Calc'!$B$1:$Q$1,0)))/$C34),"")} -> 1 | E34: {=IFERROR(IF($B34+E$26>2026,"",SUMPRODUCT(('Retention Calc'!$R$2:$R$2698=$B34)*INDEX('Retention Calc'!$B$2:$Q$2698,0,MATCH($B34+E$26,'Retention Calc'!$B$1:$Q$1,0)))/$C34),"")} -> 0.21774194 | F34: {=IFERROR(IF($B34+F$26>2026,"",SUMPRODUCT(('Retention Calc'!$R$2:$R$2698=$B34)*INDEX('Retention Calc'!$B$2:$Q$2698,0,MATCH($B34+F$26,'Retention Calc'!$B$1:$Q$1,0)))/$C34),"")} -> 0.22580645 | G34: {=IFERROR(IF($B34+G$26>2026,"",SUMPRODUCT(('Retention Calc'!$R$2:$R$2698=$B34)*INDEX('Retention Calc'!$B$2:$Q$2698,0,MATCH($B34+G$26,'Retention Calc'!$B$1:$Q$1,0)))/$C34),"")} -> 0.31451613 | H34: {=IFERROR(IF($B34+H$26>2026,"",SUMPRODUCT(('Retention Calc'!$R$2:$R$2698=$B34)*INDEX('Retention Calc'!$B$2:$Q$2698,0,MATCH($B34+H$26,'Retention Calc'!$B$1:$Q$1,0)))/$C34),"")} -> 0.23387097 | I34: {=IFERROR(IF($B34+I$26>2026,"",SUMPRODUCT(('Retention Calc'!$R$2:$R$2698=$B34)*INDEX('Retention Calc'!$B$2:$Q$2698,0,MATCH($B34+I$26,'Retention Calc'!$B$1:$Q$1,0)))/$C34),"")} -> 0.20967742 | J34: {=IFERROR(IF($B34+J$26>2026,"",SUMPRODUCT(('Retention Calc'!$R$2:$R$2698=$B34)*INDEX('Retention Calc'!$B$2:$Q$2698,0,MATCH($B34+J$26,'Retention Calc'!$B$1:$Q$1,0)))/$C34),"")} -> 0.20967742 | K34: {=IFERROR(IF($B34+K$26>2026,"",SUMPRODUCT(('Retention Calc'!$R$2:$R$2698=$B34)*INDEX('Retention Calc'!$B$2:$Q$2698,0,MATCH($B34+K$26,'Retention Calc'!$B$1:$Q$1,0)))/$C34),"")} -> 0.17741935 | ... S34: {=IFERROR(IF($B34+S$26>2026,"",SUMPRODUCT(('Retention Calc'!$R$2:$R$2698=$B34)*INDEX('Retention Calc'!$B$2:$Q$2698,0,MATCH($B34+S$26,'Retention Calc'!$B$1:$Q$1,0)))/$C34),"")} | V34: ="Year "&7 -> Year 7 | W34: =IF(K27="",NA(),K27) -> 0.38278932 | X34: =IF(K28="",NA(),K28) -> 0.20121951 | Y34: =IF(K29="",NA(),K29) -> 0.15555556 | Z34: =IF(K30="",NA(),K30) -> 0.16964286 | AA34: =IF(K31="",NA(),K31) -> 0.14 | AB34: =IF(K32="",NA(),K32) -> 0.075581395 | AC34: =IF(K33="",NA(),K33) -> 0.11320755 | AD34: =IF(K34="",NA(),K34) -> 0.17741935 | AE34: =IF(K35="",NA(),K35) -> 0.091549296 | AF34: =IF(K36="",NA(),K36) -> #N/A | AG34: =IF(K37="",NA(),K37) -> #N/A | AH34: =IF(K38="",NA(),K38) -> #N/A | AI34: =IF(K39="",NA(),K39) -> #N/A | AJ34: =IF(K40="",NA(),K40) -> #N/A | AK34: =IF(K41="",NA(),K41) -> #N/A | AL34: =IF(K42="",NA(),K42) -> #N/A | AM34: =IF(K43="",NA(),K43) -> 0.19056848 | AN34: ="FY"&B34 -> FY2018
B35: =B34+1 -> 2019 | C35: =COUNTIF('Retention Calc'!$R$2:$R$2698,$B35) -> 142 | D35: {=IFERROR(IF($B35+D$26>2026,"",SUMPRODUCT(('Retention Calc'!$R$2:$R$2698=$B35)*INDEX('Retention Calc'!$B$2:$Q$2698,0,MATCH($B35+D$26,'Retention Calc'!$B$1:$Q$1,0)))/$C35),"")} -> 1 | E35: {=IFERROR(IF($B35+E$26>2026,"",SUMPRODUCT(('Retention Calc'!$R$2:$R$2698=$B35)*INDEX('Retention Calc'!$B$2:$Q$2698,0,MATCH($B35+E$26,'Retention Calc'!$B$1:$Q$1,0)))/$C35),"")} -> 0.084507042 | F35: {=IFERROR(IF($B35+F$26>2026,"",SUMPRODUCT(('Retention Calc'!$R$2:$R$2698=$B35)*INDEX('Retention Calc'!$B$2:$Q$2698,0,MATCH($B35+F$26,'Retention Calc'!$B$1:$Q$1,0)))/$C35),"")} -> 0.13380282 | G35: {=IFERROR(IF($B35+G$26>2026,"",SUMPRODUCT(('Retention Calc'!$R$2:$R$2698=$B35)*INDEX('Retention Calc'!$B$2:$Q$2698,0,MATCH($B35+G$26,'Retention Calc'!$B$1:$Q$1,0)))/$C35),"")} -> 0.11971831 | H35: {=IFERROR(IF($B35+H$26>2026,"",SUMPRODUCT(('Retention Calc'!$R$2:$R$2698=$B35)*INDEX('Retention Calc'!$B$2:$Q$2698,0,MATCH($B35+H$26,'Retention Calc'!$B$1:$Q$1,0)))/$C35),"")} -> 0.098591549 | I35: {=IFERROR(IF($B35+I$26>2026,"",SUMPRODUCT(('Retention Calc'!$R$2:$R$2698=$B35)*INDEX('Retention Calc'!$B$2:$Q$2698,0,MATCH($B35+I$26,'Retention Calc'!$B$1:$Q$1,0)))/$C35),"")} -> 0.11267606 | J35: {=IFERROR(IF($B35+J$26>2026,"",SUMPRODUCT(('Retention Calc'!$R$2:$R$2698=$B35)*INDEX('Retention Calc'!$B$2:$Q$2698,0,MATCH($B35+J$26,'Retention Calc'!$B$1:$Q$1,0)))/$C35),"")} -> 0.11971831 | K35: {=IFERROR(IF($B35+K$26>2026,"",SUMPRODUCT(('Retention Calc'!$R$2:$R$2698=$B35)*INDEX('Retention Calc'!$B$2:$Q$2698,0,MATCH($B35+K$26,'Retention Calc'!$B$1:$Q$1,0)))/$C35),"")} -> 0.091549296 | ... S35: {=IFERROR(IF($B35+S$26>2026,"",SUMPRODUCT(('Retention Calc'!$R$2:$R$2698=$B35)*INDEX('Retention Calc'!$B$2:$Q$2698,0,MATCH($B35+S$26,'Retention Calc'!$B$1:$Q$1,0)))/$C35),"")} | V35: ="Year "&8 -> Year 8 | W35: =IF(L27="",NA(),L27) -> 0.33234421 | X35: =IF(L28="",NA(),L28) -> 0.19512195 | Y35: =IF(L29="",NA(),L29) -> 0.17037037 | Z35: =IF(L30="",NA(),L30) -> 0.125 | AA35: =IF(L31="",NA(),L31) -> 0.15333333 | AB35: =IF(L32="",NA(),L32) -> 0.075581395 | AC35: =IF(L33="",NA(),L33) -> 0.11320755 | AD35: =IF(L34="",NA(),L34) -> 0.2016129 | AE35: =IF(L35="",NA(),L35) -> #N/A | AF35: =IF(L36="",NA(),L36) -> #N/A | AG35: =IF(L37="",NA(),L37) -> #N/A | AH35: =IF(L38="",NA(),L38) -> #N/A | AI35: =IF(L39="",NA(),L39) -> #N/A | AJ35: =IF(L40="",NA(),L40) -> #N/A | AK35: =IF(L41="",NA(),L41) -> #N/A | AL35: =IF(L42="",NA(),L42) -> #N/A | AM35: =IF(L43="",NA(),L43) -> 0.18918919 | AN35: ="FY"&B35 -> FY2019
B36: =B35+1 -> 2020 | C36: =COUNTIF('Retention Calc'!$R$2:$R$2698,$B36) -> 162 | D36: {=IFERROR(IF($B36+D$26>2026,"",SUMPRODUCT(('Retention Calc'!$R$2:$R$2698=$B36)*INDEX('Retention Calc'!$B$2:$Q$2698,0,MATCH($B36+D$26,'Retention Calc'!$B$1:$Q$1,0)))/$C36),"")} -> 1 | E36: {=IFERROR(IF($B36+E$26>2026,"",SUMPRODUCT(('Retention Calc'!$R$2:$R$2698=$B36)*INDEX('Retention Calc'!$B$2:$Q$2698,0,MATCH($B36+E$26,'Retention Calc'!$B$1:$Q$1,0)))/$C36),"")} -> 0.24691358 | F36: {=IFERROR(IF($B36+F$26>2026,"",SUMPRODUCT(('Retention Calc'!$R$2:$R$2698=$B36)*INDEX('Retention Calc'!$B$2:$Q$2698,0,MATCH($B36+F$26,'Retention Calc'!$B$1:$Q$1,0)))/$C36),"")} -> 0.17283951 | G36: {=IFERROR(IF($B36+G$26>2026,"",SUMPRODUCT(('Retention Calc'!$R$2:$R$2698=$B36)*INDEX('Retention Calc'!$B$2:$Q$2698,0,MATCH($B36+G$26,'Retention Calc'!$B$1:$Q$1,0)))/$C36),"")} -> 0.13580247 | H36: {=IFERROR(IF($B36+H$26>2026,"",SUMPRODUCT(('Retention Calc'!$R$2:$R$2698=$B36)*INDEX('Retention Calc'!$B$2:$Q$2698,0,MATCH($B36+H$26,'Retention Calc'!$B$1:$Q$1,0)))/$C36),"")} -> 0.14814815 | I36: {=IFERROR(IF($B36+I$26>2026,"",SUMPRODUCT(('Retention Calc'!$R$2:$R$2698=$B36)*INDEX('Retention Calc'!$B$2:$Q$2698,0,MATCH($B36+I$26,'Retention Calc'!$B$1:$Q$1,0)))/$C36),"")} -> 0.14814815 | J36: {=IFERROR(IF($B36+J$26>2026,"",SUMPRODUCT(('Retention Calc'!$R$2:$R$2698=$B36)*INDEX('Retention Calc'!$B$2:$Q$2698,0,MATCH($B36+J$26,'Retention Calc'!$B$1:$Q$1,0)))/$C36),"")} -> 0.11111111 | K36: {=IFERROR(IF($B36+K$26>2026,"",SUMPRODUCT(('Retention Calc'!$R$2:$R$2698=$B36)*INDEX('Retention Calc'!$B$2:$Q$2698,0,MATCH($B36+K$26,'Retention Calc'!$B$1:$Q$1,0)))/$C36),"")} | ... S36: {=IFERROR(IF($B36+S$26>2026,"",SUMPRODUCT(('Retention Calc'!$R$2:$R$2698=$B36)*INDEX('Retention Calc'!$B$2:$Q$2698,0,MATCH($B36+S$26,'Retention Calc'!$B$1:$Q$1,0)))/$C36),"")} | V36: ="Year "&9 -> Year 9 | W36: =IF(M27="",NA(),M27) -> 0.3620178 | X36: =IF(M28="",NA(),M28) -> 0.19512195 | Y36: =IF(M29="",NA(),M29) -> 0.11111111 | Z36: =IF(M30="",NA(),M30) -> 0.15178571 | AA36: =IF(M31="",NA(),M31) -> 0.14 | AB36: =IF(M32="",NA(),M32) -> 0.063953488 | AC36: =IF(M33="",NA(),M33) -> 0.10849057 | AD36: =IF(M34="",NA(),M34) -> #N/A | AE36: =IF(M35="",NA(),M35) -> #N/A | AF36: =IF(M36="",NA(),M36) -> #N/A | AG36: =IF(M37="",NA(),M37) -> #N/A | AH36: =IF(M38="",NA(),M38) -> #N/A | AI36: =IF(M39="",NA(),M39) -> #N/A | AJ36: =IF(M40="",NA(),M40) -> #N/A | AK36: =IF(M41="",NA(),M41) -> #N/A | AL36: =IF(M42="",NA(),M42) -> #N/A | AM36: =IF(M43="",NA(),M43) -> 0.18798752 | AN36: ="FY"&B36 -> FY2020
B37: =B36+1 -> 2021 | C37: =COUNTIF('Retention Calc'!$R$2:$R$2698,$B37) -> 188 | D37: {=IFERROR(IF($B37+D$26>2026,"",SUMPRODUCT(('Retention Calc'!$R$2:$R$2698=$B37)*INDEX('Retention Calc'!$B$2:$Q$2698,0,MATCH($B37+D$26,'Retention Calc'!$B$1:$Q$1,0)))/$C37),"")} -> 1 | E37: {=IFERROR(IF($B37+E$26>2026,"",SUMPRODUCT(('Retention Calc'!$R$2:$R$2698=$B37)*INDEX('Retention Calc'!$B$2:$Q$2698,0,MATCH($B37+E$26,'Retention Calc'!$B$1:$Q$1,0)))/$C37),"")} -> 0.21808511 | F37: {=IFERROR(IF($B37+F$26>2026,"",SUMPRODUCT(('Retention Calc'!$R$2:$R$2698=$B37)*INDEX('Retention Calc'!$B$2:$Q$2698,0,MATCH($B37+F$26,'Retention Calc'!$B$1:$Q$1,0)))/$C37),"")} -> 0.20212766 | G37: {=IFERROR(IF($B37+G$26>2026,"",SUMPRODUCT(('Retention Calc'!$R$2:$R$2698=$B37)*INDEX('Retention Calc'!$B$2:$Q$2698,0,MATCH($B37+G$26,'Retention Calc'!$B$1:$Q$1,0)))/$C37),"")} -> 0.18085106 | H37: {=IFERROR(IF($B37+H$26>2026,"",SUMPRODUCT(('Retention Calc'!$R$2:$R$2698=$B37)*INDEX('Retention Calc'!$B$2:$Q$2698,0,MATCH($B37+H$26,'Retention Calc'!$B$1:$Q$1,0)))/$C37),"")} -> 0.20744681 | I37: {=IFERROR(IF($B37+I$26>2026,"",SUMPRODUCT(('Retention Calc'!$R$2:$R$2698=$B37)*INDEX('Retention Calc'!$B$2:$Q$2698,0,MATCH($B37+I$26,'Retention Calc'!$B$1:$Q$1,0)))/$C37),"")} -> 0.13829787 | J37: {=IFERROR(IF($B37+J$26>2026,"",SUMPRODUCT(('Retention Calc'!$R$2:$R$2698=$B37)*INDEX('Retention Calc'!$B$2:$Q$2698,0,MATCH($B37+J$26,'Retention Calc'!$B$1:$Q$1,0)))/$C37),"")} | K37: {=IFERROR(IF($B37+K$26>2026,"",SUMPRODUCT(('Retention Calc'!$R$2:$R$2698=$B37)*INDEX('Retention Calc'!$B$2:$Q$2698,0,MATCH($B37+K$26,'Retention Calc'!$B$1:$Q$1,0)))/$C37),"")} | ... S37: {=IFERROR(IF($B37+S$26>2026,"",SUMPRODUCT(('Retention Calc'!$R$2:$R$2698=$B37)*INDEX('Retention Calc'!$B$2:$Q$2698,0,MATCH($B37+S$26,'Retention Calc'!$B$1:$Q$1,0)))/$C37),"")} | V37: ="Year "&10 -> Year 10 | W37: =IF(N27="",NA(),N27) -> 0.3115727 | X37: =IF(N28="",NA(),N28) -> 0.19512195 | Y37: =IF(N29="",NA(),N29) -> 0.13333333 | Z37: =IF(N30="",NA(),N30) -> 0.089285714 | AA37: =IF(N31="",NA(),N31) -> 0.12 | AB37: =IF(N32="",NA(),N32) -> 0.069767442 | AC37: =IF(N33="",NA(),N33) -> #N/A | AD37: =IF(N34="",NA(),N34) -> #N/A | AE37: =IF(N35="",NA(),N35) -> #N/A | AF37: =IF(N36="",NA(),N36) -> #N/A | AG37: =IF(N37="",NA(),N37) -> #N/A | AH37: =IF(N38="",NA(),N38) -> #N/A | AI37: =IF(N39="",NA(),N39) -> #N/A | AJ37: =IF(N40="",NA(),N40) -> #N/A | AK37: =IF(N41="",NA(),N41) -> #N/A | AL37: =IF(N42="",NA(),N42) -> #N/A | AM37: =IF(N43="",NA(),N43) -> 0.18224299 | AN37: ="FY"&B37 -> FY2021
B38: =B37+1 -> 2022 | C38: =COUNTIF('Retention Calc'!$R$2:$R$2698,$B38) -> 182 | D38: {=IFERROR(IF($B38+D$26>2026,"",SUMPRODUCT(('Retention Calc'!$R$2:$R$2698=$B38)*INDEX('Retention Calc'!$B$2:$Q$2698,0,MATCH($B38+D$26,'Retention Calc'!$B$1:$Q$1,0)))/$C38),"")} -> 1 | E38: {=IFERROR(IF($B38+E$26>2026,"",SUMPRODUCT(('Retention Calc'!$R$2:$R$2698=$B38)*INDEX('Retention Calc'!$B$2:$Q$2698,0,MATCH($B38+E$26,'Retention Calc'!$B$1:$Q$1,0)))/$C38),"")} -> 0.31318681 | F38: {=IFERROR(IF($B38+F$26>2026,"",SUMPRODUCT(('Retention Calc'!$R$2:$R$2698=$B38)*INDEX('Retention Calc'!$B$2:$Q$2698,0,MATCH($B38+F$26,'Retention Calc'!$B$1:$Q$1,0)))/$C38),"")} -> 0.1978022 | G38: {=IFERROR(IF($B38+G$26>2026,"",SUMPRODUCT(('Retention Calc'!$R$2:$R$2698=$B38)*INDEX('Retention Calc'!$B$2:$Q$2698,0,MATCH($B38+G$26,'Retention Calc'!$B$1:$Q$1,0)))/$C38),"")} -> 0.12637363 | H38: {=IFERROR(IF($B38+H$26>2026,"",SUMPRODUCT(('Retention Calc'!$R$2:$R$2698=$B38)*INDEX('Retention Calc'!$B$2:$Q$2698,0,MATCH($B38+H$26,'Retention Calc'!$B$1:$Q$1,0)))/$C38),"")} -> 0.14285714 | I38: {=IFERROR(IF($B38+I$26>2026,"",SUMPRODUCT(('Retention Calc'!$R$2:$R$2698=$B38)*INDEX('Retention Calc'!$B$2:$Q$2698,0,MATCH($B38+I$26,'Retention Calc'!$B$1:$Q$1,0)))/$C38),"")} | J38: {=IFERROR(IF($B38+J$26>2026,"",SUMPRODUCT(('Retention Calc'!$R$2:$R$2698=$B38)*INDEX('Retention Calc'!$B$2:$Q$2698,0,MATCH($B38+J$26,'Retention Calc'!$B$1:$Q$1,0)))/$C38),"")} | K38: {=IFERROR(IF($B38+K$26>2026,"",SUMPRODUCT(('Retention Calc'!$R$2:$R$2698=$B38)*INDEX('Retention Calc'!$B$2:$Q$2698,0,MATCH($B38+K$26,'Retention Calc'!$B$1:$Q$1,0)))/$C38),"")} | ... S38: {=IFERROR(IF($B38+S$26>2026,"",SUMPRODUCT(('Retention Calc'!$R$2:$R$2698=$B38)*INDEX('Retention Calc'!$B$2:$Q$2698,0,MATCH($B38+S$26,'Retention Calc'!$B$1:$Q$1,0)))/$C38),"")} | V38: ="Year "&11 -> Year 11 | W38: =IF(O27="",NA(),O27) -> 0.30563798 | X38: =IF(O28="",NA(),O28) -> 0.19512195 | Y38: =IF(O29="",NA(),O29) -> 0.1037037 | Z38: =IF(O30="",NA(),O30) -> 0.089285714 | AA38: =IF(O31="",NA(),O31) -> 0.12 | AB38: =IF(O32="",NA(),O32) -> #N/A | AC38: =IF(O33="",NA(),O33) -> #N/A | AD38: =IF(O34="",NA(),O34) -> #N/A | AE38: =IF(O35="",NA(),O35) -> #N/A | AF38: =IF(O36="",NA(),O36) -> #N/A | AG38: =IF(O37="",NA(),O37) -> #N/A | AH38: =IF(O38="",NA(),O38) -> #N/A | AI38: =IF(O39="",NA(),O39) -> #N/A | AJ38: =IF(O40="",NA(),O40) -> #N/A | AK38: =IF(O41="",NA(),O41) -> #N/A | AL38: =IF(O42="",NA(),O42) -> #N/A | AM38: =IF(O43="",NA(),O43) -> 0.19710468 | AN38: ="FY"&B38 -> FY2022
B39: =B38+1 -> 2023 | C39: =COUNTIF('Retention Calc'!$R$2:$R$2698,$B39) -> 168 | D39: {=IFERROR(IF($B39+D$26>2026,"",SUMPRODUCT(('Retention Calc'!$R$2:$R$2698=$B39)*INDEX('Retention Calc'!$B$2:$Q$2698,0,MATCH($B39+D$26,'Retention Calc'!$B$1:$Q$1,0)))/$C39),"")} -> 1 | E39: {=IFERROR(IF($B39+E$26>2026,"",SUMPRODUCT(('Retention Calc'!$R$2:$R$2698=$B39)*INDEX('Retention Calc'!$B$2:$Q$2698,0,MATCH($B39+E$26,'Retention Calc'!$B$1:$Q$1,0)))/$C39),"")} -> 0.28571429 | F39: {=IFERROR(IF($B39+F$26>2026,"",SUMPRODUCT(('Retention Calc'!$R$2:$R$2698=$B39)*INDEX('Retention Calc'!$B$2:$Q$2698,0,MATCH($B39+F$26,'Retention Calc'!$B$1:$Q$1,0)))/$C39),"")} -> 0.18452381 | G39: {=IFERROR(IF($B39+G$26>2026,"",SUMPRODUCT(('Retention Calc'!$R$2:$R$2698=$B39)*INDEX('Retention Calc'!$B$2:$Q$2698,0,MATCH($B39+G$26,'Retention Calc'!$B$1:$Q$1,0)))/$C39),"")} -> 0.16666667 | H39: {=IFERROR(IF($B39+H$26>2026,"",SUMPRODUCT(('Retention Calc'!$R$2:$R$2698=$B39)*INDEX('Retention Calc'!$B$2:$Q$2698,0,MATCH($B39+H$26,'Retention Calc'!$B$1:$Q$1,0)))/$C39),"")} | I39: {=IFERROR(IF($B39+I$26>2026,"",SUMPRODUCT(('Retention Calc'!$R$2:$R$2698=$B39)*INDEX('Retention Calc'!$B$2:$Q$2698,0,MATCH($B39+I$26,'Retention Calc'!$B$1:$Q$1,0)))/$C39),"")} | J39: {=IFERROR(IF($B39+J$26>2026,"",SUMPRODUCT(('Retention Calc'!$R$2:$R$2698=$B39)*INDEX('Retention Calc'!$B$2:$Q$2698,0,MATCH($B39+J$26,'Retention Calc'!$B$1:$Q$1,0)))/$C39),"")} | K39: {=IFERROR(IF($B39+K$26>2026,"",SUMPRODUCT(('Retention Calc'!$R$2:$R$2698=$B39)*INDEX('Retention Calc'!$B$2:$Q$2698,0,MATCH($B39+K$26,'Retention Calc'!$B$1:$Q$1,0)))/$C39),"")} | ... S39: {=IFERROR(IF($B39+S$26>2026,"",SUMPRODUCT(('Retention Calc'!$R$2:$R$2698=$B39)*INDEX('Retention Calc'!$B$2:$Q$2698,0,MATCH($B39+S$26,'Retention Calc'!$B$1:$Q$1,0)))/$C39),"")} | V39: ="Year "&12 -> Year 12 | W39: =IF(P27="",NA(),P27) -> 0.26409496 | X39: =IF(P28="",NA(),P28) -> 0.18902439 | Y39: =IF(P29="",NA(),P29) -> 0.11851852 | Z39: =IF(P30="",NA(),P30) -> 0.10714286 | AA39: =IF(P31="",NA(),P31) -> #N/A | AB39: =IF(P32="",NA(),P32) -> #N/A | AC39: =IF(P33="",NA(),P33) -> #N/A | AD39: =IF(P34="",NA(),P34) -> #N/A | AE39: =IF(P35="",NA(),P35) -> #N/A | AF39: =IF(P36="",NA(),P36) -> #N/A | AG39: =IF(P37="",NA(),P37) -> #N/A | AH39: =IF(P38="",NA(),P38) -> #N/A | AI39: =IF(P39="",NA(),P39) -> #N/A | AJ39: =IF(P40="",NA(),P40) -> #N/A | AK39: =IF(P41="",NA(),P41) -> #N/A | AL39: =IF(P42="",NA(),P42) -> #N/A | AM39: =IF(P43="",NA(),P43) -> 0.19786096 | AN39: ="FY"&B39 -> FY2023
B40: =B39+1 -> 2024 | C40: =COUNTIF('Retention Calc'!$R$2:$R$2698,$B40) -> 123 | D40: {=IFERROR(IF($B40+D$26>2026,"",SUMPRODUCT(('Retention Calc'!$R$2:$R$2698=$B40)*INDEX('Retention Calc'!$B$2:$Q$2698,0,MATCH($B40+D$26,'Retention Calc'!$B$1:$Q$1,0)))/$C40),"")} -> 1 | E40: {=IFERROR(IF($B40+E$26>2026,"",SUMPRODUCT(('Retention Calc'!$R$2:$R$2698=$B40)*INDEX('Retention Calc'!$B$2:$Q$2698,0,MATCH($B40+E$26,'Retention Calc'!$B$1:$Q$1,0)))/$C40),"")} -> 0.30081301 | F40: {=IFERROR(IF($B40+F$26>2026,"",SUMPRODUCT(('Retention Calc'!$R$2:$R$2698=$B40)*INDEX('Retention Calc'!$B$2:$Q$2698,0,MATCH($B40+F$26,'Retention Calc'!$B$1:$Q$1,0)))/$C40),"")} -> 0.2601626 | G40: {=IFERROR(IF($B40+G$26>2026,"",SUMPRODUCT(('Retention Calc'!$R$2:$R$2698=$B40)*INDEX('Retention Calc'!$B$2:$Q$2698,0,MATCH($B40+G$26,'Retention Calc'!$B$1:$Q$1,0)))/$C40),"")} | H40: {=IFERROR(IF($B40+H$26>2026,"",SUMPRODUCT(('Retention Calc'!$R$2:$R$2698=$B40)*INDEX('Retention Calc'!$B$2:$Q$2698,0,MATCH($B40+H$26,'Retention Calc'!$B$1:$Q$1,0)))/$C40),"")} | I40: {=IFERROR(IF($B40+I$26>2026,"",SUMPRODUCT(('Retention Calc'!$R$2:$R$2698=$B40)*INDEX('Retention Calc'!$B$2:$Q$2698,0,MATCH($B40+I$26,'Retention Calc'!$B$1:$Q$1,0)))/$C40),"")} | J40: {=IFERROR(IF($B40+J$26>2026,"",SUMPRODUCT(('Retention Calc'!$R$2:$R$2698=$B40)*INDEX('Retention Calc'!$B$2:$Q$2698,0,MATCH($B40+J$26,'Retention Calc'!$B$1:$Q$1,0)))/$C40),"")} | K40: {=IFERROR(IF($B40+K$26>2026,"",SUMPRODUCT(('Retention Calc'!$R$2:$R$2698=$B40)*INDEX('Retention Calc'!$B$2:$Q$2698,0,MATCH($B40+K$26,'Retention Calc'!$B$1:$Q$1,0)))/$C40),"")} | ... S40: {=IFERROR(IF($B40+S$26>2026,"",SUMPRODUCT(('Retention Calc'!$R$2:$R$2698=$B40)*INDEX('Retention Calc'!$B$2:$Q$2698,0,MATCH($B40+S$26,'Retention Calc'!$B$1:$Q$1,0)))/$C40),"")} | V40: ="Year "&13 -> Year 13 | W40: =IF(Q27="",NA(),Q27) -> 0.24332344 | X40: =IF(Q28="",NA(),Q28) -> 0.17073171 | Y40: =IF(Q29="",NA(),Q29) -> 0.1037037 | Z40: =IF(Q30="",NA(),Q30) -> #N/A | AA40: =IF(Q31="",NA(),Q31) -> #N/A | AB40: =IF(Q32="",NA(),Q32) -> #N/A | AC40: =IF(Q33="",NA(),Q33) -> #N/A | AD40: =IF(Q34="",NA(),Q34) -> #N/A | AE40: =IF(Q35="",NA(),Q35) -> #N/A | AF40: =IF(Q36="",NA(),Q36) -> #N/A | AG40: =IF(Q37="",NA(),Q37) -> #N/A | AH40: =IF(Q38="",NA(),Q38) -> #N/A | AI40: =IF(Q39="",NA(),Q39) -> #N/A | AJ40: =IF(Q40="",NA(),Q40) -> #N/A | AK40: =IF(Q41="",NA(),Q41) -> #N/A | AL40: =IF(Q42="",NA(),Q42) -> #N/A | AM40: =IF(Q43="",NA(),Q43) -> 0.19496855 | AN40: ="FY"&B40 -> FY2024
B41: =B40+1 -> 2025 | C41: =COUNTIF('Retention Calc'!$R$2:$R$2698,$B41) -> 161 | D41: {=IFERROR(IF($B41+D$26>2026,"",SUMPRODUCT(('Retention Calc'!$R$2:$R$2698=$B41)*INDEX('Retention Calc'!$B$2:$Q$2698,0,MATCH($B41+D$26,'Retention Calc'!$B$1:$Q$1,0)))/$C41),"")} -> 1 | E41: {=IFERROR(IF($B41+E$26>2026,"",SUMPRODUCT(('Retention Calc'!$R$2:$R$2698=$B41)*INDEX('Retention Calc'!$B$2:$Q$2698,0,MATCH($B41+E$26,'Retention Calc'!$B$1:$Q$1,0)))/$C41),"")} -> 0.19875776 | F41: {=IFERROR(IF($B41+F$26>2026,"",SUMPRODUCT(('Retention Calc'!$R$2:$R$2698=$B41)*INDEX('Retention Calc'!$B$2:$Q$2698,0,MATCH($B41+F$26,'Retention Calc'!$B$1:$Q$1,0)))/$C41),"")} | G41: {=IFERROR(IF($B41+G$26>2026,"",SUMPRODUCT(('Retention Calc'!$R$2:$R$2698=$B41)*INDEX('Retention Calc'!$B$2:$Q$2698,0,MATCH($B41+G$26,'Retention Calc'!$B$1:$Q$1,0)))/$C41),"")} | H41: {=IFERROR(IF($B41+H$26>2026,"",SUMPRODUCT(('Retention Calc'!$R$2:$R$2698=$B41)*INDEX('Retention Calc'!$B$2:$Q$2698,0,MATCH($B41+H$26,'Retention Calc'!$B$1:$Q$1,0)))/$C41),"")} | I41: {=IFERROR(IF($B41+I$26>2026,"",SUMPRODUCT(('Retention Calc'!$R$2:$R$2698=$B41)*INDEX('Retention Calc'!$B$2:$Q$2698,0,MATCH($B41+I$26,'Retention Calc'!$B$1:$Q$1,0)))/$C41),"")} | J41: {=IFERROR(IF($B41+J$26>2026,"",SUMPRODUCT(('Retention Calc'!$R$2:$R$2698=$B41)*INDEX('Retention Calc'!$B$2:$Q$2698,0,MATCH($B41+J$26,'Retention Calc'!$B$1:$Q$1,0)))/$C41),"")} | K41: {=IFERROR(IF($B41+K$26>2026,"",SUMPRODUCT(('Retention Calc'!$R$2:$R$2698=$B41)*INDEX('Retention Calc'!$B$2:$Q$2698,0,MATCH($B41+K$26,'Retention Calc'!$B$1:$Q$1,0)))/$C41),"")} | ... S41: {=IFERROR(IF($B41+S$26>2026,"",SUMPRODUCT(('Retention Calc'!$R$2:$R$2698=$B41)*INDEX('Retention Calc'!$B$2:$Q$2698,0,MATCH($B41+S$26,'Retention Calc'!$B$1:$Q$1,0)))/$C41),"")} | V41: ="Year "&14 -> Year 14 | W41: =IF(R27="",NA(),R27) -> 0.21958457 | X41: =IF(R28="",NA(),R28) -> 0.16463415 | Y41: =IF(R29="",NA(),R29) -> #N/A | Z41: =IF(R30="",NA(),R30) -> #N/A | AA41: =IF(R31="",NA(),R31) -> #N/A | AB41: =IF(R32="",NA(),R32) -> #N/A | AC41: =IF(R33="",NA(),R33) -> #N/A | AD41: =IF(R34="",NA(),R34) -> #N/A | AE41: =IF(R35="",NA(),R35) -> #N/A | AF41: =IF(R36="",NA(),R36) -> #N/A | AG41: =IF(R37="",NA(),R37) -> #N/A | AH41: =IF(R38="",NA(),R38) -> #N/A | AI41: =IF(R39="",NA(),R39) -> #N/A | AJ41: =IF(R40="",NA(),R40) -> #N/A | AK41: =IF(R41="",NA(),R41) -> #N/A | AL41: =IF(R42="",NA(),R42) -> #N/A | AM41: =IF(R43="",NA(),R43) -> 0.20159681 | AN41: ="FY"&B41 -> FY2025
B42: =B41+1 -> 2026 | C42: =COUNTIF('Retention Calc'!$R$2:$R$2698,$B42) -> 165 | D42: {=IFERROR(IF($B42+D$26>2026,"",SUMPRODUCT(('Retention Calc'!$R$2:$R$2698=$B42)*INDEX('Retention Calc'!$B$2:$Q$2698,0,MATCH($B42+D$26,'Retention Calc'!$B$1:$Q$1,0)))/$C42),"")} -> 1 | E42: {=IFERROR(IF($B42+E$26>2026,"",SUMPRODUCT(('Retention Calc'!$R$2:$R$2698=$B42)*INDEX('Retention Calc'!$B$2:$Q$2698,0,MATCH($B42+E$26,'Retention Calc'!$B$1:$Q$1,0)))/$C42),"")} | F42: {=IFERROR(IF($B42+F$26>2026,"",SUMPRODUCT(('Retention Calc'!$R$2:$R$2698=$B42)*INDEX('Retention Calc'!$B$2:$Q$2698,0,MATCH($B42+F$26,'Retention Calc'!$B$1:$Q$1,0)))/$C42),"")} | G42: {=IFERROR(IF($B42+G$26>2026,"",SUMPRODUCT(('Retention Calc'!$R$2:$R$2698=$B42)*INDEX('Retention Calc'!$B$2:$Q$2698,0,MATCH($B42+G$26,'Retention Calc'!$B$1:$Q$1,0)))/$C42),"")} | H42: {=IFERROR(IF($B42+H$26>2026,"",SUMPRODUCT(('Retention Calc'!$R$2:$R$2698=$B42)*INDEX('Retention Calc'!$B$2:$Q$2698,0,MATCH($B42+H$26,'Retention Calc'!$B$1:$Q$1,0)))/$C42),"")} | I42: {=IFERROR(IF($B42+I$26>2026,"",SUMPRODUCT(('Retention Calc'!$R$2:$R$2698=$B42)*INDEX('Retention Calc'!$B$2:$Q$2698,0,MATCH($B42+I$26,'Retention Calc'!$B$1:$Q$1,0)))/$C42),"")} | J42: {=IFERROR(IF($B42+J$26>2026,"",SUMPRODUCT(('Retention Calc'!$R$2:$R$2698=$B42)*INDEX('Retention Calc'!$B$2:$Q$2698,0,MATCH($B42+J$26,'Retention Calc'!$B$1:$Q$1,0)))/$C42),"")} | K42: {=IFERROR(IF($B42+K$26>2026,"",SUMPRODUCT(('Retention Calc'!$R$2:$R$2698=$B42)*INDEX('Retention Calc'!$B$2:$Q$2698,0,MATCH($B42+K$26,'Retention Calc'!$B$1:$Q$1,0)))/$C42),"")} | ... S42: {=IFERROR(IF($B42+S$26>2026,"",SUMPRODUCT(('Retention Calc'!$R$2:$R$2698=$B42)*INDEX('Retention Calc'!$B$2:$Q$2698,0,MATCH($B42+S$26,'Retention Calc'!$B$1:$Q$1,0)))/$C42),"")} | V42: ="Year "&15 -> Year 15 | W42: =IF(S27="",NA(),S27) -> 0.22255193 | X42: =IF(S28="",NA(),S28) -> #N/A | Y42: =IF(S29="",NA(),S29) -> #N/A | Z42: =IF(S30="",NA(),S30) -> #N/A | AA42: =IF(S31="",NA(),S31) -> #N/A | AB42: =IF(S32="",NA(),S32) -> #N/A | AC42: =IF(S33="",NA(),S33) -> #N/A | AD42: =IF(S34="",NA(),S34) -> #N/A | AE42: =IF(S35="",NA(),S35) -> #N/A | AF42: =IF(S36="",NA(),S36) -> #N/A | AG42: =IF(S37="",NA(),S37) -> #N/A | AH42: =IF(S38="",NA(),S38) -> #N/A | AI42: =IF(S39="",NA(),S39) -> #N/A | AJ42: =IF(S40="",NA(),S40) -> #N/A | AK42: =IF(S41="",NA(),S41) -> #N/A | AL42: =IF(S42="",NA(),S42) -> #N/A | AM42: =IF(S43="",NA(),S43) -> 0.22255193 | AN42: ="FY"&B42 -> FY2026
B43: Blended (weighted avg) | C43: =SUM(C27:C42) -> 2697 | D43: {=IFERROR(SUMPRODUCT($C$27:$C$42,IF(ISNUMBER(D27:D42),D27:D42,0))/SUMPRODUCT($C$27:$C$42,--ISNUMBER(D27:D42)),"")} -> 1 | E43: {=IFERROR(SUMPRODUCT($C$27:$C$42,IF(ISNUMBER(E27:E42),E27:E42,0))/SUMPRODUCT($C$27:$C$42,--ISNUMBER(E27:E42)),"")} -> 0.28554502 | F43: {=IFERROR(SUMPRODUCT($C$27:$C$42,IF(ISNUMBER(F27:F42),F27:F42,0))/SUMPRODUCT($C$27:$C$42,--ISNUMBER(F27:F42)),"")} -> 0.25094897 | G43: {=IFERROR(SUMPRODUCT($C$27:$C$42,IF(ISNUMBER(G27:G42),G27:G42,0))/SUMPRODUCT($C$27:$C$42,--ISNUMBER(G27:G42)),"")} -> 0.23042705 | H43: {=IFERROR(SUMPRODUCT($C$27:$C$42,IF(ISNUMBER(H27:H42),H27:H42,0))/SUMPRODUCT($C$27:$C$42,--ISNUMBER(H27:H42)),"")} -> 0.23269231 | I43: {=IFERROR(SUMPRODUCT($C$27:$C$42,IF(ISNUMBER(I27:I42),I27:I42,0))/SUMPRODUCT($C$27:$C$42,--ISNUMBER(I27:I42)),"")} -> 0.21759747 | J43: {=IFERROR(SUMPRODUCT($C$27:$C$42,IF(ISNUMBER(J27:J42),J27:J42,0))/SUMPRODUCT($C$27:$C$42,--ISNUMBER(J27:J42)),"")} -> 0.19883041 | K43: {=IFERROR(SUMPRODUCT($C$27:$C$42,IF(ISNUMBER(K27:K42),K27:K42,0))/SUMPRODUCT($C$27:$C$42,--ISNUMBER(K27:K42)),"")} -> 0.19056848 | ... S43: {=IFERROR(SUMPRODUCT($C$27:$C$42,IF(ISNUMBER(S27:S42),S27:S42,0))/SUMPRODUCT($C$27:$C$42,--ISNUMBER(S27:S42)),"")} -> 0.22255193

Sheet One-Time Donors
A1: One-Time Donors (exactly one gift, all-time)
A2: 1,457 of 2,697 unique donors gave only once.
A4: Constituent ID | B4: Primary Salutation | C4: Last Name | D4: Gift Date | E4: Gift Amount | F4: Fund | G4: Fiscal Year | H4: Gifts (all-time) | I4: Email | J4: Duplicate Email?
A5: 1891 | B5: The Economic Alliance Foundation DBA Econ Alliance | D5: 46203 | E5: 200 | F5: Fdtn Hancock Honors Unrestr fund | G5: =IF(MONTH(D5)>=7,YEAR(D5)+1,YEAR(D5)) -> 2026 | H5: =COUNTIF('AHCF_Gifts_19952026 (1)'!$A:$A,$A5) -> 1 | I5: =IFERROR(INDEX('AHCF_Gifts_19952026 (1)'!$F:$F,MATCH($A5,'AHCF_Gifts_19952026 (1)'!$A:$A,0))&"","") | J5: =IF($I5="","",IF(COUNTIF($I$5:$I$1461,$I5)>1,"DUPLICATE",""))
A6: 1890 | B6: Michael Greicius | C6: Greicius | D6: 46192 | E6: 518.45 | F6: Foundation General Operations; Margaret Tillery Memorial Scholarship | G6: =IF(MONTH(D6)>=7,YEAR(D6)+1,YEAR(D6)) -> 2026 | H6: =COUNTIF('AHCF_Gifts_19952026 (1)'!$A:$A,$A6) -> 1 | I6: =IFERROR(INDEX('AHCF_Gifts_19952026 (1)'!$F:$F,MATCH($A6,'AHCF_Gifts_19952026 (1)'!$A:$A,0))&"","") -> greicius@stanford.edu | J6: =IF($I6="","",IF(COUNTIF($I$5:$I$1461,$I6)>1,"DUPLICATE",""))
A7: 1889 | B7: Eric | C7: Lofstrand | D7: 46190 | E7: 20 | F7: PSTC Student Emergency Restricted fund | G7: =IF(MONTH(D7)>=7,YEAR(D7)+1,YEAR(D7)) -> 2026 | H7: =COUNTIF('AHCF_Gifts_19952026 (1)'!$A:$A,$A7) -> 1 | I7: =IFERROR(INDEX('AHCF_Gifts_19952026 (1)'!$F:$F,MATCH($A7,'AHCF_Gifts_19952026 (1)'!$A:$A,0))&"","") -> eric.lofstrand@hancockcollege.edu | J7: =IF($I7="","",IF(COUNTIF($I$5:$I$1461,$I7)>1,"DUPLICATE",""))
A8: 1885 | B8: Mayra Bernard | C8: Bernard | D8: 46184 | E8: 10 | F8: PSTC Student Emergency Restricted fund | G8: =IF(MONTH(D8)>=7,YEAR(D8)+1,YEAR(D8)) -> 2026 | H8: =COUNTIF('AHCF_Gifts_19952026 (1)'!$A:$A,$A8) -> 1 | I8: =IFERROR(INDEX('AHCF_Gifts_19952026 (1)'!$F:$F,MATCH($A8,'AHCF_Gifts_19952026 (1)'!$A:$A,0))&"","") -> mcazares_p4@yahoo.com | J8: =IF($I8="","",IF(COUNTIF($I$5:$I$1461,$I8)>1,"DUPLICATE",""))
A9: 1884 | B9: Chris Caratan | C9: Caratan | D9: 46182 | E9: 518.45 | F9: Foundation General Operations; Gary Thompson Music Scholarship | G9: =IF(MONTH(D9)>=7,YEAR(D9)+1,YEAR(D9)) -> 2026 | H9: =COUNTIF('AHCF_Gifts_19952026 (1)'!$A:$A,$A9) -> 1 | I9: =IFERROR(INDEX('AHCF_Gifts_19952026 (1)'!$F:$F,MATCH($A9,'AHCF_Gifts_19952026 (1)'!$A:$A,0))&"","") -> cmcaratan@yahoo.com | J9: =IF($I9="","",IF(COUNTIF($I$5:$I$1461,$I9)>1,"DUPLICATE",""))
A10: 1883 | B10: Ken George | C10: George | D10: 46181 | E10: 10 | F10: PSTC Student Emergency Restricted fund | G10: =IF(MONTH(D10)>=7,YEAR(D10)+1,YEAR(D10)) -> 2026 | H10: =COUNTIF('AHCF_Gifts_19952026 (1)'!$A:$A,$A10) -> 1 | I10: =IFERROR(INDEX('AHCF_Gifts_19952026 (1)'!$F:$F,MATCH($A10,'AHCF_Gifts_19952026 (1)'!$A:$A,0))&"","") -> kgeorge@hancockcollege.edu | J10: =IF($I10="","",IF(COUNTIF($I$5:$I$1461,$I10)>1,"DUPLICATE",""))
A11: 905 | B11: Gerald | C11: Chase | D11: 46178 | E11: 40000 | F11: AHC EMS Program | G11: =IF(MONTH(D11)>=7,YEAR(D11)+1,YEAR(D11)) -> 2026 | H11: =COUNTIF('AHCF_Gifts_19952026 (1)'!$A:$A,$A11) -> 1 | I11: =IFERROR(INDEX('AHCF_Gifts_19952026 (1)'!$F:$F,MATCH($A11,'AHCF_Gifts_19952026 (1)'!$A:$A,0))&"","") | J11: =IF($I11="","",IF(COUNTIF($I$5:$I$1461,$I11)>1,"DUPLICATE",""))
A12: 1882 | B12: Jaret Pinon | C12: Pinon | D12: 46177 | E12: 10 | F12: PSTC Student Emergency Restricted fund | G12: =IF(MONTH(D12)>=7,YEAR(D12)+1,YEAR(D12)) -> 2026 | H12: =COUNTIF('AHCF_Gifts_19952026 (1)'!$A:$A,$A12) -> 1 | I12: =IFERROR(INDEX('AHCF_Gifts_19952026 (1)'!$F:$F,MATCH($A12,'AHCF_Gifts_19952026 (1)'!$A:$A,0))&"","") -> jaretpinon290@gmail.com | J12: =IF($I12="","",IF(COUNTIF($I$5:$I$1461,$I12)>1,"DUPLICATE",""))
A13: 1881 | B13: Eric Johnson | C13: Johnson | D13: 46176 | E13: 31.4 | F13: Foundation General Operations; PSTC Student Emergency Restricted fund | G13: =IF(MONTH(D13)>=7,YEAR(D13)+1,YEAR(D13)) -> 2026 | H13: =COUNTIF('AHCF_Gifts_19952026 (1)'!$A:$A,$A13) -> 1 | I13: =IFERROR(INDEX('AHCF_Gifts_19952026 (1)'!$F:$F,MATCH($A13,'AHCF_Gifts_19952026 (1)'!$A:$A,0))&"","") -> e.w.johnson14@gmail.com | J13: =IF($I13="","",IF(COUNTIF($I$5:$I$1461,$I13)>1,"DUPLICATE",""))
A14: 1879 | B14: Myra | C14: Wapner | D14: 46176 | E14: 25 | F14: Future Teachers Scholarship, SM-LO CA Retired Teachers Assn | G14: =IF(MONTH(D14)>=7,YEAR(D14)+1,YEAR(D14)) -> 2026 | H14: =COUNTIF('AHCF_Gifts_19952026 (1)'!$A:$A,$A14) -> 1 | I14: =IFERROR(INDEX('AHCF_Gifts_19952026 (1)'!$F:$F,MATCH($A14,'AHCF_Gifts_19952026 (1)'!$A:$A,0))&"","") | J14: =IF($I14="","",IF(COUNTIF($I$5:$I$1461,$I14)>1,"DUPLICATE",""))
A15: 1880 | B15: Jesus Valle | C15: Valle | D15: 46176 | E15: 10.67 | F15: Foundation General Operations; PSTC Student Emergency Restricted fund | G15: =IF(MONTH(D15)>=7,YEAR(D15)+1,YEAR(D15)) -> 2026 | H15: =COUNTIF('AHCF_Gifts_19952026 (1)'!$A:$A,$A15) -> 1 | I15: =IFERROR(INDEX('AHCF_Gifts_19952026 (1)'!$F:$F,MATCH($A15,'AHCF_Gifts_19952026 (1)'!$A:$A,0))&"","") -> jvalle19091@gmail.com | J15: =IF($I15="","",IF(COUNTIF($I$5:$I$1461,$I15)>1,"DUPLICATE",""))
A16: 1857 | B16: Christine Calvert | C16: Calvert | D16: 46175 | E16: 21.04 | F16: Foundation General Operations; PSTC Student Emergency Restricted fund | G16: =IF(MONTH(D16)>=7,YEAR(D16)+1,YEAR(D16)) -> 2026 | H16: =COUNTIF('AHCF_Gifts_19952026 (1)'!$A:$A,$A16) -> 1 | I16: =IFERROR(INDEX('AHCF_Gifts_19952026 (1)'!$F:$F,MATCH($A16,'AHCF_Gifts_19952026 (1)'!$A:$A,0))&"","") -> calvertchristine7@yahoo.com | J16: =IF($I16="","",IF(COUNTIF($I$5:$I$1461,$I16)>1,"DUPLICATE",""))
A17: 1874 | B17: Jorge Magana | C17: Magana | D17: 46175 | E17: 10.67 | F17: Foundation General Operations; PSTC Student Emergency Restricted fund | G17: =IF(MONTH(D17)>=7,YEAR(D17)+1,YEAR(D17)) -> 2026 | H17: =COUNTIF('AHCF_Gifts_19952026 (1)'!$A:$A,$A17) -> 1 | I17: =IFERROR(INDEX('AHCF_Gifts_19952026 (1)'!$F:$F,MATCH($A17,'AHCF_Gifts_19952026 (1)'!$A:$A,0))&"","") -> jorge.magana@hancockcollege.edu | J17: =IF($I17="","",IF(COUNTIF($I$5:$I$1461,$I17)>1,"DUPLICATE",""))
... A27: 1861 | B27: Valerio Garcia-Ruiz | C27: Garcia-Ruiz | D27: 46174 | E27: 10 | F27: PSTC Student Emergency Restricted fund | G27: =IF(MONTH(D27)>=7,YEAR(D27)+1,YEAR(D27)) -> 2026 | H27: =COUNTIF('AHCF_Gifts_19952026 (1)'!$A:$A,$A27) -> 1 | I27: =IFERROR(INDEX('AHCF_Gifts_19952026 (1)'!$F:$F,MATCH($A27,'AHCF_Gifts_19952026 (1)'!$A:$A,0))&"","") -> garciavalerio7489@gmail.com | J27: =IF($I27="","",IF(COUNTIF($I$5:$I$1461,$I27)>1,"DUPLICATE",""))
A28: 1856 | B28: D & S Properties | D28: 46160 | E28: 5000 | F28: Merrell Williams Memrl Non Fed Title III Schlrshp Endowment | G28: =IF(MONTH(D28)>=7,YEAR(D28)+1,YEAR(D28)) -> 2026 | H28: =COUNTIF('AHCF_Gifts_19952026 (1)'!$A:$A,$A28) -> 1 | I28: =IFERROR(INDEX('AHCF_Gifts_19952026 (1)'!$F:$F,MATCH($A28,'AHCF_Gifts_19952026 (1)'!$A:$A,0))&"","") | J28: =IF($I28="","",IF(COUNTIF($I$5:$I$1461,$I28)>1,"DUPLICATE",""))
A29: 1855 | B29: Angie Leeper | C29: Leeper | D29: 46158 | E29: 10 | F29: PSTC Student Emergency Restricted fund | G29: =IF(MONTH(D29)>=7,YEAR(D29)+1,YEAR(D29)) -> 2026 | H29: =COUNTIF('AHCF_Gifts_19952026 (1)'!$A:$A,$A29) -> 1 | I29: =IFERROR(INDEX('AHCF_Gifts_19952026 (1)'!$F:$F,MATCH($A29,'AHCF_Gifts_19952026 (1)'!$A:$A,0))&"","") -> angienleep@gmail.com | J29: =IF($I29="","",IF(COUNTIF($I$5:$I$1461,$I29)>1,"DUPLICATE",""))
A30: 1853 | B30: Jan Schultz | C30: Schultz | D30: 46157 | E30: 259.38 | F30: AHC Science Field Studies Program; Foundation General Operations | G30: =IF(MONTH(D30)>=7,YEAR(D30)+1,YEAR(D30)) -> 2026 | H30: =COUNTIF('AHCF_Gifts_19952026 (1)'!$A:$A,$A30) -> 1 | I30: =IFERROR(INDEX('AHCF_Gifts_19952026 (1)'!$F:$F,MATCH($A30,'AHCF_Gifts_19952026 (1)'!$A:$A,0))&"","") -> schultz@sbcc.edu | J30: =IF($I30="","",IF(COUNTIF($I$5:$I$1461,$I30)>1,"DUPLICATE",""))
A31: 1854 | B31: Casey Allen | C31: Allen | D31: 46157 | E31: 20 | F31: PSTC Student Emergency Restricted fund | G31: =IF(MONTH(D31)>=7,YEAR(D31)+1,YEAR(D31)) -> 2026 | H31: =COUNTIF('AHCF_Gifts_19952026 (1)'!$A:$A,$A31) -> 1 | I31: =IFERROR(INDEX('AHCF_Gifts_19952026 (1)'!$F:$F,MATCH($A31,'AHCF_Gifts_19952026 (1)'!$A:$A,0))&"","") -> ca8789@gmail.com | J31: =IF($I31="","",IF(COUNTIF($I$5:$I$1461,$I31)>1,"DUPLICATE",""))
A32: 1846 | B32: Joy Kereakes-Soboslay | C32: Kereakes-Soboslay | D32: 46154 | E32: 10 | F32: PSTC Student Emergency Restricted fund | G32: =IF(MONTH(D32)>=7,YEAR(D32)+1,YEAR(D32)) -> 2026 | H32: =COUNTIF('AHCF_Gifts_19952026 (1)'!$A:$A,$A32) -> 1 | I32: =IFERROR(INDEX('AHCF_Gifts_19952026 (1)'!$F:$F,MATCH($A32,'AHCF_Gifts_19952026 (1)'!$A:$A,0))&"","") -> cjoyksx@gmail.com | J32: =IF($I32="","",IF(COUNTIF($I$5:$I$1461,$I32)>1,"DUPLICATE",""))
A33: 1845 | B33: Herminio | C33: Franquiz | D33: 46136 | E33: 50 | F33: AHC LVC's Beautification Restricted Fund | G33: =IF(MONTH(D33)>=7,YEAR(D33)+1,YEAR(D33)) -> 2026 | H33: =COUNTIF('AHCF_Gifts_19952026 (1)'!$A:$A,$A33) -> 1 | I33: =IFERROR(INDEX('AHCF_Gifts_19952026 (1)'!$F:$F,MATCH($A33,'AHCF_Gifts_19952026 (1)'!$A:$A,0))&"","") | J33: =IF($I33="","",IF(COUNTIF($I$5:$I$1461,$I33)>1,"DUPLICATE",""))
A34: 1844 | B34: Sarah Easton | C34: Easton | D34: 46133 | E34: 250 | F34: Margaret Tillery Memorial Scholarship | G34: =IF(MONTH(D34)>=7,YEAR(D34)+1,YEAR(D34)) -> 2026 | H34: =COUNTIF('AHCF_Gifts_19952026 (1)'!$A:$A,$A34) -> 1 | I34: =IFERROR(INDEX('AHCF_Gifts_19952026 (1)'!$F:$F,MATCH($A34,'AHCF_Gifts_19952026 (1)'!$A:$A,0))&"","") -> seaston@hancockcollege.edu | J34: =IF($I34="","",IF(COUNTIF($I$5:$I$1461,$I34)>1,"DUPLICATE",""))
A35: H01016081 | B35: Mark and Deborah | C35: Jackson | D35: 46133 | E35: 200 | F35: Spike Monument Campaign | G35: =IF(MONTH(D35)>=7,YEAR(D35)+1,YEAR(D35)) -> 2026 | H35: =COUNTIF('AHCF_Gifts_19952026 (1)'!$A:$A,$A35) -> 1 | I35: =IFERROR(INDEX('AHCF_Gifts_19952026 (1)'!$F:$F,MATCH($A35,'AHCF_Gifts_19952026 (1)'!$A:$A,0))&"","") -> fivejaxons@msn.com | J35: =IF($I35="","",IF(COUNTIF($I$5:$I$1461,$I35)>1,"DUPLICATE",""))
A36: 1841 | B36: Michelle Southwick | C36: Southwick | D36: 46121 | E36: 52.12 | F36: Foundation General Operations; Monarch Fund Scholarship | G36: =IF(MONTH(D36)>=7,YEAR(D36)+1,YEAR(D36)) -> 2026 | H36: =COUNTIF('AHCF_Gifts_19952026 (1)'!$A:$A,$A36) -> 1 | I36: =IFERROR(INDEX('AHCF_Gifts_19952026 (1)'!$F:$F,MATCH($A36,'AHCF_Gifts_19952026 (1)'!$A:$A,0))&"","") -> michellesouthwickwood@gmail.co | J36: =IF($I36="","",IF(COUNTIF($I$5:$I$1461,$I36)>1,"DUPLICATE",""))
A37: 1840 | B37: Luis Magana | C37: Magana | D37: 46121 | E37: 26.22 | F37: AHC Swimming & Diving; Foundation General Operations | G37: =IF(MONTH(D37)>=7,YEAR(D37)+1,YEAR(D37)) -> 2026 | H37: =COUNTIF('AHCF_Gifts_19952026 (1)'!$A:$A,$A37) -> 1 | I37: =IFERROR(INDEX('AHCF_Gifts_19952026 (1)'!$F:$F,MATCH($A37,'AHCF_Gifts_19952026 (1)'!$A:$A,0))&"","") -> izzmechito@gmail.com | J37: =IF($I37="","",IF(COUNTIF($I$5:$I$1461,$I37)>1,"DUPLICATE",""))
A38: 1833 | B38: ROOSTSM LLC | D38: 46119 | E38: 333 | F38: Athletic Annl Golf Tournament Restricted | G38: =IF(MONTH(D38)>=7,YEAR(D38)+1,YEAR(D38)) -> 2026 | H38: =COUNTIF('AHCF_Gifts_19952026 (1)'!$A:$A,$A38) -> 1 | I38: =IFERROR(INDEX('AHCF_Gifts_19952026 (1)'!$F:$F,MATCH($A38,'AHCF_Gifts_19952026 (1)'!$A:$A,0))&"","") | J38: =IF($I38="","",IF(COUNTIF($I$5:$I$1461,$I38)>1,"DUPLICATE",""))
A39: 1843 | B39: Frank | C39: Villatoro | D39: 46118 | E39: 175 | F39: Athletic Annl Golf Tournament Restricted | G39: =IF(MONTH(D39)>=7,YEAR(D39)+1,YEAR(D39)) -> 2026 | H39: =COUNTIF('AHCF_Gifts_19952026 (1)'!$A:$A,$A39) -> 1 | I39: =IFERROR(INDEX('AHCF_Gifts_19952026 (1)'!$F:$F,MATCH($A39,'AHCF_Gifts_19952026 (1)'!$A:$A,0))&"","") | J39: =IF($I39="","",IF(COUNTIF($I$5:$I$1461,$I39)>1,"DUPLICATE",""))
A40: 1832 | B40: Berto Vargas | C40: Vargas | D40: 46117 | E40: 103.94 | F40: AHC Swimming & Diving; Foundation General Operations | G40: =IF(MONTH(D40)>=7,YEAR(D40)+1,YEAR(D40)) -> 2026 | H40: =COUNTIF('AHCF_Gifts_19952026 (1)'!$A:$A,$A40) -> 1 | I40: =IFERROR(INDEX('AHCF_Gifts_19952026 (1)'!$F:$F,MATCH($A40,'AHCF_Gifts_19952026 (1)'!$A:$A,0))&"","") -> cowboysfan1904@gmail.com | J40: =IF($I40="","",IF(COUNTIF($I$5:$I$1461,$I40)>1,"DUPLICATE",""))
A41: 1842 | B41: Deckers Outdoor Corporation | D41: 46113 | E41: 25000 | F41: Grants - Deckers Brands | G41: =IF(MONTH(D41)>=7,YEAR(D41)+1,YEAR(D41)) -> 2026 | H41: =COUNTIF('AHCF_Gifts_19952026 (1)'!$A:$A,$A41) -> 1 | I41: =IFERROR(INDEX('AHCF_Gifts_19952026 (1)'!$F:$F,MATCH($A41,'AHCF_Gifts_19952026 (1)'!$A:$A,0))&"","") | J41: =IF($I41="","",IF(COUNTIF($I$5:$I$1461,$I41)>1,"DUPLICATE",""))
A42: 1831 | B42: Jesus | C42: Solorio | D42: 46113 | E42: 500 | F42: AHC Commercial Dance Scholarship | G42: =IF(MONTH(D42)>=7,YEAR(D42)+1,YEAR(D42)) -> 2026 | H42: =COUNTIF('AHCF_Gifts_19952026 (1)'!$A:$A,$A42) -> 1 | I42: =IFERROR(INDEX('AHCF_Gifts_19952026 (1)'!$F:$F,MATCH($A42,'AHCF_Gifts_19952026 (1)'!$A:$A,0))&"","") | J42: =IF($I42="","",IF(COUNTIF($I$5:$I$1461,$I42)>1,"DUPLICATE",""))
A43: 1829 | B43: Mister Car Wash | D43: 46112 | E43: 2500 | F43: AHC Student Emergency Fund | G43: =IF(MONTH(D43)>=7,YEAR(D43)+1,YEAR(D43)) -> 2026 | H43: =COUNTIF('AHCF_Gifts_19952026 (1)'!$A:$A,$A43) -> 1 | I43: =IFERROR(INDEX('AHCF_Gifts_19952026 (1)'!$F:$F,MATCH($A43,'AHCF_Gifts_19952026 (1)'!$A:$A,0))&"","") | J43: =IF($I43="","",IF(COUNTIF($I$5:$I$1461,$I43)>1,"DUPLICATE",""))
A44: 1827 | B44: RK & G Construction | D44: 46112 | E44: 500 | F44: Athletic Annl Golf Tournament Restricted | G44: =IF(MONTH(D44)>=7,YEAR(D44)+1,YEAR(D44)) -> 2026 | H44: =COUNTIF('AHCF_Gifts_19952026 (1)'!$A:$A,$A44) -> 1 | I44: =IFERROR(INDEX('AHCF_Gifts_19952026 (1)'!$F:$F,MATCH($A44,'AHCF_Gifts_19952026 (1)'!$A:$A,0))&"","") | J44: =IF($I44="","",IF(COUNTIF($I$5:$I$1461,$I44)>1,"DUPLICATE",""))
A45: 1828 | B45: Kinyon Construction | D45: 46112 | E45: 500 | F45: Athletic Annl Golf Tournament Restricted | G45: =IF(MONTH(D45)>=7,YEAR(D45)+1,YEAR(D45)) -> 2026 | H45: =COUNTIF('AHCF_Gifts_19952026 (1)'!$A:$A,$A45) -> 1 | I45: =IFERROR(INDEX('AHCF_Gifts_19952026 (1)'!$F:$F,MATCH($A45,'AHCF_Gifts_19952026 (1)'!$A:$A,0))&"","") | J45: =IF($I45="","",IF(COUNTIF($I$5:$I$1461,$I45)>1,"DUPLICATE",""))
A46: 1826 | B46: Martin Cuevas | C46: Cuevas | D46: 46112 | E46: 103.94 | F46: AHC Swimming & Diving; Foundation General Operations | G46: =IF(MONTH(D46)>=7,YEAR(D46)+1,YEAR(D46)) -> 2026 | H46: =COUNTIF('AHCF_Gifts_19952026 (1)'!$A:$A,$A46) -> 1 | I46: =IFERROR(INDEX('AHCF_Gifts_19952026 (1)'!$F:$F,MATCH($A46,'AHCF_Gifts_19952026 (1)'!$A:$A,0))&"","") -> martinc_07@icloud.com | J46: =IF($I46="","",IF(COUNTIF($I$5:$I$1461,$I46)>1,"DUPLICATE",""))
A47: 1830 | B47: Jesse Verdin | C47: Verdin | D47: 46112 | E47: 103.94 | F47: AHC Swimming & Diving; Foundation General Operations | G47: =IF(MONTH(D47)>=7,YEAR(D47)+1,YEAR(D47)) -> 2026 | H47: =COUNTIF('AHCF_Gifts_19952026 (1)'!$A:$A,$A47) -> 1 | I47: =IFERROR(INDEX('AHCF_Gifts_19952026 (1)'!$F:$F,MATCH($A47,'AHCF_Gifts_19952026 (1)'!$A:$A,0))&"","") -> jesseverdin@gmail.com | J47: =IF($I47="","",IF(COUNTIF($I$5:$I$1461,$I47)>1,"DUPLICATE",""))
A48: 1825 | B48: Carry Smee | C48: Smee | D48: 46108 | E48: 103.94 | F48: AHC Swimming & Diving; Foundation General Operations | G48: =IF(MONTH(D48)>=7,YEAR(D48)+1,YEAR(D48)) -> 2026 | H48: =COUNTIF('AHCF_Gifts_19952026 (1)'!$A:$A,$A48) -> 1 | I48: =IFERROR(INDEX('AHCF_Gifts_19952026 (1)'!$F:$F,MATCH($A48,'AHCF_Gifts_19952026 (1)'!$A:$A,0))&"","") -> carry_smee@yahoo.com | J48: =IF($I48="","",IF(COUNTIF($I$5:$I$1461,$I48)>1,"DUPLICATE",""))
A49: 1461 | B49: Katie and Brian | C49: Gorndt | D49: 46107 | E49: 1000 | F49: Spike Monument Campaign | G49: =IF(MONTH(D49)>=7,YEAR(D49)+1,YEAR(D49)) -> 2026 | H49: =COUNTIF('AHCF_Gifts_19952026 (1)'!$A:$A,$A49) -> 1 | I49: =IFERROR(INDEX('AHCF_Gifts_19952026 (1)'!$F:$F,MATCH($A49,'AHCF_Gifts_19952026 (1)'!$A:$A,0))&"","") -> kgorndt@sbch.org | J49: =IF($I49="","",IF(COUNTIF($I$5:$I$1461,$I49)>1,"DUPLICATE",""))
A50: H01640620 | B50: Stephen and Mary | C50: Green | D50: 46104 | E50: 41 | F50: Mr. and Mrs. A.M. DeGasparis Memorial Scholarship | G50: =IF(MONTH(D50)>=7,YEAR(D50)+1,YEAR(D50)) -> 2026 | H50: =COUNTIF('AHCF_Gifts_19952026 (1)'!$A:$A,$A50) -> 1 | I50: =IFERROR(INDEX('AHCF_Gifts_19952026 (1)'!$F:$F,MATCH($A50,'AHCF_Gifts_19952026 (1)'!$A:$A,0))&"","") | J50: =IF($I50="","",IF(COUNTIF($I$5:$I$1461,$I50)>1,"DUPLICATE",""))
A51: 1820 | B51: Brian | C51: Spencer | D51: 46099 | E51: 2500 | F51: Future Teachers Scholarship, SM-LO CA Retired Teachers Assn | G51: =IF(MONTH(D51)>=7,YEAR(D51)+1,YEAR(D51)) -> 2026 | H51: =COUNTIF('AHCF_Gifts_19952026 (1)'!$A:$A,$A51) -> 1 | I51: =IFERROR(INDEX('AHCF_Gifts_19952026 (1)'!$F:$F,MATCH($A51,'AHCF_Gifts_19952026 (1)'!$A:$A,0))&"","") | J51: =IF($I51="","",IF(COUNTIF($I$5:$I$1461,$I51)>1,"DUPLICATE",""))
A52: 1816 | B52: Barbara | C52: Sellers | D52: 46097 | E52: 1000 | F52: Margaret Tillery Memorial Scholarship | G52: =IF(MONTH(D52)>=7,YEAR(D52)+1,YEAR(D52)) -> 2026 | H52: =COUNTIF('AHCF_Gifts_19952026 (1)'!$A:$A,$A52) -> 1 | I52: =IFERROR(INDEX('AHCF_Gifts_19952026 (1)'!$F:$F,MATCH($A52,'AHCF_Gifts_19952026 (1)'!$A:$A,0))&"","") | J52: =IF($I52="","",IF(COUNTIF($I$5:$I$1461,$I52)>1,"DUPLICATE",""))
A53: 1815 | B53: Ari Skinner | C53: Skinner | D53: 46096 | E53: 103.94 | F53: AHC Swimming & Diving; Foundation General Operations | G53: =IF(MONTH(D53)>=7,YEAR(D53)+1,YEAR(D53)) -> 2026 | H53: =COUNTIF('AHCF_Gifts_19952026 (1)'!$A:$A,$A53) -> 1 | I53: =IFERROR(INDEX('AHCF_Gifts_19952026 (1)'!$F:$F,MATCH($A53,'AHCF_Gifts_19952026 (1)'!$A:$A,0))&"","") -> littlearidinner@gmail.com | J53: =IF($I53="","",IF(COUNTIF($I$5:$I$1461,$I53)>1,"DUPLICATE",""))
A54: 1811 | B54: Big Yahu | C54: Yahu | D54: 46094 | E54: 103.94 | F54: AHC Swimming & Diving; Foundation General Operations | G54: =IF(MONTH(D54)>=7,YEAR(D54)+1,YEAR(D54)) -> 2026 | H54: =COUNTIF('AHCF_Gifts_19952026 (1)'!$A:$A,$A54) -> 1 | I54: =IFERROR(INDEX('AHCF_Gifts_19952026 (1)'!$F:$F,MATCH($A54,'AHCF_Gifts_19952026 (1)'!$A:$A,0))&"","") -> tobiaspierce56@gmail.com | J54: =IF($I54="","",IF(COUNTIF($I$5:$I$1461,$I54)>1,"DUPLICATE",""))
A55: 1812 | B55: Lisa Kinney | C55: Kinney | D55: 46094 | E55: 103.94 | F55: AHC Swimming & Diving; Foundation General Operations | G55: =IF(MONTH(D55)>=7,YEAR(D55)+1,YEAR(D55)) -> 2026 | H55: =COUNTIF('AHCF_Gifts_19952026 (1)'!$A:$A,$A55) -> 1 | I55: =IFERROR(INDEX('AHCF_Gifts_19952026 (1)'!$F:$F,MATCH($A55,'AHCF_Gifts_19952026 (1)'!$A:$A,0))&"","") -> ccss4fun@aol.com | J55: =IF($I55="","",IF(COUNTIF($I$5:$I$1461,$I55)>1,"DUPLICATE",""))
A56: 1813 | B56: Brianna Garbiso | C56: Garbiso | D56: 46094 | E56: 78.03 | F56: AHC Swimming & Diving; Foundation General Operations | G56: =IF(MONTH(D56)>=7,YEAR(D56)+1,YEAR(D56)) -> 2026 | H56: =COUNTIF('AHCF_Gifts_19952026 (1)'!$A:$A,$A56) -> 1 | I56: =IFERROR(INDEX('AHCF_Gifts_19952026 (1)'!$F:$F,MATCH($A56,'AHCF_Gifts_19952026 (1)'!$A:$A,0))&"","") -> bgarbiso3@gmail.com | J56: =IF($I56="","",IF(COUNTIF($I$5:$I$1461,$I56)>1,"DUPLICATE",""))
A57: 1810 | B57: Jersey Mike's | D57: 46093 | E57: 1000 | F57: Athletic Annl Golf Tournament Restricted | G57: =IF(MONTH(D57)>=7,YEAR(D57)+1,YEAR(D57)) -> 2026 | H57: =COUNTIF('AHCF_Gifts_19952026 (1)'!$A:$A,$A57) -> 1 | I57: =IFERROR(INDEX('AHCF_Gifts_19952026 (1)'!$F:$F,MATCH($A57,'AHCF_Gifts_19952026 (1)'!$A:$A,0))&"","") | J57: =IF($I57="","",IF(COUNTIF($I$5:$I$1461,$I57)>1,"DUPLICATE",""))
A58: 1809 | B58: Thomas | C58: Mott | D58: 46092 | E58: 700 | F58: Athletic Annl Golf Tournament Restricted | G58: =IF(MONTH(D58)>=7,YEAR(D58)+1,YEAR(D58)) -> 2026 | H58: =COUNTIF('AHCF_Gifts_19952026 (1)'!$A:$A,$A58) -> 1 | I58: =IFERROR(INDEX('AHCF_Gifts_19952026 (1)'!$F:$F,MATCH($A58,'AHCF_Gifts_19952026 (1)'!$A:$A,0))&"","") | J58: =IF($I58="","",IF(COUNTIF($I$5:$I$1461,$I58)>1,"DUPLICATE",""))
A59: 1803 | B59: Carolyn Urban | C59: Urban | D59: 46092 | E59: 500 | F59: Karisa Bennett Memorial Scholarship Endowment | G59: =IF(MONTH(D59)>=7,YEAR(D59)+1,YEAR(D59)) -> 2026 | H59: =COUNTIF('AHCF_Gifts_19952026 (1)'!$A:$A,$A59) -> 1 | I59: =IFERROR(INDEX('AHCF_Gifts_19952026 (1)'!$F:$F,MATCH($A59,'AHCF_Gifts_19952026 (1)'!$A:$A,0))&"","") -> r2c2.nabru23030@yahoo.com | J59: =IF($I59="","",IF(COUNTIF($I$5:$I$1461,$I59)>1,"DUPLICATE",""))
A60: 1814 | B60: Flight Academy Volleyball | D60: 46092 | E60: 400 | F60: Athletic Annl Golf Tournament Restricted | G60: =IF(MONTH(D60)>=7,YEAR(D60)+1,YEAR(D60)) -> 2026 | H60: =COUNTIF('AHCF_Gifts_19952026 (1)'!$A:$A,$A60) -> 1 | I60: =IFERROR(INDEX('AHCF_Gifts_19952026 (1)'!$F:$F,MATCH($A60,'AHCF_Gifts_19952026 (1)'!$A:$A,0))&"","") | J60: =IF($I60="","",IF(COUNTIF($I$5:$I$1461,$I60)>1,"DUPLICATE",""))
A61: 1804 | B61: Pamela Polowy | C61: Polowy | D61: 46092 | E61: 26.22 | F61: AHC Swimming & Diving; Foundation General Operations | G61: =IF(MONTH(D61)>=7,YEAR(D61)+1,YEAR(D61)) -> 2026 | H61: =COUNTIF('AHCF_Gifts_19952026 (1)'!$A:$A,$A61) -> 1 | I61: =IFERROR(INDEX('AHCF_Gifts_19952026 (1)'!$F:$F,MATCH($A61,'AHCF_Gifts_19952026 (1)'!$A:$A,0))&"","") -> polowypam@gmail.com | J61: =IF($I61="","",IF(COUNTIF($I$5:$I$1461,$I61)>1,"DUPLICATE",""))
A62: 1802 | B62: Clay's Septic and Jetting, Inc | D62: 46091 | E62: 1000 | F62: Athletic Annl Golf Tournament Restricted | G62: =IF(MONTH(D62)>=7,YEAR(D62)+1,YEAR(D62)) -> 2026 | H62: =COUNTIF('AHCF_Gifts_19952026 (1)'!$A:$A,$A62) -> 1 | I62: =IFERROR(INDEX('AHCF_Gifts_19952026 (1)'!$F:$F,MATCH($A62,'AHCF_Gifts_19952026 (1)'!$A:$A,0))&"","") -> Lynda@clays-septic.com | J62: =IF($I62="","",IF(COUNTIF($I$5:$I$1461,$I62)>1,"DUPLICATE",""))
A63: 1801 | B63: Ianna Calderon | C63: Calderon | D63: 46089 | E63: 103.94 | F63: AHC Swimming & Diving; Foundation General Operations | G63: =IF(MONTH(D63)>=7,YEAR(D63)+1,YEAR(D63)) -> 2026 | H63: =COUNTIF('AHCF_Gifts_19952026 (1)'!$A:$A,$A63) -> 1 | I63: =IFERROR(INDEX('AHCF_Gifts_19952026 (1)'!$F:$F,MATCH($A63,'AHCF_Gifts_19952026 (1)'!$A:$A,0))&"","") -> iannacalderon07@gmail.com | J63: =IF($I63="","",IF(COUNTIF($I$5:$I$1461,$I63)>1,"DUPLICATE",""))
A64: 1808 | B64: Primus Solutions | D64: 46088 | E64: 400 | F64: Athletic Annl Golf Tournament Restricted | G64: =IF(MONTH(D64)>=7,YEAR(D64)+1,YEAR(D64)) -> 2026 | H64: =COUNTIF('AHCF_Gifts_19952026 (1)'!$A:$A,$A64) -> 1 | I64: =IFERROR(INDEX('AHCF_Gifts_19952026 (1)'!$F:$F,MATCH($A64,'AHCF_Gifts_19952026 (1)'!$A:$A,0))&"","") | J64: =IF($I64="","",IF(COUNTIF($I$5:$I$1461,$I64)>1,"DUPLICATE",""))
A65: 1800 | B65: Weston Guerra | C65: Guerra | D65: 46088 | E65: 259.38 | F65: Foundation General Operations; Margaret Tillery Memorial Scholarship | G65: =IF(MONTH(D65)>=7,YEAR(D65)+1,YEAR(D65)) -> 2026 | H65: =COUNTIF('AHCF_Gifts_19952026 (1)'!$A:$A,$A65) -> 1 | I65: =IFERROR(INDEX('AHCF_Gifts_19952026 (1)'!$F:$F,MATCH($A65,'AHCF_Gifts_19952026 (1)'!$A:$A,0))&"","") -> westonbguerra@gmail.com | J65: =IF($I65="","",IF(COUNTIF($I$5:$I$1461,$I65)>1,"DUPLICATE",""))
A66: 1799 | B66: Rosa Gaytan | C66: Gaytan | D66: 46085 | E66: 103.94 | F66: AHC Swimming & Diving; Foundation General Operations | G66: =IF(MONTH(D66)>=7,YEAR(D66)+1,YEAR(D66)) -> 2026 | H66: =COUNTIF('AHCF_Gifts_19952026 (1)'!$A:$A,$A66) -> 1 | I66: =IFERROR(INDEX('AHCF_Gifts_19952026 (1)'!$F:$F,MATCH($A66,'AHCF_Gifts_19952026 (1)'!$A:$A,0))&"","") -> rosamariagaytan1973@gmail.com | J66: =IF($I66="","",IF(COUNTIF($I$5:$I$1461,$I66)>1,"DUPLICATE",""))
A67: 1798 | B67: Jillian Knight | C67: Knight | D67: 46084 | E67: 103.94 | F67: AHC Swimming & Diving; Foundation General Operations | G67: =IF(MONTH(D67)>=7,YEAR(D67)+1,YEAR(D67)) -> 2026 | H67: =COUNTIF('AHCF_Gifts_19952026 (1)'!$A:$A,$A67) -> 1 | I67: =IFERROR(INDEX('AHCF_Gifts_19952026 (1)'!$F:$F,MATCH($A67,'AHCF_Gifts_19952026 (1)'!$A:$A,0))&"","") -> jillian.knight@comcast.net | J67: =IF($I67="","",IF(COUNTIF($I$5:$I$1461,$I67)>1,"DUPLICATE",""))
A68: 1797 | B68: ABV Scoreboard Services, Inc | D68: 46083 | E68: 1000 | F68: Athletic Annl Golf Tournament Restricted | G68: =IF(MONTH(D68)>=7,YEAR(D68)+1,YEAR(D68)) -> 2026 | H68: =COUNTIF('AHCF_Gifts_19952026 (1)'!$A:$A,$A68) -> 1 | I68: =IFERROR(INDEX('AHCF_Gifts_19952026 (1)'!$F:$F,MATCH($A68,'AHCF_Gifts_19952026 (1)'!$A:$A,0))&"","") -> jalfino@abservices.net | J68: =IF($I68="","",IF(COUNTIF($I$5:$I$1461,$I68)>1,"DUPLICATE",""))
A69: 1795 | B69: Allen Maris | C69: Maris | D69: 46078 | E69: 103.94 | F69: Allan Hancock College Athletic Program; Foundation General Operations | G69: =IF(MONTH(D69)>=7,YEAR(D69)+1,YEAR(D69)) -> 2026 | H69: =COUNTIF('AHCF_Gifts_19952026 (1)'!$A:$A,$A69) -> 1 | I69: =IFERROR(INDEX('AHCF_Gifts_19952026 (1)'!$F:$F,MATCH($A69,'AHCF_Gifts_19952026 (1)'!$A:$A,0))&"","") -> allenmaris@gmail.com | J69: =IF($I69="","",IF(COUNTIF($I$5:$I$1461,$I69)>1,"DUPLICATE",""))
A70: 1796 | B70: Santa Barbara County Office of Arts & Culture | D70: 46077 | E70: 750 | F70: Allan Hancock College Art Program | G70: =IF(MONTH(D70)>=7,YEAR(D70)+1,YEAR(D70)) -> 2026 | H70: =COUNTIF('AHCF_Gifts_19952026 (1)'!$A:$A,$A70) -> 1 | I70: =IFERROR(INDEX('AHCF_Gifts_19952026 (1)'!$F:$F,MATCH($A70,'AHCF_Gifts_19952026 (1)'!$A:$A,0))&"","") | J70: =IF($I70="","",IF(COUNTIF($I$5:$I$1461,$I70)>1,"DUPLICATE",""))
A71: 1794 | B71: Pets Urgent Care | D71: 46071 | E71: 400 | F71: Athletic Annl Golf Tournament Restricted | G71: =IF(MONTH(D71)>=7,YEAR(D71)+1,YEAR(D71)) -> 2026 | H71: =COUNTIF('AHCF_Gifts_19952026 (1)'!$A:$A,$A71) -> 1 | I71: =IFERROR(INDEX('AHCF_Gifts_19952026 (1)'!$F:$F,MATCH($A71,'AHCF_Gifts_19952026 (1)'!$A:$A,0))&"","") -> mw.petsurgentcare@gmail.com | J71: =IF($I71="","",IF(COUNTIF($I$5:$I$1461,$I71)>1,"DUPLICATE",""))
A72: 1793 | B72: CalRTA Santa Maria Division 17 | D72: 46065 | E72: 300 | F72: Future Teachers Scholarship, SM-LO CA Retired Teachers Assn | G72: =IF(MONTH(D72)>=7,YEAR(D72)+1,YEAR(D72)) -> 2026 | H72: =COUNTIF('AHCF_Gifts_19952026 (1)'!$A:$A,$A72) -> 1 | I72: =IFERROR(INDEX('AHCF_Gifts_19952026 (1)'!$F:$F,MATCH($A72,'AHCF_Gifts_19952026 (1)'!$A:$A,0))&"","") | J72: =IF($I72="","",IF(COUNTIF($I$5:$I$1461,$I72)>1,"DUPLICATE",""))
A73: 1791 | B73: Kathleen Mulligan | C73: Mulligan | D73: 46058 | E73: 52.12 | F73: Foundation General Operations; Margaret Tillery Memorial Scholarship | G73: =IF(MONTH(D73)>=7,YEAR(D73)+1,YEAR(D73)) -> 2026 | H73: =COUNTIF('AHCF_Gifts_19952026 (1)'!$A:$A,$A73) -> 1 | I73: =IFERROR(INDEX('AHCF_Gifts_19952026 (1)'!$F:$F,MATCH($A73,'AHCF_Gifts_19952026 (1)'!$A:$A,0))&"","") -> kmulligan@ithaca.edu | J73: =IF($I73="","",IF(COUNTIF($I$5:$I$1461,$I73)>1,"DUPLICATE",""))
A74: 1790 | B74: Nutanix | D74: 46056 | E74: 250 | F74: Foundation Restricted Clearing Fund | G74: =IF(MONTH(D74)>=7,YEAR(D74)+1,YEAR(D74)) -> 2026 | H74: =COUNTIF('AHCF_Gifts_19952026 (1)'!$A:$A,$A74) -> 1 | I74: =IFERROR(INDEX('AHCF_Gifts_19952026 (1)'!$F:$F,MATCH($A74,'AHCF_Gifts_19952026 (1)'!$A:$A,0))&"","") | J74: =IF($I74="","",IF(COUNTIF($I$5:$I$1461,$I74)>1,"DUPLICATE",""))
A75: 1789 | B75: Gregory | C75: Verch | D75: 46052 | E75: 200 | F75: Athletic Annl Golf Tournament Restricted | G75: =IF(MONTH(D75)>=7,YEAR(D75)+1,YEAR(D75)) -> 2026 | H75: =COUNTIF('AHCF_Gifts_19952026 (1)'!$A:$A,$A75) -> 1 | I75: =IFERROR(INDEX('AHCF_Gifts_19952026 (1)'!$F:$F,MATCH($A75,'AHCF_Gifts_19952026 (1)'!$A:$A,0))&"","") -> verchteach@gmail.com | J75: =IF($I75="","",IF(COUNTIF($I$5:$I$1461,$I75)>1,"DUPLICATE",""))
A76: 1788 | B76: Chick-fil-A Enos Ranch and 101 & Broadway | D76: 46039 | E76: 2000 | F76: Chick-fil-A Opportunity Scholarship | G76: =IF(MONTH(D76)>=7,YEAR(D76)+1,YEAR(D76)) -> 2026 | H76: =COUNTIF('AHCF_Gifts_19952026 (1)'!$A:$A,$A76) -> 1 | I76: =IFERROR(INDEX('AHCF_Gifts_19952026 (1)'!$F:$F,MATCH($A76,'AHCF_Gifts_19952026 (1)'!$A:$A,0))&"","") | J76: =IF($I76="","",IF(COUNTIF($I$5:$I$1461,$I76)>1,"DUPLICATE",""))
A77: 1787 | B77: Pismo Beach Hospitality Association | D77: 46038 | E77: 500 | F77: General Scholarship | G77: =IF(MONTH(D77)>=7,YEAR(D77)+1,YEAR(D77)) -> 2026 | H77: =COUNTIF('AHCF_Gifts_19952026 (1)'!$A:$A,$A77) -> 1 | I77: =IFERROR(INDEX('AHCF_Gifts_19952026 (1)'!$F:$F,MATCH($A77,'AHCF_Gifts_19952026 (1)'!$A:$A,0))&"","") -> colleen@ccchotels.com | J77: =IF($I77="","",IF(COUNTIF($I$5:$I$1461,$I77)>1,"DUPLICATE",""))
A78: 1785 | B78: JoAnn Grau | C78: Grau | D78: 46037 | E78: 103.94 | F78: Foundation General Operations; Foundation Restricted Clearing Fund | G78: =IF(MONTH(D78)>=7,YEAR(D78)+1,YEAR(D78)) -> 2026 | H78: =COUNTIF('AHCF_Gifts_19952026 (1)'!$A:$A,$A78) -> 1 | I78: =IFERROR(INDEX('AHCF_Gifts_19952026 (1)'!$F:$F,MATCH($A78,'AHCF_Gifts_19952026 (1)'!$A:$A,0))&"","") -> graujo@aol.com | J78: =IF($I78="","",IF(COUNTIF($I$5:$I$1461,$I78)>1,"DUPLICATE",""))
A79: 1783 | B79: Nancy Mason | C79: Mason | D79: 46035 | E79: 103.94 | F79: Foundation General Operations; Foundation Restricted Clearing Fund | G79: =IF(MONTH(D79)>=7,YEAR(D79)+1,YEAR(D79)) -> 2026 | H79: =COUNTIF('AHCF_Gifts_19952026 (1)'!$A:$A,$A79) -> 1 | I79: =IFERROR(INDEX('AHCF_Gifts_19952026 (1)'!$F:$F,MATCH($A79,'AHCF_Gifts_19952026 (1)'!$A:$A,0))&"","") -> Nancy.mason@me.com | J79: =IF($I79="","",IF(COUNTIF($I$5:$I$1461,$I79)>1,"DUPLICATE",""))
A80: 1781 | B80: Daniel Mason | C80: Mason | D80: 46035 | E80: 50 | F80: Foundation Restricted Clearing Fund | G80: =IF(MONTH(D80)>=7,YEAR(D80)+1,YEAR(D80)) -> 2026 | H80: =COUNTIF('AHCF_Gifts_19952026 (1)'!$A:$A,$A80) -> 1 | I80: =IFERROR(INDEX('AHCF_Gifts_19952026 (1)'!$F:$F,MATCH($A80,'AHCF_Gifts_19952026 (1)'!$A:$A,0))&"","") -> kacomason@comcast.net | J80: =IF($I80="","",IF(COUNTIF($I$5:$I$1461,$I80)>1,"DUPLICATE",""))
A81: 1780 | B81: Diane | C81: Miller | D81: 46032 | E81: 155.75 | F81: Foundation General Operations; Foundation Restricted Clearing Fund | G81: =IF(MONTH(D81)>=7,YEAR(D81)+1,YEAR(D81)) -> 2026 | H81: =COUNTIF('AHCF_Gifts_19952026 (1)'!$A:$A,$A81) -> 1 | I81: =IFERROR(INDEX('AHCF_Gifts_19952026 (1)'!$F:$F,MATCH($A81,'AHCF_Gifts_19952026 (1)'!$A:$A,0))&"","") -> sasyangel3@yahoo.com | J81: =IF($I81="","",IF(COUNTIF($I$5:$I$1461,$I81)>1,"DUPLICATE",""))
A82: 1786 | B82: Rob | C82: Grant | D82: 46028 | E82: 700 | F82: Athletic Annl Golf Tournament Restricted | G82: =IF(MONTH(D82)>=7,YEAR(D82)+1,YEAR(D82)) -> 2026 | H82: =COUNTIF('AHCF_Gifts_19952026 (1)'!$A:$A,$A82) -> 1 | I82: =IFERROR(INDEX('AHCF_Gifts_19952026 (1)'!$F:$F,MATCH($A82,'AHCF_Gifts_19952026 (1)'!$A:$A,0))&"","") -> rob@vintageab.com | J82: =IF($I82="","",IF(COUNTIF($I$5:$I$1461,$I82)>1,"DUPLICATE",""))
A83: 1776 | B83: Bonnie | C83: Mancini | D83: 46028 | E83: 155.75 | F83: Foundation General Operations; Foundation Restricted Clearing Fund | G83: =IF(MONTH(D83)>=7,YEAR(D83)+1,YEAR(D83)) -> 2026 | H83: =COUNTIF('AHCF_Gifts_19952026 (1)'!$A:$A,$A83) -> 1 | I83: =IFERROR(INDEX('AHCF_Gifts_19952026 (1)'!$F:$F,MATCH($A83,'AHCF_Gifts_19952026 (1)'!$A:$A,0))&"","") -> bonniechristina@gmail.com | J83: =IF($I83="","",IF(COUNTIF($I$5:$I$1461,$I83)>1,"DUPLICATE",""))
A84: 1775 | B84: The 3 Falconeers | D84: 46028 | E84: 103.94 | F84: Foundation General Operations; Foundation Restricted Clearing Fund | G84: =IF(MONTH(D84)>=7,YEAR(D84)+1,YEAR(D84)) -> 2026 | H84: =COUNTIF('AHCF_Gifts_19952026 (1)'!$A:$A,$A84) -> 1 | I84: =IFERROR(INDEX('AHCF_Gifts_19952026 (1)'!$F:$F,MATCH($A84,'AHCF_Gifts_19952026 (1)'!$A:$A,0))&"","") | J84: =IF($I84="","",IF(COUNTIF($I$5:$I$1461,$I84)>1,"DUPLICATE",""))
A85: 1770 | B85: Bree Jansen | C85: Jansen | D85: 46026 | E85: 52.12 | F85: Foundation General Operations; Foundation Restricted Clearing Fund | G85: =IF(MONTH(D85)>=7,YEAR(D85)+1,YEAR(D85)) -> 2026 | H85: =COUNTIF('AHCF_Gifts_19952026 (1)'!$A:$A,$A85) -> 1 | I85: =IFERROR(INDEX('AHCF_Gifts_19952026 (1)'!$F:$F,MATCH($A85,'AHCF_Gifts_19952026 (1)'!$A:$A,0))&"","") -> jansen5678@gmail.com | J85: =IF($I85="","",IF(COUNTIF($I$5:$I$1461,$I85)>1,"DUPLICATE",""))
A86: 1767 | B86: Ellen Rilla-Laherty | C86: Rilla-Laherty | D86: 46024 | E86: 829.33 | F86: Foundation General Operations; Foundation Restricted Clearing Fund | G86: =IF(MONTH(D86)>=7,YEAR(D86)+1,YEAR(D86)) -> 2026 | H86: =COUNTIF('AHCF_Gifts_19952026 (1)'!$A:$A,$A86) -> 1 | I86: =IFERROR(INDEX('AHCF_Gifts_19952026 (1)'!$F:$F,MATCH($A86,'AHCF_Gifts_19952026 (1)'!$A:$A,0))&"","") -> erilla@me.com | J86: =IF($I86="","",IF(COUNTIF($I$5:$I$1461,$I86)>1,"DUPLICATE",""))
A87: 1769 | B87: Dianna DeLany | C87: DeLany | D87: 46024 | E87: 259.38 | F87: Foundation General Operations; Foundation Restricted Clearing Fund | G87: =IF(MONTH(D87)>=7,YEAR(D87)+1,YEAR(D87)) -> 2026 | H87: =COUNTIF('AHCF_Gifts_19952026 (1)'!$A:$A,$A87) -> 1 | I87: =IFERROR(INDEX('AHCF_Gifts_19952026 (1)'!$F:$F,MATCH($A87,'AHCF_Gifts_19952026 (1)'!$A:$A,0))&"","") -> 1970Dianna@att.net | J87: =IF($I87="","",IF(COUNTIF($I$5:$I$1461,$I87)>1,"DUPLICATE",""))
A88: 1768 | B88: Steve Grau | C88: Grau | D88: 46024 | E88: 155.75 | F88: Foundation General Operations; Foundation Restricted Clearing Fund | G88: =IF(MONTH(D88)>=7,YEAR(D88)+1,YEAR(D88)) -> 2026 | H88: =COUNTIF('AHCF_Gifts_19952026 (1)'!$A:$A,$A88) -> 1 | I88: =IFERROR(INDEX('AHCF_Gifts_19952026 (1)'!$F:$F,MATCH($A88,'AHCF_Gifts_19952026 (1)'!$A:$A,0))&"","") -> sgrau33@gmail.com | J88: =IF($I88="","",IF(COUNTIF($I$5:$I$1461,$I88)>1,"DUPLICATE",""))
A89: 1782 | B89: Elaine | C89: Bozanich | D89: 46022 | E89: 500 | F89: Ronald R Wilkins Memorial Scholarship | G89: =IF(MONTH(D89)>=7,YEAR(D89)+1,YEAR(D89)) -> 2026 | H89: =COUNTIF('AHCF_Gifts_19952026 (1)'!$A:$A,$A89) -> 1 | I89: =IFERROR(INDEX('AHCF_Gifts_19952026 (1)'!$F:$F,MATCH($A89,'AHCF_Gifts_19952026 (1)'!$A:$A,0))&"","") -> ebozanich@yahoo.com | J89: =IF($I89="","",IF(COUNTIF($I$5:$I$1461,$I89)>1,"DUPLICATE",""))
A90: 1765 | B90: Sarah | C90: Barthel | D90: 46022 | E90: 207.56 | F90: Foundation General Operations; Foundation Restricted Clearing Fund | G90: =IF(MONTH(D90)>=7,YEAR(D90)+1,YEAR(D90)) -> 2026 | H90: =COUNTIF('AHCF_Gifts_19952026 (1)'!$A:$A,$A90) -> 1 | I90: =IFERROR(INDEX('AHCF_Gifts_19952026 (1)'!$F:$F,MATCH($A90,'AHCF_Gifts_19952026 (1)'!$A:$A,0))&"","") -> sarahambarthel@gmail.com | J90: =IF($I90="","",IF(COUNTIF($I$5:$I$1461,$I90)>1,"DUPLICATE",""))
A91: 1773 | B91: Sandee | C91: Sesto | D91: 46022 | E91: 150 | F91: Foundation Restricted Clearing Fund | G91: =IF(MONTH(D91)>=7,YEAR(D91)+1,YEAR(D91)) -> 2026 | H91: =COUNTIF('AHCF_Gifts_19952026 (1)'!$A:$A,$A91) -> 1 | I91: =IFERROR(INDEX('AHCF_Gifts_19952026 (1)'!$F:$F,MATCH($A91,'AHCF_Gifts_19952026 (1)'!$A:$A,0))&"","") | J91: =IF($I91="","",IF(COUNTIF($I$5:$I$1461,$I91)>1,"DUPLICATE",""))
A92: 1645 | B92: Patricia | C92: Keelean | D92: 46022 | E92: 103.94 | F92: Foundation Annual Fund Unrestricted; Foundation General Operations | G92: =IF(MONTH(D92)>=7,YEAR(D92)+1,YEAR(D92)) -> 2026 | H92: =COUNTIF('AHCF_Gifts_19952026 (1)'!$A:$A,$A92) -> 1 | I92: =IFERROR(INDEX('AHCF_Gifts_19952026 (1)'!$F:$F,MATCH($A92,'AHCF_Gifts_19952026 (1)'!$A:$A,0))&"","") -> pkeelean@communifysb.org | J92: =IF($I92="","",IF(COUNTIF($I$5:$I$1461,$I92)>1,"DUPLICATE",""))
A93: 1777 | B93: Cisco | D93: 46021 | E93: 3000 | F93: Foundation Restricted Clearing Fund | G93: =IF(MONTH(D93)>=7,YEAR(D93)+1,YEAR(D93)) -> 2026 | H93: =COUNTIF('AHCF_Gifts_19952026 (1)'!$A:$A,$A93) -> 1 | I93: =IFERROR(INDEX('AHCF_Gifts_19952026 (1)'!$F:$F,MATCH($A93,'AHCF_Gifts_19952026 (1)'!$A:$A,0))&"","") | J93: =IF($I93="","",IF(COUNTIF($I$5:$I$1461,$I93)>1,"DUPLICATE",""))
A94: 1764 | B94: Sharon | C94: Lutz | D94: 46021 | E94: 518.45 | F94: AHC Choir Scholarship; Foundation General Operations | G94: =IF(MONTH(D94)>=7,YEAR(D94)+1,YEAR(D94)) -> 2026 | H94: =COUNTIF('AHCF_Gifts_19952026 (1)'!$A:$A,$A94) -> 1 | I94: =IFERROR(INDEX('AHCF_Gifts_19952026 (1)'!$F:$F,MATCH($A94,'AHCF_Gifts_19952026 (1)'!$A:$A,0))&"","") -> lutzskl@aol.com | J94: =IF($I94="","",IF(COUNTIF($I$5:$I$1461,$I94)>1,"DUPLICATE",""))
A95: 1761 | B95: Jason | C95: Hansen | D95: 46020 | E95: 259.38 | F95: Foundation General Operations; Foundation Restricted Clearing Fund | G95: =IF(MONTH(D95)>=7,YEAR(D95)+1,YEAR(D95)) -> 2026 | H95: =COUNTIF('AHCF_Gifts_19952026 (1)'!$A:$A,$A95) -> 1 | I95: =IFERROR(INDEX('AHCF_Gifts_19952026 (1)'!$F:$F,MATCH($A95,'AHCF_Gifts_19952026 (1)'!$A:$A,0))&"","") -> perlhack40@gmail.com | J95: =IF($I95="","",IF(COUNTIF($I$5:$I$1461,$I95)>1,"DUPLICATE",""))
A96: 1762 | B96: Meagan Dean | C96: Dean | D96: 46020 | E96: 155.75 | F96: Foundation General Operations; Foundation Restricted Clearing Fund | G96: =IF(MONTH(D96)>=7,YEAR(D96)+1,YEAR(D96)) -> 2026 | H96: =COUNTIF('AHCF_Gifts_19952026 (1)'!$A:$A,$A96) -> 1 | I96: =IFERROR(INDEX('AHCF_Gifts_19952026 (1)'!$F:$F,MATCH($A96,'AHCF_Gifts_19952026 (1)'!$A:$A,0))&"","") -> deanfam4@gmail.com | J96: =IF($I96="","",IF(COUNTIF($I$5:$I$1461,$I96)>1,"DUPLICATE",""))
A97: 1763 | B97: Alice | C97: Thio | D97: 46020 | E97: 52.12 | F97: Foundation General Operations; Foundation Restricted Clearing Fund | G97: =IF(MONTH(D97)>=7,YEAR(D97)+1,YEAR(D97)) -> 2026 | H97: =COUNTIF('AHCF_Gifts_19952026 (1)'!$A:$A,$A97) -> 1 | I97: =IFERROR(INDEX('AHCF_Gifts_19952026 (1)'!$F:$F,MATCH($A97,'AHCF_Gifts_19952026 (1)'!$A:$A,0))&"","") -> yummydurians@yahoo.com | J97: =IF($I97="","",IF(COUNTIF($I$5:$I$1461,$I97)>1,"DUPLICATE",""))
A98: 1760 | B98: Tyler | C98: Almaguer | D98: 46016 | E98: 155.75 | F98: Bulldog Pride Scholarship; Foundation General Operations | G98: =IF(MONTH(D98)>=7,YEAR(D98)+1,YEAR(D98)) -> 2026 | H98: =COUNTIF('AHCF_Gifts_19952026 (1)'!$A:$A,$A98) -> 1 | I98: =IFERROR(INDEX('AHCF_Gifts_19952026 (1)'!$F:$F,MATCH($A98,'AHCF_Gifts_19952026 (1)'!$A:$A,0))&"","") -> tylerluis1@gmail.com | J98: =IF($I98="","",IF(COUNTIF($I$5:$I$1461,$I98)>1,"DUPLICATE",""))
A99: 1758 | B99: Julian | C99: Chairez | D99: 46016 | E99: 52.12 | F99: Bulldog Pride Scholarship; Foundation General Operations | G99: =IF(MONTH(D99)>=7,YEAR(D99)+1,YEAR(D99)) -> 2026 | H99: =COUNTIF('AHCF_Gifts_19952026 (1)'!$A:$A,$A99) -> 1 | I99: =IFERROR(INDEX('AHCF_Gifts_19952026 (1)'!$F:$F,MATCH($A99,'AHCF_Gifts_19952026 (1)'!$A:$A,0))&"","") -> Julian.chairez805@gmail.com | J99: =IF($I99="","",IF(COUNTIF($I$5:$I$1461,$I99)>1,"DUPLICATE",""))
A100: 1759 | B100: Jose | C100: Villanueva | D100: 46016 | E100: 52.12 | F100: Bulldog Pride Scholarship; Foundation General Operations | G100: =IF(MONTH(D100)>=7,YEAR(D100)+1,YEAR(D100)) -> 2026 | H100: =COUNTIF('AHCF_Gifts_19952026 (1)'!$A:$A,$A100) -> 1 | I100: =IFERROR(INDEX('AHCF_Gifts_19952026 (1)'!$F:$F,MATCH($A100,'AHCF_Gifts_19952026 (1)'!$A:$A,0))&"","") -> Jevillanueva79@gmail.com | J100: =IF($I100="","",IF(COUNTIF($I$5:$I$1461,$I100)>1,"DUPLICATE",""))
A101: 1757 | B101: Aiden | C101: McGuire | D101: 46015 | E101: 259.38 | F101: Foundation General Operations; Foundation Restricted Clearing Fund | G101: =IF(MONTH(D101)>=7,YEAR(D101)+1,YEAR(D101)) -> 2026 | H101: =COUNTIF('AHCF_Gifts_19952026 (1)'!$A:$A,$A101) -> 1 | I101: =IFERROR(INDEX('AHCF_Gifts_19952026 (1)'!$F:$F,MATCH($A101,'AHCF_Gifts_19952026 (1)'!$A:$A,0))&"","") -> aidenkmcguire@gmail.com | J101: =IF($I101="","",IF(COUNTIF($I$5:$I$1461,$I101)>1,"DUPLICATE",""))
A102: 1754 | B102: Lisa | C102: Rotter | D102: 46014 | E102: 264.56 | F102: Foundation General Operations; Foundation Restricted Clearing Fund | G102: =IF(MONTH(D102)>=7,YEAR(D102)+1,YEAR(D102)) -> 2026 | H102: =COUNTIF('AHCF_Gifts_19952026 (1)'!$A:$A,$A102) -> 1 | I102: =IFERROR(INDEX('AHCF_Gifts_19952026 (1)'!$F:$F,MATCH($A102,'AHCF_Gifts_19952026 (1)'!$A:$A,0))&"","") -> lisamrotter@gmail.com | J102: =IF($I102="","",IF(COUNTIF($I$5:$I$1461,$I102)>1,"DUPLICATE",""))
A103: 1756 | B103: Leonard | C103: Finocchio | D103: 46014 | E103: 155.75 | F103: Foundation General Operations; Foundation Restricted Clearing Fund | G103: =IF(MONTH(D103)>=7,YEAR(D103)+1,YEAR(D103)) -> 2026 | H103: =COUNTIF('AHCF_Gifts_19952026 (1)'!$A:$A,$A103) -> 1 | I103: =IFERROR(INDEX('AHCF_Gifts_19952026 (1)'!$F:$F,MATCH($A103,'AHCF_Gifts_19952026 (1)'!$A:$A,0))&"","") -> len_finocchio@me.com | J103: =IF($I103="","",IF(COUNTIF($I$5:$I$1461,$I103)>1,"DUPLICATE",""))
A104: 1753 | B104: Rafael | C104: Valdovinos | D104: 46014 | E104: 103.94 | F104: Foundation Annual Fund Unrestricted; Foundation General Operations | G104: =IF(MONTH(D104)>=7,YEAR(D104)+1,YEAR(D104)) -> 2026 | H104: =COUNTIF('AHCF_Gifts_19952026 (1)'!$A:$A,$A104) -> 1 | I104: =IFERROR(INDEX('AHCF_Gifts_19952026 (1)'!$F:$F,MATCH($A104,'AHCF_Gifts_19952026 (1)'!$A:$A,0))&"","") -> ralphy0336@gmail.com | J104: =IF($I104="","",IF(COUNTIF($I$5:$I$1461,$I104)>1,"DUPLICATE",""))
A105: 1755 | B105: Jason | C105: Moses | D105: 46014 | E105: 37.62 | F105: Foundation General Operations; Foundation Restricted Clearing Fund | G105: =IF(MONTH(D105)>=7,YEAR(D105)+1,YEAR(D105)) -> 2026 | H105: =COUNTIF('AHCF_Gifts_19952026 (1)'!$A:$A,$A105) -> 1 | I105: =IFERROR(INDEX('AHCF_Gifts_19952026 (1)'!$F:$F,MATCH($A105,'AHCF_Gifts_19952026 (1)'!$A:$A,0))&"","") -> moses.jason@gmail.com | J105: =IF($I105="","",IF(COUNTIF($I$5:$I$1461,$I105)>1,"DUPLICATE",""))
A106: 1752 | B106: Sandhya | C106: Patel | D106: 46010 | E106: 4000 | F106: JDX Pharmacy Nursing Scholarship | G106: =IF(MONTH(D106)>=7,YEAR(D106)+1,YEAR(D106)) -> 2026 | H106: =COUNTIF('AHCF_Gifts_19952026 (1)'!$A:$A,$A106) -> 1 | I106: =IFERROR(INDEX('AHCF_Gifts_19952026 (1)'!$F:$F,MATCH($A106,'AHCF_Gifts_19952026 (1)'!$A:$A,0))&"","") -> cndesi@cs.com | J106: =IF($I106="","",IF(COUNTIF($I$5:$I$1461,$I106)>1,"DUPLICATE",""))
A107: 1751 | B107: AHC BIGE Club | D107: 46009 | E107: 400 | F107: General Scholarship | G107: =IF(MONTH(D107)>=7,YEAR(D107)+1,YEAR(D107)) -> 2026 | H107: =COUNTIF('AHCF_Gifts_19952026 (1)'!$A:$A,$A107) -> 1 | I107: =IFERROR(INDEX('AHCF_Gifts_19952026 (1)'!$F:$F,MATCH($A107,'AHCF_Gifts_19952026 (1)'!$A:$A,0))&"","") | J107: =IF($I107="","",IF(COUNTIF($I$5:$I$1461,$I107)>1,"DUPLICATE",""))
A108: 1750 | B108: Norma | C108: Flemming | D108: 46009 | E108: 180 | F108: Tim Flemming Memorial Scholarship | G108: =IF(MONTH(D108)>=7,YEAR(D108)+1,YEAR(D108)) -> 2026 | H108: =COUNTIF('AHCF_Gifts_19952026 (1)'!$A:$A,$A108) -> 1 | I108: =IFERROR(INDEX('AHCF_Gifts_19952026 (1)'!$F:$F,MATCH($A108,'AHCF_Gifts_19952026 (1)'!$A:$A,0))&"","") | J108: =IF($I108="","",IF(COUNTIF($I$5:$I$1461,$I108)>1,"DUPLICATE",""))
A109: 1749 | B109: Tim Hogan | C109: Hogan | D109: 46001 | E109: 52.12 | F109: Foundation Annual Fund Unrestricted; Foundation General Operations | G109: =IF(MONTH(D109)>=7,YEAR(D109)+1,YEAR(D109)) -> 2026 | H109: =COUNTIF('AHCF_Gifts_19952026 (1)'!$A:$A,$A109) -> 1 | I109: =IFERROR(INDEX('AHCF_Gifts_19952026 (1)'!$F:$F,MATCH($A109,'AHCF_Gifts_19952026 (1)'!$A:$A,0))&"","") -> ahogan@pcpa.org | J109: =IF($I109="","",IF(COUNTIF($I$5:$I$1461,$I109)>1,"DUPLICATE","")) -> DUPLICATE
A110: 1748 | B110: Thomas and Deborah | C110: Sherry | D110: 46000 | E110: 1000 | F110: Foster Youth Support Restricted | G110: =IF(MONTH(D110)>=7,YEAR(D110)+1,YEAR(D110)) -> 2026 | H110: =COUNTIF('AHCF_Gifts_19952026 (1)'!$A:$A,$A110) -> 1 | I110: =IFERROR(INDEX('AHCF_Gifts_19952026 (1)'!$F:$F,MATCH($A110,'AHCF_Gifts_19952026 (1)'!$A:$A,0))&"","") -> tomsherry55@hotmail.com | J110: =IF($I110="","",IF(COUNTIF($I$5:$I$1461,$I110)>1,"DUPLICATE",""))
...

Sheet Retention Calc
A1: Constituent ID | B1: 2011 | C1: 2012 | D1: 2013 | E1: 2014 | F1: 2015 | G1: 2016 | H1: 2017 | I1: 2018 | J1: 2019 | K1: 2020 | L1: 2021 | M1: 2022 | N1: 2023 | O1: 2024 | P1: 2025 | Q1: 2026 | R1: First FY (Cohort)
A2: 10 | B2: 0 | C2: 0 | D2: 0 | E2: 0 | F2: 0 | G2: 0 | H2: 0 | I2: 0 | J2: 0 | K2: 0 | L2: 1 | M2: 0 | N2: 1 | O2: 0 | P2: 0 | Q2: 0 | R2: =INDEX($B$1:$Q$1,MATCH(1,B2:Q2,0)) -> 2021
A3: 1000 | B3: 0 | C3: 0 | D3: 0 | E3: 0 | F3: 0 | G3: 0 | H3: 0 | I3: 0 | J3: 0 | K3: 0 | L3: 0 | M3: 0 | N3: 1 | O3: 1 | P3: 1 | Q3: 1 | R3: =INDEX($B$1:$Q$1,MATCH(1,B3:Q3,0)) -> 2023
A4: 1001 | B4: 0 | C4: 0 | D4: 0 | E4: 0 | F4: 0 | G4: 0 | H4: 0 | I4: 0 | J4: 0 | K4: 0 | L4: 0 | M4: 0 | N4: 1 | O4: 1 | P4: 1 | Q4: 1 | R4: =INDEX($B$1:$Q$1,MATCH(1,B4:Q4,0)) -> 2023
A5: 1002 | B5: 0 | C5: 0 | D5: 0 | E5: 0 | F5: 0 | G5: 0 | H5: 0 | I5: 0 | J5: 0 | K5: 0 | L5: 0 | M5: 0 | N5: 1 | O5: 1 | P5: 1 | Q5: 0 | R5: =INDEX($B$1:$Q$1,MATCH(1,B5:Q5,0)) -> 2023
A6: 1003 | B6: 0 | C6: 0 | D6: 0 | E6: 0 | F6: 0 | G6: 0 | H6: 0 | I6: 0 | J6: 0 | K6: 0 | L6: 0 | M6: 0 | N6: 1 | O6: 0 | P6: 0 | Q6: 0 | R6: =INDEX($B$1:$Q$1,MATCH(1,B6:Q6,0)) -> 2023
A7: 1004 | B7: 0 | C7: 0 | D7: 0 | E7: 0 | F7: 0 | G7: 0 | H7: 0 | I7: 0 | J7: 0 | K7: 0 | L7: 0 | M7: 0 | N7: 1 | O7: 1 | P7: 0 | Q7: 0 | R7: =INDEX($B$1:$Q$1,MATCH(1,B7:Q7,0)) -> 2023
A8: 101 | B8: 0 | C8: 0 | D8: 0 | E8: 0 | F8: 0 | G8: 0 | H8: 0 | I8: 0 | J8: 0 | K8: 0 | L8: 0 | M8: 0 | N8: 0 | O8: 1 | P8: 0 | Q8: 0 | R8: =INDEX($B$1:$Q$1,MATCH(1,B8:Q8,0)) -> 2024
A9: 1025 | B9: 0 | C9: 0 | D9: 0 | E9: 0 | F9: 0 | G9: 0 | H9: 0 | I9: 0 | J9: 0 | K9: 0 | L9: 0 | M9: 0 | N9: 1 | O9: 0 | P9: 0 | Q9: 0 | R9: =INDEX($B$1:$Q$1,MATCH(1,B9:Q9,0)) -> 2023
A10: 1026 | B10: 0 | C10: 0 | D10: 0 | E10: 0 | F10: 0 | G10: 0 | H10: 0 | I10: 0 | J10: 0 | K10: 0 | L10: 0 | M10: 0 | N10: 1 | O10: 0 | P10: 0 | Q10: 0 | R10: =INDEX($B$1:$Q$1,MATCH(1,B10:Q10,0)) -> 2023
A11: 1028 | B11: 0 | C11: 0 | D11: 0 | E11: 0 | F11: 0 | G11: 0 | H11: 0 | I11: 0 | J11: 0 | K11: 0 | L11: 0 | M11: 0 | N11: 1 | O11: 0 | P11: 0 | Q11: 0 | R11: =INDEX($B$1:$Q$1,MATCH(1,B11:Q11,0)) -> 2023
A12: 1029 | B12: 0 | C12: 0 | D12: 0 | E12: 0 | F12: 0 | G12: 0 | H12: 0 | I12: 0 | J12: 0 | K12: 0 | L12: 0 | M12: 0 | N12: 1 | O12: 0 | P12: 0 | Q12: 0 | R12: =INDEX($B$1:$Q$1,MATCH(1,B12:Q12,0)) -> 2023
A13: 1030 | B13: 0 | C13: 0 | D13: 0 | E13: 0 | F13: 0 | G13: 0 | H13: 0 | I13: 0 | J13: 0 | K13: 0 | L13: 0 | M13: 0 | N13: 1 | O13: 0 | P13: 0 | Q13: 0 | R13: =INDEX($B$1:$Q$1,MATCH(1,B13:Q13,0)) -> 2023
... A1033: 999 | B1033: 0 | C1033: 0 | D1033: 0 | E1033: 0 | F1033: 0 | G1033: 0 | H1033: 0 | I1033: 0 | J1033: 0 | K1033: 0 | L1033: 0 | M1033: 0 | N1033: 1 | O1033: 0 | P1033: 0 | Q1033: 0 | R1033: =INDEX($B$1:$Q$1,MATCH(1,B1033:Q1033,0)) -> 2023
A1034: B01079041 | B1034: 1 | C1034: 0 | D1034: 0 | E1034: 0 | F1034: 0 | G1034: 0 | H1034: 0 | I1034: 0 | J1034: 0 | K1034: 0 | L1034: 0 | M1034: 0 | N1034: 0 | O1034: 0 | P1034: 0 | Q1034: 0 | R1034: =INDEX($B$1:$Q$1,MATCH(1,B1034:Q1034,0)) -> 2011
A1035: B20021818 | B1035: 1 | C1035: 0 | D1035: 0 | E1035: 0 | F1035: 0 | G1035: 0 | H1035: 0 | I1035: 0 | J1035: 0 | K1035: 0 | L1035: 0 | M1035: 0 | N1035: 0 | O1035: 0 | P1035: 0 | Q1035: 0 | R1035: =INDEX($B$1:$Q$1,MATCH(1,B1035:Q1035,0)) -> 2011
A1036: H00754278 | B1036: 0 | C1036: 0 | D1036: 0 | E1036: 0 | F1036: 0 | G1036: 0 | H1036: 1 | I1036: 0 | J1036: 0 | K1036: 0 | L1036: 0 | M1036: 0 | N1036: 0 | O1036: 0 | P1036: 0 | Q1036: 0 | R1036: =INDEX($B$1:$Q$1,MATCH(1,B1036:Q1036,0)) -> 2017
A1037: H00756273 | B1037: 0 | C1037: 0 | D1037: 0 | E1037: 0 | F1037: 0 | G1037: 0 | H1037: 0 | I1037: 1 | J1037: 0 | K1037: 1 | L1037: 1 | M1037: 0 | N1037: 0 | O1037: 0 | P1037: 0 | Q1037: 0 | R1037: =INDEX($B$1:$Q$1,MATCH(1,B1037:Q1037,0)) -> 2018
A1038: H00765977 | B1038: 0 | C1038: 0 | D1038: 0 | E1038: 0 | F1038: 0 | G1038: 0 | H1038: 0 | I1038: 1 | J1038: 0 | K1038: 0 | L1038: 0 | M1038: 0 | N1038: 0 | O1038: 0 | P1038: 0 | Q1038: 0 | R1038: =INDEX($B$1:$Q$1,MATCH(1,B1038:Q1038,0)) -> 2018
A1039: H01000256 | B1039: 0 | C1039: 0 | D1039: 0 | E1039: 0 | F1039: 0 | G1039: 0 | H1039: 0 | I1039: 0 | J1039: 0 | K1039: 1 | L1039: 0 | M1039: 0 | N1039: 0 | O1039: 0 | P1039: 0 | Q1039: 0 | R1039: =INDEX($B$1:$Q$1,MATCH(1,B1039:Q1039,0)) -> 2020
A1040: H01001067 | B1040: 0 | C1040: 0 | D1040: 0 | E1040: 0 | F1040: 0 | G1040: 0 | H1040: 1 | I1040: 0 | J1040: 0 | K1040: 0 | L1040: 0 | M1040: 0 | N1040: 0 | O1040: 0 | P1040: 0 | Q1040: 0 | R1040: =INDEX($B$1:$Q$1,MATCH(1,B1040:Q1040,0)) -> 2017
A1041: H01001788 | B1041: 0 | C1041: 0 | D1041: 1 | E1041: 0 | F1041: 0 | G1041: 0 | H1041: 0 | I1041: 0 | J1041: 0 | K1041: 0 | L1041: 0 | M1041: 0 | N1041: 0 | O1041: 0 | P1041: 0 | Q1041: 0 | R1041: =INDEX($B$1:$Q$1,MATCH(1,B1041:Q1041,0)) -> 2013
A1042: H01001928 | B1042: 0 | C1042: 0 | D1042: 0 | E1042: 0 | F1042: 0 | G1042: 0 | H1042: 1 | I1042: 1 | J1042: 0 | K1042: 0 | L1042: 0 | M1042: 0 | N1042: 0 | O1042: 0 | P1042: 0 | Q1042: 0 | R1042: =INDEX($B$1:$Q$1,MATCH(1,B1042:Q1042,0)) -> 2017
A1043: H01001943 | B1043: 1 | C1043: 0 | D1043: 0 | E1043: 0 | F1043: 0 | G1043: 0 | H1043: 0 | I1043: 0 | J1043: 0 | K1043: 0 | L1043: 0 | M1043: 0 | N1043: 0 | O1043: 0 | P1043: 0 | Q1043: 0 | R1043: =INDEX($B$1:$Q$1,MATCH(1,B1043:Q1043,0)) -> 2011
A1044: H01002189 | B1044: 0 | C1044: 1 | D1044: 1 | E1044: 0 | F1044: 0 | G1044: 0 | H1044: 0 | I1044: 0 | J1044: 0 | K1044: 0 | L1044: 0 | M1044: 1 | N1044: 0 | O1044: 0 | P1044: 1 | Q1044: 0 | R1044: =INDEX($B$1:$Q$1,MATCH(1,B1044:Q1044,0)) -> 2012
A1045: H01002783 | B1045: 1 | C1045: 0 | D1045: 0 | E1045: 0 | F1045: 0 | G1045: 0 | H1045: 0 | I1045: 0 | J1045: 0 | K1045: 0 | L1045: 0 | M1045: 0 | N1045: 0 | O1045: 0 | P1045: 0 | Q1045: 0 | R1045: =INDEX($B$1:$Q$1,MATCH(1,B1045:Q1045,0)) -> 2011
... A2698: H20123197 | B2698: 0 | C2698: 0 | D2698: 0 | E2698: 0 | F2698: 0 | G2698: 0 | H2698: 0 | I2698: 0 | J2698: 0 | K2698: 1 | L2698: 1 | M2698: 0 | N2698: 0 | O2698: 0 | P2698: 0 | Q2698: 0 | R2698: =INDEX($B$1:$Q$1,MATCH(1,B2698:Q2698,0)) -> 2020

Sheet AHCF_Gifts_19952026 (1)
A1: Constituent ID | B1: Primary Salutation | C1: Last Name | D1: Gift Date | E1: Gift Amount | F1: Email Number | G1: Fund List
A2: H20020169 | B2: C.S.E.A. Chapter No. 251 | D2: 40365 | E2: 667 | G2: AHC C.S.E.A. Chapter No. 251 Scholarship
A3: H01064059 | B3: Gwinneth | C3: Howard | D3: 40371 | E3: 500 | G3: Howard Family Scholarship
A4: H01108464 | B4: Mary | C4: Harvey | D4: 40372 | E4: 1200 | F4: meditate.lompoc@gmail.com | G4: Ed Harvey Scholarship
A5: H20020197 | B5: Santa Maria Family Medicine | D5: 40375 | E5: 83.33 | G5: Allan Hancock College Foundation's President's Circle
A6: H01120472 | B6: Dean | C6: Ubben | D6: 40378 | E6: 15 | G6: Susan B. Dana Memorial Scholarship Endowment
A7: H20017967 | B7: Mechanics Bank | D7: 40380 | E7: 1000 | F7: James_Thomas@mechanicsbank.com | G7: Allan Hancock College Foundation's President's Circle
A8: H20017967 | B8: Mechanics Bank | D8: 40380 | E8: 1000 | F8: steven.harding@rabobank.com | G8: Allan Hancock College Foundation's President's Circle
A9: H10002471 | B9: José and Carmen | C9: Ortiz | D9: 40381 | E9: 1000 | F9: jortiz@hancockcollege.edu | G9: Annual President's Circle
A10: H10002471 | B10: José and Carmen | C10: Ortiz | D10: 40381 | E10: 1000 | F10: jmortiz331@gmail.com | G10: Annual President's Circle
A11: H01026881 | B11: Michael and Susan | C11: Moats | D11: 40381 | E11: 1000 | F11: mmoats1700@aol.com | G11: Allan Hancock College Foundation's President's Circle
A12: H01020121 | B12: Terry and Inda | C12: Dworaczyk | D12: 40382 | E12: 83.33 | F12: terryD350@gmail.com | G12: Allan Hancock College Foundation's President's Circle
A13: H01122036 | B13: Tim | C13: Bennett | D13: 40382 | E13: 83.33 | F13: tbennett@hancockcollege.edu | G13: Allan Hancock College Foundation's President's Circle
A14: H01122036 | B14: Tim | C14: Bennett | D14: 40382 | E14: 83.33 | F14: tabennett77@gmail.com | G14: Allan Hancock College Foundation's President's Circle
A15: H01028367 | B15: Mike and Marla | C15: Gibson | D15: 40382 | E15: 83.33 | F15: mikegibson2842@gmail.com | G15: Allan Hancock College Foundation's President's Circle
A16: H01150443 | B16: Maggi | C16: Daane | D16: 40382 | E16: 83.33 | F16: maggi.daane@gmail.com | G16: Allan Hancock College Foundation's President's Circle
A17: H01150443 | B17: Maggi | C17: Daane | D17: 40382 | E17: 83.33 | F17: maggidaane@gmail.com | G17: Allan Hancock College Foundation's President's Circle
A18: H20020501 | B18: D.E. and Carmen | C18: Regan | D18: 40382 | E18: 100 | G18: Allan Hancock College Foundation's President's Circle
A19: H20018801 | B19: John Ross Financial Services | D19: 40382 | E19: 83.33 | G19: Allan Hancock College Foundation's President's Circle
A20: H20018663 | B20: PrimusLabs.com | D20: 40385 | E20: 1000 | G20: Allan Hancock College Foundation's President's Circle
A21: H20020912 | B21: Allan Hancock College Part-Time Faculty Association | D21: 40387 | E21: 500 | G21: General Scholarship
A22: H20019312 | B22: Santa Maria Elks Lodge No. 1538 | D22: 40388 | E22: 1000 | G22: Butch Simas Elks Lodge No. 1538 Memorial Scholarship
A23: H20019312 | B23: Santa Maria Elks Lodge No. 1538 | D23: 40388 | E23: 1500 | G23: Santa Maria Elks Lodge No. 1538 Vocational Scholarships
A24: H20019312 | B24: Santa Maria Elks Lodge No. 1538 | D24: 40388 | E24: 3000 | G24: Ernest Righetti, Sr. Transfer Scholarship-SM Elks Lodge 1538
A25: H10000374 | B25: Angela | C25: Caballero de Cordero | D25: 40389 | E25: 40 | F25: acdecordero@hancockcollege.edu | G25: Allan Hancock College AB 540 Dream Fund
A26: H10000374 | B26: Angela | C26: Caballero de Cordero | D26: 40389 | E26: 40 | F26: acdecordero@hancockcollege.edu | G26: Allan Hancock College AB 540 Dream Fund
A27: H10002006 | B27: Geraldine | C27: Valdiviezo | D27: 40389 | E27: 35 | F27: gvaldiviezo@hancockcollege.edu | G27: AHC C.S.E.A. Chapter No. 251 Scholarship
A28: H10002006 | B28: Geraldine | C28: Valdiviezo | D28: 40389 | E28: 35 | F28: gvaldiviezo@hancockcollege.edu | G28: AHC C.S.E.A. Chapter No. 251 Scholarship
A29: H10002386 | B29: Joyce | C29: Dendo | D29: 40389 | E29: 10 | F29: jcole@hancockcollege.edu | G29: General Scholarship
A30: H10002386 | B30: Joyce | C30: Dendo | D30: 40389 | E30: 10 | F30: rosduch@hotmail.com | G30: General Scholarship
A31: H10002386 | B31: Joyce | C31: Dendo | D31: 40389 | E31: 5 | F31: jcole@hancockcollege.edu | G31: Allan Hancock College AB 540 Dream Fund
A32: H10002386 | B32: Joyce | C32: Dendo | D32: 40389 | E32: 5 | F32: rosduch@hotmail.com | G32: Allan Hancock College AB 540 Dream Fund
A33: H10001133 | B33: Juanita | C33: Tuan | D33: 40389 | E33: 25 | F33: jtuan@hancockcollege.edu | G33: Allan Hancock College AB 540 Dream Fund
A34: H10001133 | B34: Juanita | C34: Tuan | D34: 40389 | E34: 25 | F34: jtuan3@yahoo.com | G34: Allan Hancock College AB 540 Dream Fund
A35: H10001133 | B35: Juanita | C35: Tuan | D35: 40389 | E35: 25 | F35: jtuan3@yahoo.com | G35: Allan Hancock College AB 540 Dream Fund
A36: H10001133 | B36: Juanita | C36: Tuan | D36: 40389 | E36: 25 | F36: juanita.tuan@gmail.com | G36: Allan Hancock College AB 540 Dream Fund
... A59: H10000207 | B59: Yvonne and Augustin | C59: Teniente | D59: 40389 | E59: 40 | F59: yteniente@hancockcollege.edu | G59: Allan Hancock College AB 540 Dream Fund
A60: H20019003 | B60: Paula and Tony | C60: Sousa | D60: 40389 | E60: 7.5 | G60: Allan Hancock College AB 540 Dream Fund
A61: H20019003 | B61: Paula and Tony | C61: Sousa | D61: 40389 | E61: 7.5 | G61: Allan Hancock College EOPS Program
A62: H01045631 | B62: Toni and Mike | C62: McCracken | D62: 40389 | E62: 84 | F62: tmccracken@hancockcollege.edu | G62: Allan Hancock College Foundation's President's Circle
A63: H01045631 | B63: Toni and Mike | C63: McCracken | D63: 40389 | E63: 84 | F63: toni_mccracken@yahoo.com | G63: Allan Hancock College Foundation's President's Circle
A64: H10002100 | B64: Carol | C64: Moore | D64: 40389 | E64: 40 | F64: moorepaso@gmail.com | G64: Foundation General Operations
A65: H10002221 | B65: Jeannette | C65: Hernandez | D65: 40389 | E65: 5 | F65: jhernandez@hancockcollege.edu | G65: Allan Hancock College AB 540 Dream Fund
A66: H10002221 | B66: Jeannette | C66: Hernandez | D66: 40389 | E66: 5 | F66: jhernandez@hancockcollege.edu | G66: Allan Hancock College AB 540 Dream Fund
A67: H10002380 | B67: Rebecca and Edmund | C67: Alarcio | D67: 40389 | E67: 40 | F67: alarcior@charter.net | G67: Foundation General Operations
A68: H10002380 | B68: Rebecca and Edmund | C68: Alarcio | D68: 40389 | E68: 15 | F68: alarcior@charter.net | G68: Allan Hancock College Public Affairs Projects
A69: H10000560 | B69: Mayra | C69: Morales | D69: 40389 | E69: 25 | F69: mmorales@hancockcollege.edu | G69: Allan Hancock College AB 540 Dream Fund
A70: H10000560 | B70: Mayra | C70: Morales | D70: 40389 | E70: 25 | F70: mmorales9505@gmail.com | G70: Allan Hancock College AB 540 Dream Fund
A71: H10002365 | B71: Odette | C71: Pinheiro | D71: 40389 | E71: 10 | F71: opinheiro65@gmail.com | G71: AHC Student Emergency Fund
A72: H10002365 | B72: Odette | C72: Pinheiro | D72: 40389 | E72: 10 | F72: opinheiro@hancockcollege.edu | G72: AHC Student Emergency Fund
A73: H10000332 | B73: Margaret | C73: Tillery | D73: 40389 | E73: 10 | F73: mtillery49@gmail.com | G73: Foundation General Operations
A74: H10002234 | B74: Christina | C74: Koob | D74: 40389 | E74: 5 | F74: ckoob@hancockcollege.edu | G74: AHC LRC - Jim Morrow Book Fund
A75: H20019283 | B75: Santa Maria-Lompoc Calif. Retired Teachers Assn. | D75: 40391 | E75: 925 | F75: evelynwright@verizon.net | G75: Future Teachers Scholarship, SM-LO CA Retired Teachers Assn
A76: H01026881 | B76: Michael and Susan | C76: Moats | D76: 40392 | E76: 2000 | F76: mmoats1700@aol.com | G76: Moats Family Scholarship
A77: H01040146 | B77: Henry | C77: Grennan | D77: 40395 | E77: 150 | F77: hmgrennan@hotmail.com | G77: Grennan Family Scholarship
A78: H01040146 | B78: Henry | C78: Grennan | D78: 40395 | E78: 100 | F78: hmgrennan@hotmail.com | G78: Allan Hancock College Foundation's President's Circle
A79: H20020674 | B79: Santa Maria Central Coast Soccer | D79: 40395 | E79: 5900 | G79: Allan Hancock College EOPS Program
A80: H10000916 | B80: Mario and Linda | C80: Juarez | D80: 40396 | E80: 2500 | F80: mjuarez@smvlaw.com | G80: Annual President's Circle
A81: H20019837 | B81: Norma | C81: Hansen | D81: 40397 | E81: 20000 | G81: Hansen Engineering Scholarship Endowment
A82: H20019141 | B82: Mark | C82: Smith | D82: 40399 | E82: 30000 | G82: Annual President's Circle
A83: H20021613 | B83: Sally | C83: Haynes | D83: 40400 | E83: 1000 | G83: RE7 Conversion Fund
A84: H01730790 | B84: Franziska | C84: Shepard | D84: 40401 | E84: 1000 | F84: theshepardinc@gmail.com | G84: Allan Hancock College Foundation's President's Circle
A85: H01139713 | B85: Kate and Arlan | C85: Ferguson | D85: 40402 | E85: 1000 | F85: just_kate@live.com | G85: Annual President's Circle
A86: H20020197 | B86: Santa Maria Family Medicine | D86: 40403 | E86: 83.33 | G86: Allan Hancock College Foundation's President's Circle
A87: H20021626 | B87: Gloria | C87: Gariglio | D87: 40405 | E87: 50 | G87: RE7 Conversion Fund
A88: H01122036 | B88: Tim | C88: Bennett | D88: 40406 | E88: 83.33 | F88: tbennett@hancockcollege.edu | G88: Allan Hancock College Foundation's President's Circle
A89: H01122036 | B89: Tim | C89: Bennett | D89: 40406 | E89: 83.33 | F89: tabennett77@gmail.com | G89: Allan Hancock College Foundation's President's Circle
A90: H01028367 | B90: Mike and Marla | C90: Gibson | D90: 40406 | E90: 0.08 | F90: mikegibson2842@gmail.com | G90: Allan Hancock College Foundation's President's Circle
A91: H01028367 | B91: Mike and Marla | C91: Gibson | D91: 40406 | E91: 83.25 | F91: mikegibson2842@gmail.com | G91: Allan Hancock College Foundation's President's Circle
A92: H01020121 | B92: Terry and Inda | C92: Dworaczyk | D92: 40406 | E92: 83.33 | F92: terryD350@gmail.com | G92: Allan Hancock College Foundation's President's Circle
A93: H01150443 | B93: Maggi | C93: Daane | D93: 40406 | E93: 83.33 | F93: maggi.daane@gmail.com | G93: Allan Hancock College Foundation's President's Circle
A94: H01150443 | B94: Maggi | C94: Daane | D94: 40406 | E94: 83.33 | F94: maggidaane@gmail.com | G94: Allan Hancock College Foundation's President's Circle
A95: H20020501 | B95: D.E. and Carmen | C95: Regan | D95: 40406 | E95: 100 | G95: Allan Hancock College Foundation's President's Circle
A96: H20018801 | B96: John Ross Financial Services | D96: 40406 | E96: 83.33 | G96: Allan Hancock College Foundation's President's Circle
A97: H01092001 | B97: Judy | C97: Frost | D97: 40407 | E97: 1500 | F97: enjfrost@aol.com | G97: Annual President's Circle
A98: H01042168 | B98: Greg and Jackie | C98: Pensa | D98: 40407 | E98: 1000 | F98: gpensa@silcom.com | G98: Allan Hancock College Foundation's President's Circle
A99: H20021211 | B99: Foundation for California Community Colleges | D99: 40408 | E99: 5000 | G99: Osher Scholarship
A100: H20019023 | B100: The Law Firm of Brenneman, Juarez, & Adam, LLP | D100: 40415 | E100: 2500 | F100: mjuarez@bjalaw.net | G100: Annual President's Circle
A101: H10002736 | B101: Jeff and Patti | C101: Cotter | D101: 40415 | E101: 15 | F101: jeffrey.cotter@hancockcollege.edu | G101: Foundation General Operations
A102: H10002736 | B102: Jeff and Patti | C102: Cotter | D102: 40415 | E102: 15 | F102: jeffcotter@impulse.net | G102: Foundation General Operations
A103: H01108464 | B103: Mary | C103: Harvey | D103: 40415 | E103: 1 | F103: meditate.lompoc@gmail.com | G103: Foundation General Operations
A104: H20019141 | B104: Mark | C104: Smith | D104: 40416 | E104: 5000 | G104: Dorothy and Mark J. Smith Scholarship
A105: H20019141 | B105: Mark | C105: Smith | D105: 40416 | E105: 5000 | G105: Annual President's Circle
A106: H01042168 | B106: Greg and Jackie | C106: Pensa | D106: 40416 | E106: 10 | F106: gpensa@silcom.com | G106: Foundation General Operations
A107: H10002380 | B107: Rebecca and Edmund | C107: Alarcio | D107: 40421 | E107: 40 | F107: alarcior@charter.net | G107: Foundation General Operations
A108: H10002380 | B108: Rebecca and Edmund | C108: Alarcio | D108: 40421 | E108: 15 | F108: alarcior@charter.net | G108: Allan Hancock College Public Affairs Projects
A109: H10002221 | B109: Jeannette | C109: Hernandez | D109: 40421 | E109: 5 | F109: jhernandez@hancockcollege.edu | G109: Allan Hancock College AB 540 Dream Fund
A110: H10002221 | B110: Jeannette | C110: Hernandez | D110: 40421 | E110: 5 | F110: jhernandez@hancockcollege.edu | G110: Allan Hancock College AB 540 Dream Fund
A111: H10002100 | B111: Carol | C111: Moore | D111: 40421 | E111: 40 | F111: moorepaso@gmail.com | G111: Foundation General Operations
A112: H01045631 | B112: Toni and Mike | C112: McCracken | D112: 40421 | E112: 84 | F112: tmccracken@hancockcollege.edu | G112: Allan Hancock College Foundation's President's Circle
A113: H01045631 | B113: Toni and Mike | C113: McCracken | D113: 40421 | E113: 84 | F113: toni_mccracken@yahoo.com | G113: Allan Hancock College Foundation's President's Circle
A114: H20019003 | B114: Paula and Tony | C114: Sousa | D114: 40421 | E114: 7.5 | G114: Allan Hancock College AB 540 Dream Fund
A115: H20019003 | B115: Paula and Tony | C115: Sousa | D115: 40421 | E115: 7.5 | G115: Allan Hancock College EOPS Program
A116: H10000438 | B116: Linda | C116: Metaxas | D116: 40421 | E116: 300 | F116: lmetaxas@hancockcollege.edu | G116: Daniel Metaxas and Donald Tinker Memorial Scholarships
A117: H10000438 | B117: Linda | C117: Metaxas | D117: 40421 | E117: 300 | F117: lmetaxas@gmail.com | G117: Daniel Metaxas and Donald Tinker Memorial Scholarships
A118: H10002365 | B118: Odette | C118: Pinheiro | D118: 40421 | E118: 10 | F118: opinheiro65@gmail.com | G118: AHC Student Emergency Fund
A119: H10002365 | B119: Odette | C119: Pinheiro | D119: 40421 | E119: 10 | F119: opinheiro@hancockcollege.edu | G119: AHC Student Emergency Fund
A120: H10000560 | B120: Mayra | C120: Morales | D120: 40421 | E120: 25 | F120: mmorales@hancockcollege.edu | G120: Allan Hancock College AB 540 Dream Fund
A121: H10000560 | B121: Mayra | C121: Morales | D121: 40421 | E121: 25 | F121: mmorales9505@gmail.com | G121: Allan Hancock College AB 540 Dream Fund
A122: H10000332 | B122: Margaret | C122: Tillery | D122: 40421 | E122: 10 | F122: mtillery49@gmail.com | G122: Foundation General Operations
...

Sheet Duplicates to Review
A1: Duplicate Email Review — One-Time Donors
A2: 8 emails shared across 17 one-time-donor records. Same-surname groups are likely duplicate records to merge in the CRM.
A4: Email | B4: Constituent ID | C4: Salutation | D4: Last Name | E4: Gift Date | F4: Gift Amount | G4: Fiscal Year | H4: Classification | I4: Src Row
A5: ahogan@pcpa.org | B5: 1749 | C5: Tim Hogan | D5: Hogan | E5: 46001 | F5: 52.12 | G5: 2026 | H5: Likely duplicate record — review/merge | I5: 109
A6: ahogan@pcpa.org | B6: 517 | C6: Abigail and Tim | D6: Hogan | E6: 45964 | F6: 103.94 | G6: 2026 | H6: Likely duplicate record — review/merge | I6: 124
A7: ed7murray@gmail.com | B7: 243 | C7: Lisa | D7: Murray | E7: 44196 | F7: 100 | G7: 2021 | H7: Likely duplicate record — review/merge | I7: 600
A8: ed7murray@gmail.com | B8: H20019108 | C8: Edward and Lisa | D8: Murray | E8: 40518 | F8: 1000 | G8: 2011 | H8: Likely duplicate record — review/merge | I8: 1408
A9: mission.hills.school.ca@gmail.com | B9: 1527 | C9: Betty | D9: Pierce | E9: 45679 | F9: 25 | G9: 2025 | H9: Likely duplicate record — review/merge | I9: 219
A10: mission.hills.school.ca@gmail.com | B10: 1528 | C10: Katrina | D10: Pierce | E10: 45679 | F10: 25 | G10: 2025 | H10: Likely duplicate record — review/merge | I10: 220
A11: wedmore2@comcast.net | B11: H01670074 | C11: James and Vicki | D11: Wedmore | E11: 42006 | F11: 50 | G11: 2015 | H11: Likely duplicate record — review/merge | I11: 1179
A12: wedmore2@comcast.net | B12: H01723646 | C12: Vicki and James | D12: Wedmore | E12: 41211 | F12: 100 | G12: 2013 | H12: Likely duplicate record — review/merge | I12: 1301
A13: cmbchivitas@yahoo.com | B13: 1558 | C13: Luis | D13: Miranda | E13: 45694 | F13: 40 | G13: 2025 | H13: Shared household/org email | I13: 203
A14: cmbchivitas@yahoo.com | B14: 1533 | C14: Claudia | D14: Miranda | E14: 45682 | F14: 100 | G14: 2025 | H14: Shared household/org email | I14: 215
A15: cmbchivitas@yahoo.com | B15: 1534 | C15: Carlos | D15: Bojorquez | E15: 45682 | F15: 100 | G15: 2025 | H15: Shared household/org email | I15: 216
A16: hello@better2getherevents.com | B16: 1679 | C16: Jenna | D16: Nichols | E16: 45905 | F16: 100 | G16: 2026 | H16: Shared household/org email | I16: 141
A17: hello@better2getherevents.com | B17: 1434 | C17: Better2gether Events | D17: Events | E17: 45541 | F17: 100 | G17: 2025 | H17: Shared household/org email | I17: 264
A18: jdeming@bgcsmv.org | B18: H20103240 | C18: Jeremy | D18: Deming | E18: 43214 | F18: 250 | G18: 2018 | H18: Shared household/org email | I18: 850
A19: jdeming@bgcsmv.org | B19: H20082844 | C19: Boys & Girls Clubs of Santa Maria Valley | E19: 42681 | F19: 1000 | G19: 2017 | H19: Shared household/org email | I19: 1012
A20: trcbrl@gmail.com | B20: H20070049 | C20: Katherine | D20: Reynolds | E20: 42318 | F20: 100 | G20: 2016 | H20: Shared household/org email | I20: 1085
A21: trcbrl@gmail.com | B21: H20070048 | C21: Patricia | D21: Cabral | E21: 42318 | F21: 100 | G21: 2016 | H21: Shared household/org email | I21: 1086
